Workbook
Name BANCOS: Tabla4[BANCOS]
Name CLIENTES: Tabla3[CLIENTES]
Name DOLARES: Tabla12[#All]
Name EMISOR2: Tabla12[[#All],[EMISOR2]]
Name GASTOS: GASTOS2[GASTOS]
Name ORIGEN: Tabla2[ORIGEN]
Name OTROS: #REF!
Name PLATAFORMAS: Tabla10[PLATAFORMAS]
Name RECEPTOR: BOLIVARES!#REF!

Sheet DOLARES
B2: FECHA | C2: ORIGEN2 | D2: EMISOR2 | E2: MONEDA | F2: MONTO | G2: DESTINO | H2: RECEPTOR | I2: MONTO2 | J2: REMITENTE | K2: RECEPTOR2 | M2: VERIFICADOR DE USD
B3: 46218 | C3: PLATAFORMAS | D3: CASH BELKIS | E3: CASH | F3: 1000 | G3: CLIENTES | H3: SARAH ALVAREZ | I3: =Tabla12[[#This Row],[MONTO]] -> 1000 | M3: USD RECIBIDO | N3: =SUMIF(Tabla12[ORIGEN2],LISTAS!B4,Tabla12[MONTO]) -> 900 | O3: =SUM(Tabla14[PAGO]) -> 900 | P3: =N3-O3 -> 0
B4: 46218 | C4: CLIENTES | D4: SARAH ALVAREZ | E4: EUR | F4: 900 | G4: CLIENTES | H4: EVELIO RAMIREZ | I4: =Tabla12[[#This Row],[MONTO]] -> 900 | M4: USD PAGADO | N4: =SUMIFS(Tabla12[MONTO],Tabla12[ORIGEN2],LISTAS!B5,Tabla12[DESTINO],Tabla2[[#This Row],[ORIGEN]]) -> 1000 | O4: =SUM(Tabla14[RETIRO]) -> 1900 | P4: =(N4+N5)-O4 -> 0
I5: =Tabla12[[#This Row],[MONTO]] -> 0 | M5: USD PAGADO CLIENTES | N5: =SUMIFS(Tabla12[MONTO],Tabla12[ORIGEN2],LISTAS!B4,Tabla12[DESTINO],LISTAS!B4) -> 900
I6: =Tabla12[[#This Row],[MONTO]] -> 0
I7: =Tabla12[[#This Row],[MONTO]] -> 0
I8: =Tabla12[[#This Row],[MONTO]] -> 0 | M8: VERIFICADOR DE PLATAFORMAS
I9: =Tabla12[[#This Row],[MONTO]] -> 0 | M9: INGRESOS | N9: =SUMIF(Tabla12[DESTINO],LISTAS!B5,Tabla12[MONTO2]) -> 0 | O9: =Tabla17[[#Totals],[INGRESOS]] -> 0 | P9: =N9-O9 -> 0
I10: =Tabla12[[#This Row],[MONTO]] -> 0 | M10: EGRESOS | N10: =SUMIF(Tabla12[ORIGEN2],LISTAS!B5,Tabla12[MONTO]) -> 1000 | O10: =Tabla17[[#Totals],[EGRESOS]] -> 0 | P10: =N10-O10 -> 1000
I11: =Tabla12[[#This Row],[MONTO]] -> 0
I12: =Tabla12[[#This Row],[MONTO]] -> 0
I13: =Tabla12[[#This Row],[MONTO]] -> 0
I14: =Tabla12[[#This Row],[MONTO]] -> 0

Sheet BOLIVARES
B2: FECHA | C2: ORIGEN | D2: EMISOR | E2: MONEDA | F2: DOLARES | G2: TASA | H2: BOLIVARES1 | I2: COMISION | J2: REF | K2: DESTINO | L2: RECEPTOR | M2: MONEDA2 | N2: DOLARES2 | O2: TASA2 | P2: BOLIVARES2 | Q2: DESCRIPCION | R2: GANANCIA DIRECTA | T2: VERIFICADOR DE USD X BOLIVARES | Y2: DISTRIBUCION DE LOS INGRESOS | AB2: MOVIMIENTOS INTERNOS
B3: 46041 | C3: BANCOS | D3: VZLA JOHA | E3: BS | F3: =IFERROR(BOLIVARES[[#This Row],[BOLIVARES1]]/BOLIVARES[[#This Row],[TASA]],0) -> 0 | H3: 19500 | J3: 5271 | K3: CLIENTES | L3: EVELIO RAMIREZ | M3: CASH | N3: =IFERROR(BOLIVARES[[#This Row],[BOLIVARES2]]/BOLIVARES[[#This Row],[TASA2]],0) -> 50 | O3: 390 | P3: =BOLIVARES[[#This Row],[BOLIVARES1]] -> 19500 | R3: =IF(AND(C3="CLIENTES",K3="CLIENTES"),N3-F3,0) -> 0 | T3: VENDIDO | U3: =SUMIF(BOLIVARES[ORIGEN],LISTAS!B4,BOLIVARES[DOLARES]) -> 0 | V3: =SUM(Tabla14[COMPRA]) -> 0 | W3: =U3-V3 -> 0 | Y3: INGRESOS POR VENTAS | Z3: =SUMIFS(BOLIVARES[BOLIVARES1],BOLIVARES[ORIGEN],LISTAS!B4,BOLIVARES[DESTINO],LISTAS!B3) -> 100000 | AB3: =SUMIFS(BOLIVARES[BOLIVARES1],BOLIVARES[ORIGEN],LISTAS!B3,BOLIVARES[DESTINO],LISTAS!B3) -> 0
B4: 46041 | C4: BANCOS | D4: VZLA JOHA | E4: BS | H4: 31200 | J4: 8505 | K4: CLIENTES | L4: EVELIO RAMIREZ | M4: CASH | N4: =IFERROR(BOLIVARES[[#This Row],[BOLIVARES2]]/BOLIVARES[[#This Row],[TASA2]],0) -> 80 | O4: 390 | P4: =BOLIVARES[[#This Row],[BOLIVARES1]] -> 31200 | R4: =IF(AND(C4="CLIENTES",K4="CLIENTES"),N4-F4,0) -> 0 | T4: COMPRADO | U4: =SUMIF(BOLIVARES[DESTINO],DESTINO[[#This Row],[DESTINO]],BOLIVARES[DOLARES2]) -> 455 | V4: =SUM(Tabla14[VENTA]) -> 455 | W4: =U4-V4 -> 0 | Y4: INGRESOS PARA PAGO DE GASTOS | Z4: =SUMIFS(BOLIVARES[BOLIVARES1],BOLIVARES[ORIGEN],LISTAS!B4,BOLIVARES[DESTINO],LISTAS!J5) -> 0
B5: 46041 | C5: BANCOS | D5: MERC KAR | E5: BS | H5: 80000 | J5: 9530 | K5: CLIENTES | L5: KAROL MALDONADO | M5: PANAMA | N5: =IFERROR(BOLIVARES[[#This Row],[BOLIVARES2]]/BOLIVARES[[#This Row],[TASA2]],0) -> 200 | O5: 400 | P5: =BOLIVARES[[#This Row],[BOLIVARES1]] -> 80000 | R5: =IF(AND(C5="CLIENTES",K5="CLIENTES"),N5-F5,0) -> 0 | Y5: INGRESOS POR PAGO DE INTERESES | Z5: =SUMIF(BOLIVARES[EMISOR],LISTAS!F36,BOLIVARES[BOLIVARES1]) -> 0
B6: 46041 | C6: CLIENTES | D6: KAROL MALDONADO | E6: BS | G6: 500 | H6: 100000 | J6: 9645 | K6: BANCOS | L6: BAN JOH | N6: =IFERROR(BOLIVARES[[#This Row],[BOLIVARES2]]/BOLIVARES[[#This Row],[TASA2]],0) -> 0 | P6: =BOLIVARES[[#This Row],[BOLIVARES1]] -> 100000 | T6: VERIFICADOR DE BOLIVARES EN BANCOS
B7: 46041 | C7: CLIENTES | D7: KAROL MALDONADO | E7: BS | G7: 500 | H7: 50000 | J7: 9874 | K7: CLIENTES | L7: SARAH ALVAREZ | M7: CASH | N7: =IFERROR(BOLIVARES[[#This Row],[BOLIVARES2]]/BOLIVARES[[#This Row],[TASA2]],0) -> 125 | O7: 400 | P7: =BOLIVARES[[#This Row],[BOLIVARES1]] -> 50000 | T7: RECIBIDOS EN BANCOS | U7: =SUM(Tabla16[INGRESO])-AB3 -> 100000 | V7: =Z3 -> 100000 | W7: =U7-V7 -> 0 | Y7: DISTRIBUCION DE LOS EGRESOS
I8: =BOLIVARES[[#This Row],[BOLIVARES1]]*0.003 -> 0 | N8: =IFERROR(BOLIVARES[[#This Row],[BOLIVARES2]]/BOLIVARES[[#This Row],[TASA2]],0) -> 0 | P8: =BOLIVARES[[#This Row],[BOLIVARES1]] -> 0 | T8: ENVIADO DESDE BANCOS | U8: =SUM(Tabla16[EGRESO])-AB3 -> 130700 | V8: =SUM(Z8:Z10)-Z4 -> 130700 | W8: =U8-V8 -> 0 | Y8: EGRESOS POR COMPRAS | Z8: =SUMIFS(BOLIVARES[BOLIVARES1],BOLIVARES[ORIGEN],LISTAS!B3,BOLIVARES[DESTINO],LISTAS!B4) -> 130700
I9: =BOLIVARES[[#This Row],[BOLIVARES1]]*0.003 -> 0 | N9: =IFERROR(BOLIVARES[[#This Row],[BOLIVARES2]]/BOLIVARES[[#This Row],[TASA2]],0) -> 0 | P9: =BOLIVARES[[#This Row],[BOLIVARES1]] -> 0 | Y9: EGRESOS POR GASTOS | Z9: =SUM(Z13:Z20) -> 0
I10: =BOLIVARES[[#This Row],[BOLIVARES1]]*0.003 -> 0 | N10: =IFERROR(BOLIVARES[[#This Row],[BOLIVARES2]]/BOLIVARES[[#This Row],[TASA2]],0) -> 0 | P10: =BOLIVARES[[#This Row],[BOLIVARES1]] -> 0 | T10: COMPRAS DIRECTAS | Y10: COMISIONES POR PAGO MOVIL | Z10: =SUMIF(BOLIVARES[ORIGEN],LISTAS!B3,BOLIVARES[COMISION]) -> 0
I11: =BOLIVARES[[#This Row],[BOLIVARES1]]*0.003 -> 0 | N11: =IFERROR(BOLIVARES[[#This Row],[BOLIVARES2]]/BOLIVARES[[#This Row],[TASA2]],0) -> 0 | P11: =BOLIVARES[[#This Row],[BOLIVARES1]] -> 0 | T11: ENVIOS BS DE CLIENTES A CLIENTES | U11: =SUMIFS(BOLIVARES[BOLIVARES1],BOLIVARES[ORIGEN],LISTAS!B4,BOLIVARES[DESTINO],LISTAS!B4) -> 50000 | V11: =SUM(BOLIVARES[BOLIVARES1])+SUM(BOLIVARES[COMISION])-Z3-AB3-V8-Z4 -> 50000 | W11: =U11-V11 -> 0
I12: =BOLIVARES[[#This Row],[BOLIVARES1]]*0.003 -> 0 | N12: =IFERROR(BOLIVARES[[#This Row],[BOLIVARES2]]/BOLIVARES[[#This Row],[TASA2]],0) -> 0 | P12: =BOLIVARES[[#This Row],[BOLIVARES1]] -> 0 | Y12: DISTRIBUCION DE LOS GASTOS | Z12: BS | AA12: USD | AC12: CONTRATACION DE SERVICIOS | AD12: BS | AE12: USD
I13: =BOLIVARES[[#This Row],[BOLIVARES1]]*0.003 -> 0 | N13: =IFERROR(BOLIVARES[[#This Row],[BOLIVARES2]]/BOLIVARES[[#This Row],[TASA2]],0) -> 0 | P13: =BOLIVARES[[#This Row],[BOLIVARES1]] -> 0 | T13: VERIFICADOR DE BOLIVARES TOTALES | Y13: NOMINA | Z13: =SUM(Z25:Z29) -> 0 | AA13: =SUM(AA25:AA29) -> 0 | AC13: CARRERAS | AD13: =SUMIF(BOLIVARES[RECEPTOR],LISTAS!L14,BOLIVARES[BOLIVARES2]) -> 0 | AE13: =SUMIF(Tabla12[RECEPTOR],LISTAS!L14,Tabla12[MONTO2]) -> 0
I14: =BOLIVARES[[#This Row],[BOLIVARES1]]*0.003 -> 0 | N14: =IFERROR(BOLIVARES[[#This Row],[BOLIVARES2]]/BOLIVARES[[#This Row],[TASA2]],0) -> 0 | P14: =BOLIVARES[[#This Row],[BOLIVARES1]] -> 0 | T14: TOTAL INGRESOS | U14: =SUMIF(BOLIVARES[ORIGEN],LISTAS!B4,BOLIVARES[BOLIVARES1]) -> 150000 | V14: =SUMIF(BOLIVARES[ORIGEN],LISTAS!B4,BOLIVARES[DOLARES]) -> 0 | W14: =SUMPRODUCT(BOLIVARES[DOLARES],BOLIVARES[TASA]) -> 0 | Y14: COMISIONES | Z14: =SUM(Z32:Z38)+SUM(AB32:AB38) -> 0
I15: =BOLIVARES[[#This Row],[BOLIVARES1]]*0.003 -> 0 | N15: =IFERROR(BOLIVARES[[#This Row],[BOLIVARES2]]/BOLIVARES[[#This Row],[TASA2]],0) -> 0 | P15: =BOLIVARES[[#This Row],[BOLIVARES1]] -> 0 | T15: TOTAL EGRESOS | U15: =SUMIF(BOLIVARES[DESTINO],LISTAS!B4,BOLIVARES[BOLIVARES2]) -> 180700 | V15: =SUMIF(BOLIVARES[DESTINO],LISTAS!B4,BOLIVARES[DOLARES2]) -> 455 | W15: =SUM(BOLIVARES[DOLARES]) -> 0 | Y15: CONTRATACION DE SERVICIOS | Z15: =AD13 -> 0
I16: =BOLIVARES[[#This Row],[BOLIVARES1]]*0.003 -> 0 | N16: =IFERROR(BOLIVARES[[#This Row],[BOLIVARES2]]/BOLIVARES[[#This Row],[TASA2]],0) -> 0 | P16: =BOLIVARES[[#This Row],[BOLIVARES1]] -> 0 | V16: =V15-V14 -> 455 | Y16: OPERATIVOS | Z16: =SUMIF(BOLIVARES[RECEPTOR],LISTAS!L13,BOLIVARES[BOLIVARES2]) -> 0
I17: =BOLIVARES[[#This Row],[BOLIVARES1]]*0.003 -> 0 | N17: =IFERROR(BOLIVARES[[#This Row],[BOLIVARES2]]/BOLIVARES[[#This Row],[TASA2]],0) -> 0 | P17: =BOLIVARES[[#This Row],[BOLIVARES1]] -> 0 | T17: REMANENTE | U17: =(U14+U19)-U15-U21-U20 -> 5240910.6 | V17: =U17/U46 -> #DIV/0! | W17: =V17+V16 -> #DIV/0! | Y17: IMPUESTOS | Z17: =SUMIF(BOLIVARES[RECEPTOR],LISTAS!L15,BOLIVARES[BOLIVARES2]) -> 0
I18: =BOLIVARES[[#This Row],[BOLIVARES1]]*0.003 -> 0 | N18: =IFERROR(BOLIVARES[[#This Row],[BOLIVARES2]]/BOLIVARES[[#This Row],[TASA2]],0) -> 0 | P18: =BOLIVARES[[#This Row],[BOLIVARES1]] -> 0 | Y18: PERDIDA | Z18: =SUMIF(BOLIVARES[RECEPTOR],LISTAS!L16,BOLIVARES[BOLIVARES2]) -> 0
I19: =BOLIVARES[[#This Row],[BOLIVARES1]]*0.003 -> 0 | N19: =IFERROR(BOLIVARES[[#This Row],[BOLIVARES2]]/BOLIVARES[[#This Row],[TASA2]],0) -> 0 | P19: =BOLIVARES[[#This Row],[BOLIVARES1]] -> 0 | T19: ACUMULADO | U19: =Tabla16[[#Totals],[ACUMULADO]] -> 5271610.6 | V19: =U19/420 -> 12551.454 | Y19: OTROS | Z19: =SUMIF(BOLIVARES[RECEPTOR],LISTAS!L17,BOLIVARES[BOLIVARES2]) -> 0
I20: =BOLIVARES[[#This Row],[BOLIVARES1]]*0.003 -> 0 | N20: =IFERROR(BOLIVARES[[#This Row],[BOLIVARES2]]/BOLIVARES[[#This Row],[TASA2]],0) -> 0 | P20: =BOLIVARES[[#This Row],[BOLIVARES1]] -> 0 | T20: GASTOS OPERATIVOS | U20: =SUMIF(BOLIVARES[DESTINO],LISTAS!J5,BOLIVARES[BOLIVARES2]) -> 0 | V20: =SUMIF(BOLIVARES[DESTINO],LISTAS!J5,BOLIVARES[DOLARES2]) -> 0 | Y20: REMODELACION | Z20: =SUMIF(BOLIVARES[RECEPTOR],LISTAS!L22,BOLIVARES[BOLIVARES2]) -> 0
I21: =BOLIVARES[[#This Row],[BOLIVARES1]]*0.003 -> 0 | N21: =IFERROR(BOLIVARES[[#This Row],[BOLIVARES2]]/BOLIVARES[[#This Row],[TASA2]],0) -> 0 | P21: =BOLIVARES[[#This Row],[BOLIVARES1]] -> 0 | T21: COMISIONES POR PM | U21: =+SUM(BOLIVARES[COMISION]) -> 0 | V21: =W16/U21 -> #DIV/0!
I22: =BOLIVARES[[#This Row],[BOLIVARES1]]*0.003 -> 0 | N22: =IFERROR(BOLIVARES[[#This Row],[BOLIVARES2]]/BOLIVARES[[#This Row],[TASA2]],0) -> 0 | P22: =BOLIVARES[[#This Row],[BOLIVARES1]] -> 0
I23: =BOLIVARES[[#This Row],[BOLIVARES1]]*0.003 -> 0 | N23: =IFERROR(BOLIVARES[[#This Row],[BOLIVARES2]]/BOLIVARES[[#This Row],[TASA2]],0) -> 0 | P23: =BOLIVARES[[#This Row],[BOLIVARES1]] -> 0 | T23: COMPRAS C2C | U23: =SUM(BOLIVARES[GANANCIA DIRECTA]) -> 0 | V23: =U23+U24 -> #DIV/0!
I24: =BOLIVARES[[#This Row],[BOLIVARES1]]*0.003 -> 0 | N24: =IFERROR(BOLIVARES[[#This Row],[BOLIVARES2]]/BOLIVARES[[#This Row],[TASA2]],0) -> 0 | P24: =BOLIVARES[[#This Row],[BOLIVARES1]] -> 0 | T24: COMPRAS N2C | U24: =W17 -> #DIV/0! | Y24: DISTRIBUCION DE LA NOMINA | Z24: BS | AA24: USD
I25: =BOLIVARES[[#This Row],[BOLIVARES1]]*0.003 -> 0 | N25: =IFERROR(BOLIVARES[[#This Row],[BOLIVARES2]]/BOLIVARES[[#This Row],[TASA2]],0) -> 0 | P25: =BOLIVARES[[#This Row],[BOLIVARES1]] -> 0 | Y25: KAROL MALDONADO | Z25: =SUMIF(BOLIVARES[RECEPTOR],LISTAS!L3,BOLIVARES[BOLIVARES2]) -> 0 | AA25: =SUMIF(Tabla12[RECEPTOR],LISTAS!L3,Tabla12[MONTO2]) -> 0
I26: =BOLIVARES[[#This Row],[BOLIVARES1]]*0.003 -> 0 | N26: =IFERROR(BOLIVARES[[#This Row],[BOLIVARES2]]/BOLIVARES[[#This Row],[TASA2]],0) -> 0 | P26: =BOLIVARES[[#This Row],[BOLIVARES1]] -> 0 | T26: VENTA A CUENTAS | U26: =SUMIFS(BOLIVARES[BOLIVARES1],BOLIVARES[ORIGEN],LISTAS!B4,BOLIVARES[DESTINO],LISTAS!B3) -> 100000 | V26: =U26+Tabla16[[#Totals],[ACUMULADO]] -> 5371610.6 | Y26: MIGUEL RAMONES | Z26: =SUMIF(BOLIVARES[RECEPTOR],LISTAS!L4,BOLIVARES[BOLIVARES2]) -> 0 | AA26: =SUMIF(Tabla12[RECEPTOR],LISTAS!L4,Tabla12[MONTO2]) -> 0
I27: =BOLIVARES[[#This Row],[BOLIVARES1]]*0.003 -> 0 | N27: =IFERROR(BOLIVARES[[#This Row],[BOLIVARES2]]/BOLIVARES[[#This Row],[TASA2]],0) -> 0 | P27: =BOLIVARES[[#This Row],[BOLIVARES1]] -> 0 | T27: DOLARES VENDIDOS PARA TRABAJAR | U27: =SUMIFS(BOLIVARES[DOLARES],BOLIVARES[ORIGEN],LISTAS!B4,BOLIVARES[DESTINO],LISTAS!B3) -> 0 | V27: =(Tabla16[[#Totals],[ACUMULADO]]/420)+BOLIVARES!U27 -> 12551.454 | Y27: SARAH ALVAREZ | Z27: =SUMIF(BOLIVARES[RECEPTOR],LISTAS!L5,BOLIVARES[BOLIVARES2]) -> 0 | AA27: =SUMIF(Tabla12[RECEPTOR],LISTAS!L5,Tabla12[MONTO2]) -> 0
I28: =BOLIVARES[[#This Row],[BOLIVARES1]]*0.003 -> 0 | N28: =IFERROR(BOLIVARES[[#This Row],[BOLIVARES2]]/BOLIVARES[[#This Row],[TASA2]],0) -> 0 | P28: =BOLIVARES[[#This Row],[BOLIVARES1]] -> 0 | T28: USD COMPRADOS | U28: =SUMIFS(BOLIVARES[DOLARES2],BOLIVARES[ORIGEN],LISTAS!B3,BOLIVARES[DESTINO],LISTAS!B4) -> 330 | V28: =U28 -> 330 | Y28: SERGIO LOPEZ | Z28: =SUMIF(BOLIVARES[RECEPTOR],LISTAS!L6,BOLIVARES[BOLIVARES2]) -> 0 | AA28: =SUMIF(Tabla12[RECEPTOR],LISTAS!L6,Tabla12[MONTO2]) -> 0
I29: =BOLIVARES[[#This Row],[BOLIVARES1]]*0.003 -> 0 | N29: =IFERROR(BOLIVARES[[#This Row],[BOLIVARES2]]/BOLIVARES[[#This Row],[TASA2]],0) -> 0 | P29: =BOLIVARES[[#This Row],[BOLIVARES1]] -> 0 | T29: DIF | U29: =U28-U27 -> 330 | V29: =V28-V27 -> -12221.454 | Y29: YENSI RIOS | Z29: =SUMIF(BOLIVARES[RECEPTOR],LISTAS!L7,BOLIVARES[BOLIVARES2]) -> 0 | AA29: =SUMIF(Tabla12[RECEPTOR],LISTAS!L7,Tabla12[MONTO2]) -> 0
I30: =BOLIVARES[[#This Row],[BOLIVARES1]]*0.003 -> 0 | N30: =IFERROR(BOLIVARES[[#This Row],[BOLIVARES2]]/BOLIVARES[[#This Row],[TASA2]],0) -> 0 | P30: =BOLIVARES[[#This Row],[BOLIVARES1]] -> 0 | T30: BS USADOS | U30: =SUMIFS(BOLIVARES[BOLIVARES1],BOLIVARES[ORIGEN],LISTAS!B3,BOLIVARES[DESTINO],LISTAS!B4) -> 130700
I31: =BOLIVARES[[#This Row],[BOLIVARES1]]*0.003 -> 0 | N31: =IFERROR(BOLIVARES[[#This Row],[BOLIVARES2]]/BOLIVARES[[#This Row],[TASA2]],0) -> 0 | P31: =BOLIVARES[[#This Row],[BOLIVARES1]] -> 0 | T31: DIF | U31: =U26-U30 -> -30700 | Y31: DISTRIBUCION DE LAS COMISIONES | Z31: BS | AA31: USD | AB31: ALQUILER
I32: =BOLIVARES[[#This Row],[BOLIVARES1]]*0.003 -> 0 | N32: =IFERROR(BOLIVARES[[#This Row],[BOLIVARES2]]/BOLIVARES[[#This Row],[TASA2]],0) -> 0 | P32: =BOLIVARES[[#This Row],[BOLIVARES1]] -> 0 | T32: COMPRAR | U32: =U31/U46 -> #DIV/0! | Y32: EDUARD OCHOA | Z32: =SUMIF(BOLIVARES[RECEPTOR],LISTAS!L8,BOLIVARES[BOLIVARES2]) -> 0 | AA32: =SUMIF(Tabla12[RECEPTOR],LISTAS!L8,Tabla12[MONTO2]) -> 0 | AB32: =SUMIF(BOLIVARES[RECEPTOR],LISTAS!L18,BOLIVARES[BOLIVARES2]) -> 0
I33: =BOLIVARES[[#This Row],[BOLIVARES1]]*0.003 -> 0 | N33: =IFERROR(BOLIVARES[[#This Row],[BOLIVARES2]]/BOLIVARES[[#This Row],[TASA2]],0) -> 0 | P33: =BOLIVARES[[#This Row],[BOLIVARES1]] -> 0 | T33: GANANCIA | U33: =U32+U29 -> #DIV/0! | Y33: KAROL MALDONADO | Z33: =SUMIF(BOLIVARES[RECEPTOR],LISTAS!L9,BOLIVARES[BOLIVARES2]) -> 0 | AA33: =SUMIF(Tabla12[RECEPTOR],LISTAS!L9,Tabla12[MONTO2]) -> 0 | AB33: =SUMIF(BOLIVARES[RECEPTOR],LISTAS!L19,BOLIVARES[BOLIVARES2]) -> 0
I34: =BOLIVARES[[#This Row],[BOLIVARES1]]*0.003 -> 0 | N34: =IFERROR(BOLIVARES[[#This Row],[BOLIVARES2]]/BOLIVARES[[#This Row],[TASA2]],0) -> 0 | P34: =BOLIVARES[[#This Row],[BOLIVARES1]] -> 0
I35: =BOLIVARES[[#This Row],[BOLIVARES1]]*0.003 -> 0 | N35: =IFERROR(BOLIVARES[[#This Row],[BOLIVARES2]]/BOLIVARES[[#This Row],[TASA2]],0) -> 0 | P35: =BOLIVARES[[#This Row],[BOLIVARES1]] -> 0 | Y35: SARAH ALVAREZ | Z35: =SUMIF(BOLIVARES[RECEPTOR],LISTAS!L10,BOLIVARES[BOLIVARES2]) -> 0 | AA35: =SUMIF(Tabla12[RECEPTOR],LISTAS!L10,Tabla12[MONTO2]) -> 0 | AB35: =SUMIF(BOLIVARES[RECEPTOR],LISTAS!L20,BOLIVARES[BOLIVARES2]) -> 0
I36: =BOLIVARES[[#This Row],[BOLIVARES1]]*0.003 -> 0 | N36: =IFERROR(BOLIVARES[[#This Row],[BOLIVARES2]]/BOLIVARES[[#This Row],[TASA2]],0) -> 0 | P36: =BOLIVARES[[#This Row],[BOLIVARES1]] -> 0 | T36: PROMEDIO DE COMPRAS A CLIENTES | U36: =SUMIFS(BOLIVARES[BOLIVARES1],BOLIVARES[ORIGEN],LISTAS!B3,BOLIVARES[DESTINO],LISTAS!B4) -> 130700 | V36: =Tabla16[[#Totals],[SALDO]] -> 5240910.6 | Y36: YENSI RIOS | Z36: =SUMIF(BOLIVARES[RECEPTOR],LISTAS!L11,BOLIVARES[BOLIVARES2]) -> 0 | AA36: =SUMIF(Tabla12[RECEPTOR],LISTAS!L11,Tabla12[MONTO2]) -> 0 | AB36: =SUMIF(BOLIVARES[RECEPTOR],LISTAS!L21,BOLIVARES[BOLIVARES2]) -> 0
I37: =BOLIVARES[[#This Row],[BOLIVARES1]]*0.003 -> 0 | N37: =IFERROR(BOLIVARES[[#This Row],[BOLIVARES2]]/BOLIVARES[[#This Row],[TASA2]],0) -> 0 | P37: =BOLIVARES[[#This Row],[BOLIVARES1]] -> 0 | T37: DOLARES COMPRADOS DE BANCOS | U37: 64182 | V37: =V36/300 -> 17469.702 | W37: =V37+U37 -> 81651.702 | Y37: BEATRIZ TORREALBA | Z37: =SUMIF(BOLIVARES[RECEPTOR],LISTAS!L12,BOLIVARES[BOLIVARES2]) -> 0 | AA37: =SUMIF(Tabla12[RECEPTOR],LISTAS!L12,Tabla12[MONTO2]) -> 0 | AB37: =SUMIF(BOLIVARES[RECEPTOR],LISTAS!L25,BOLIVARES[BOLIVARES2]) -> 0
I38: =BOLIVARES[[#This Row],[BOLIVARES1]]*0.003 -> 0 | N38: =IFERROR(BOLIVARES[[#This Row],[BOLIVARES2]]/BOLIVARES[[#This Row],[TASA2]],0) -> 0 | P38: =BOLIVARES[[#This Row],[BOLIVARES1]] -> 0 | W38: =W37-V27 -> 69100.248
I39: =BOLIVARES[[#This Row],[BOLIVARES1]]*0.003 -> 0 | N39: =IFERROR(BOLIVARES[[#This Row],[BOLIVARES2]]/BOLIVARES[[#This Row],[TASA2]],0) -> 0 | P39: =BOLIVARES[[#This Row],[BOLIVARES1]] -> 0
I40: =BOLIVARES[[#This Row],[BOLIVARES1]]*0.003 -> 0 | N40: =IFERROR(BOLIVARES[[#This Row],[BOLIVARES2]]/BOLIVARES[[#This Row],[TASA2]],0) -> 0 | P40: =BOLIVARES[[#This Row],[BOLIVARES1]] -> 0
I41: =BOLIVARES[[#This Row],[BOLIVARES1]]*0.003 -> 0 | N41: =IFERROR(BOLIVARES[[#This Row],[BOLIVARES2]]/BOLIVARES[[#This Row],[TASA2]],0) -> 0 | P41: =BOLIVARES[[#This Row],[BOLIVARES1]] -> 0
I42: =BOLIVARES[[#This Row],[BOLIVARES1]]*0.003 -> 0 | N42: =IFERROR(BOLIVARES[[#This Row],[BOLIVARES2]]/BOLIVARES[[#This Row],[TASA2]],0) -> 0 | P42: =BOLIVARES[[#This Row],[BOLIVARES1]] -> 0 | Y42: KAROL MALDONADO | Z42: =BANCOS!D3+BANCOS!D9+BANCOS!D15+BANCOS!D18+BANCOS!D20+BANCOS!D23+BANCOS!D25+BANCOS!D27 -> 0 | AB42: =Z42-AA42 -> 0 | AC42: =AB42*0.003 -> 0 | AD42: =AB33 -> 0 | AE42: =AC42-AD42 -> 0 | AF42: =AC42/300 -> 0
I43: =BOLIVARES[[#This Row],[BOLIVARES1]]*0.003 -> 0 | N43: =IFERROR(BOLIVARES[[#This Row],[BOLIVARES2]]/BOLIVARES[[#This Row],[TASA2]],0) -> 0 | P43: =BOLIVARES[[#This Row],[BOLIVARES1]] -> 0 | Y43: SARAH ALVAREZ | Z43: =BANCOS!D10+BANCOS!D11+BANCOS!D19+BANCOS!D26 -> 0 | AB43: =Z43-AA43 -> 0 | AC43: =AB43*0.003 -> 0 | AD43: =AB35 -> 0 | AE43: =AC43-AD43 -> 0 | AF43: =AC43/300 -> 0
I44: =BOLIVARES[[#This Row],[BOLIVARES1]]*0.003 -> 0 | N44: =IFERROR(BOLIVARES[[#This Row],[BOLIVARES2]]/BOLIVARES[[#This Row],[TASA2]],0) -> 0 | P44: =BOLIVARES[[#This Row],[BOLIVARES1]] -> 0 | Y44: BEATRIZ TORREALBA | Z44: =BANCOS!D5 -> 0 | AB44: =Z44-AA44 -> 0 | AC44: =AB44*0.003 -> 0 | AD44: =AB37 -> 0 | AE44: =AC44-AD44 -> 0
I45: =BOLIVARES[[#This Row],[BOLIVARES1]]*0.003 -> 0 | N45: =IFERROR(BOLIVARES[[#This Row],[BOLIVARES2]]/BOLIVARES[[#This Row],[TASA2]],0) -> 0 | P45: =BOLIVARES[[#This Row],[BOLIVARES1]] -> 0 | Y45: ANA KARINA MORENO | Z45: =BANCOS!D21+BANCOS!D4 -> 0
I46: =BOLIVARES[[#This Row],[BOLIVARES1]]*0.003 -> 0 | N46: =IFERROR(BOLIVARES[[#This Row],[BOLIVARES2]]/BOLIVARES[[#This Row],[TASA2]],0) -> 0 | P46: =BOLIVARES[[#This Row],[BOLIVARES1]] -> 0
I47: =BOLIVARES[[#This Row],[BOLIVARES1]]*0.003 -> 0 | N47: =IFERROR(BOLIVARES[[#This Row],[BOLIVARES2]]/BOLIVARES[[#This Row],[TASA2]],0) -> 0 | P47: =BOLIVARES[[#This Row],[BOLIVARES1]] -> 0
I48: =BOLIVARES[[#This Row],[BOLIVARES1]]*0.003 -> 0 | N48: =IFERROR(BOLIVARES[[#This Row],[BOLIVARES2]]/BOLIVARES[[#This Row],[TASA2]],0) -> 0 | P48: =BOLIVARES[[#This Row],[BOLIVARES1]] -> 0
I49: =BOLIVARES[[#This Row],[BOLIVARES1]]*0.003 -> 0 | N49: =IFERROR(BOLIVARES[[#This Row],[BOLIVARES2]]/BOLIVARES[[#This Row],[TASA2]],0) -> 0 | P49: =BOLIVARES[[#This Row],[BOLIVARES1]] -> 0
I50: =BOLIVARES[[#This Row],[BOLIVARES1]]*0.003 -> 0 | N50: =IFERROR(BOLIVARES[[#This Row],[BOLIVARES2]]/BOLIVARES[[#This Row],[TASA2]],0) -> 0 | P50: =BOLIVARES[[#This Row],[BOLIVARES1]] -> 0
I51: =BOLIVARES[[#This Row],[BOLIVARES1]]*0.003 -> 0 | N51: =IFERROR(BOLIVARES[[#This Row],[BOLIVARES2]]/BOLIVARES[[#This Row],[TASA2]],0) -> 0 | P51: =BOLIVARES[[#This Row],[BOLIVARES1]] -> 0
I52: =BOLIVARES[[#This Row],[BOLIVARES1]]*0.003 -> 0 | N52: =IFERROR(BOLIVARES[[#This Row],[BOLIVARES2]]/BOLIVARES[[#This Row],[TASA2]],0) -> 0 | P52: =BOLIVARES[[#This Row],[BOLIVARES1]] -> 0
I53: =BOLIVARES[[#This Row],[BOLIVARES1]]*0.003 -> 0 | N53: =IFERROR(BOLIVARES[[#This Row],[BOLIVARES2]]/BOLIVARES[[#This Row],[TASA2]],0) -> 0 | P53: =BOLIVARES[[#This Row],[BOLIVARES1]] -> 0
I54: =BOLIVARES[[#This Row],[BOLIVARES1]]*0.003 -> 0 | N54: =IFERROR(BOLIVARES[[#This Row],[BOLIVARES2]]/BOLIVARES[[#This Row],[TASA2]],0) -> 0 | P54: =BOLIVARES[[#This Row],[BOLIVARES1]] -> 0
I55: =BOLIVARES[[#This Row],[BOLIVARES1]]*0.003 -> 0 | N55: =IFERROR(BOLIVARES[[#This Row],[BOLIVARES2]]/BOLIVARES[[#This Row],[TASA2]],0) -> 0 | P55: =BOLIVARES[[#This Row],[BOLIVARES1]] -> 0
I56: =BOLIVARES[[#This Row],[BOLIVARES1]]*0.003 -> 0 | N56: =IFERROR(BOLIVARES[[#This Row],[BOLIVARES2]]/BOLIVARES[[#This Row],[TASA2]],0) -> 0 | P56: =BOLIVARES[[#This Row],[BOLIVARES1]] -> 0
I57: =BOLIVARES[[#This Row],[BOLIVARES1]]*0.003 -> 0 | N57: =IFERROR(BOLIVARES[[#This Row],[BOLIVARES2]]/BOLIVARES[[#This Row],[TASA2]],0) -> 0 | P57: =BOLIVARES[[#This Row],[BOLIVARES1]] -> 0
I58: =BOLIVARES[[#This Row],[BOLIVARES1]]*0.003 -> 0 | N58: =IFERROR(BOLIVARES[[#This Row],[BOLIVARES2]]/BOLIVARES[[#This Row],[TASA2]],0) -> 0 | P58: =BOLIVARES[[#This Row],[BOLIVARES1]] -> 0
I59: =BOLIVARES[[#This Row],[BOLIVARES1]]*0.003 -> 0 | N59: =IFERROR(BOLIVARES[[#This Row],[BOLIVARES2]]/BOLIVARES[[#This Row],[TASA2]],0) -> 0 | P59: =BOLIVARES[[#This Row],[BOLIVARES1]] -> 0 | T59: =W3 -> 0
I60: =BOLIVARES[[#This Row],[BOLIVARES1]]*0.003 -> 0 | N60: =IFERROR(BOLIVARES[[#This Row],[BOLIVARES2]]/BOLIVARES[[#This Row],[TASA2]],0) -> 0 | P60: =BOLIVARES[[#This Row],[BOLIVARES1]] -> 0 | T60: =W4 -> 0
I61: =BOLIVARES[[#This Row],[BOLIVARES1]]*0.003 -> 0 | N61: =IFERROR(BOLIVARES[[#This Row],[BOLIVARES2]]/BOLIVARES[[#This Row],[TASA2]],0) -> 0 | P61: =BOLIVARES[[#This Row],[BOLIVARES1]] -> 0 | T61: =W5 -> 0

Sheet CAMBIOS
B2: FECHA | C2: CAMBIO | D2: SOLIICTANTES | E2: RECIBIDO | F2: ENVIAR | G2: COSTOS DE ENVÍO | H2: DIFERENCIA | I2: PORCENTAJE | J2: GANANCIA REAL | K2: % REAL | L2: OBSERVACIONES | N2: VERIFICADOR DE USD
B3: 46218 | C3: CASH/EUR | D3: SARAH ALVAREZ | E3: 900 | F3: 1000 | H3: =CAMBIOS[[#This Row],[RECIBIDO ]]-CAMBIOS[[#This Row],[ENVIAR ]] -> -100 | I3: =IFERROR(CAMBIOS[[#This Row],[DIFERENCIA]]*100/CAMBIOS[[#This Row],[ENVIAR ]],0) -> -10 | J3: =CAMBIOS[[#This Row],[DIFERENCIA]]-CAMBIOS[[#This Row],[COSTOS DE ENVÍO]] -> -100 | K3: =IFERROR((CAMBIOS[[#This Row],[DIFERENCIA]]-CAMBIOS[[#This Row],[COSTOS DE ENVÍO]])*100/CAMBIOS[[#This Row],[ENVIAR ]],0) -> -10 | N3: COMISIONES RECIBIDAS | O3: =SUM(CAMBIOS[DIFERENCIA]) -> -100 | P3: =SUM(Tabla14[COMISION]) -> -100 | Q3: =SUM(CAMBIOS[COSTOS DE ENVÍO]) -> 0 | R3: =O3-P3 -> 0
H4: =CAMBIOS[[#This Row],[RECIBIDO ]]-CAMBIOS[[#This Row],[ENVIAR ]] -> 0 | I4: =IFERROR(CAMBIOS[[#This Row],[DIFERENCIA]]*100/CAMBIOS[[#This Row],[ENVIAR ]],0) -> 0 | J4: =CAMBIOS[[#This Row],[DIFERENCIA]]-CAMBIOS[[#This Row],[COSTOS DE ENVÍO]] -> 0 | K4: =IFERROR((CAMBIOS[[#This Row],[DIFERENCIA]]-CAMBIOS[[#This Row],[COSTOS DE ENVÍO]])*100/CAMBIOS[[#This Row],[ENVIAR ]],0) -> 0 | N4: COSTOS DE ENVIOS | O4: =SUM(CAMBIOS[COSTOS DE ENVÍO]) -> 0
H5: =CAMBIOS[[#This Row],[RECIBIDO ]]-CAMBIOS[[#This Row],[ENVIAR ]] -> 0 | I5: =IFERROR(CAMBIOS[[#This Row],[DIFERENCIA]]*100/CAMBIOS[[#This Row],[ENVIAR ]],0) -> 0 | J5: =CAMBIOS[[#This Row],[DIFERENCIA]]-CAMBIOS[[#This Row],[COSTOS DE ENVÍO]] -> 0 | K5: =IFERROR((CAMBIOS[[#This Row],[DIFERENCIA]]-CAMBIOS[[#This Row],[COSTOS DE ENVÍO]])*100/CAMBIOS[[#This Row],[ENVIAR ]],0) -> 0
H6: =CAMBIOS[[#This Row],[RECIBIDO ]]-CAMBIOS[[#This Row],[ENVIAR ]] -> 0 | I6: =IFERROR(CAMBIOS[[#This Row],[DIFERENCIA]]*100/CAMBIOS[[#This Row],[ENVIAR ]],0) -> 0 | J6: =CAMBIOS[[#This Row],[DIFERENCIA]]-CAMBIOS[[#This Row],[COSTOS DE ENVÍO]] -> 0 | K6: =IFERROR((CAMBIOS[[#This Row],[DIFERENCIA]]-CAMBIOS[[#This Row],[COSTOS DE ENVÍO]])*100/CAMBIOS[[#This Row],[ENVIAR ]],0) -> 0
H7: =CAMBIOS[[#This Row],[RECIBIDO ]]-CAMBIOS[[#This Row],[ENVIAR ]] -> 0 | I7: =IFERROR(CAMBIOS[[#This Row],[DIFERENCIA]]*100/CAMBIOS[[#This Row],[ENVIAR ]],0) -> 0 | J7: =CAMBIOS[[#This Row],[DIFERENCIA]]-CAMBIOS[[#This Row],[COSTOS DE ENVÍO]] -> 0 | K7: =IFERROR((CAMBIOS[[#This Row],[DIFERENCIA]]-CAMBIOS[[#This Row],[COSTOS DE ENVÍO]])*100/CAMBIOS[[#This Row],[ENVIAR ]],0) -> 0
H8: =CAMBIOS[[#This Row],[RECIBIDO ]]-CAMBIOS[[#This Row],[ENVIAR ]] -> 0 | I8: =IFERROR(CAMBIOS[[#This Row],[DIFERENCIA]]*100/CAMBIOS[[#This Row],[ENVIAR ]],0) -> 0 | J8: =CAMBIOS[[#This Row],[DIFERENCIA]]-CAMBIOS[[#This Row],[COSTOS DE ENVÍO]] -> 0 | K8: =IFERROR((CAMBIOS[[#This Row],[DIFERENCIA]]-CAMBIOS[[#This Row],[COSTOS DE ENVÍO]])*100/CAMBIOS[[#This Row],[ENVIAR ]],0) -> 0
H9: =CAMBIOS[[#This Row],[RECIBIDO ]]-CAMBIOS[[#This Row],[ENVIAR ]] -> 0 | I9: =IFERROR(CAMBIOS[[#This Row],[DIFERENCIA]]*100/CAMBIOS[[#This Row],[ENVIAR ]],0) -> 0 | J9: =CAMBIOS[[#This Row],[DIFERENCIA]]-CAMBIOS[[#This Row],[COSTOS DE ENVÍO]] -> 0 | K9: =IFERROR((CAMBIOS[[#This Row],[DIFERENCIA]]-CAMBIOS[[#This Row],[COSTOS DE ENVÍO]])*100/CAMBIOS[[#This Row],[ENVIAR ]],0) -> 0 | N9: COMPRA TRON | O9: =SUMIF(Tabla12[RECEPTOR],LISTAS!L26,Tabla12[MONTO2]) -> 0
H10: =CAMBIOS[[#This Row],[RECIBIDO ]]-CAMBIOS[[#This Row],[ENVIAR ]] -> 0 | I10: =IFERROR(CAMBIOS[[#This Row],[DIFERENCIA]]*100/CAMBIOS[[#This Row],[ENVIAR ]],0) -> 0 | J10: =CAMBIOS[[#This Row],[DIFERENCIA]]-CAMBIOS[[#This Row],[COSTOS DE ENVÍO]] -> 0 | K10: =IFERROR((CAMBIOS[[#This Row],[DIFERENCIA]]-CAMBIOS[[#This Row],[COSTOS DE ENVÍO]])*100/CAMBIOS[[#This Row],[ENVIAR ]],0) -> 0 | N10: DISPONIBLE EN TRON | O10: =O9-SUM(CAMBIOS[COSTOS DE ENVÍO]) -> 0
H11: =CAMBIOS[[#This Row],[RECIBIDO ]]-CAMBIOS[[#This Row],[ENVIAR ]] -> 0 | I11: =IFERROR(CAMBIOS[[#This Row],[DIFERENCIA]]*100/CAMBIOS[[#This Row],[ENVIAR ]],0) -> 0 | J11: =CAMBIOS[[#This Row],[DIFERENCIA]]-CAMBIOS[[#This Row],[COSTOS DE ENVÍO]] -> 0 | K11: =IFERROR((CAMBIOS[[#This Row],[DIFERENCIA]]-CAMBIOS[[#This Row],[COSTOS DE ENVÍO]])*100/CAMBIOS[[#This Row],[ENVIAR ]],0) -> 0
H12: =CAMBIOS[[#This Row],[RECIBIDO ]]-CAMBIOS[[#This Row],[ENVIAR ]] -> 0 | I12: =IFERROR(CAMBIOS[[#This Row],[DIFERENCIA]]*100/CAMBIOS[[#This Row],[ENVIAR ]],0) -> 0 | J12: =CAMBIOS[[#This Row],[DIFERENCIA]]-CAMBIOS[[#This Row],[COSTOS DE ENVÍO]] -> 0 | K12: =IFERROR((CAMBIOS[[#This Row],[DIFERENCIA]]-CAMBIOS[[#This Row],[COSTOS DE ENVÍO]])*100/CAMBIOS[[#This Row],[ENVIAR ]],0) -> 0
H13: =CAMBIOS[[#This Row],[RECIBIDO ]]-CAMBIOS[[#This Row],[ENVIAR ]] -> 0 | I13: =IFERROR(CAMBIOS[[#This Row],[DIFERENCIA]]*100/CAMBIOS[[#This Row],[ENVIAR ]],0) -> 0 | J13: =CAMBIOS[[#This Row],[DIFERENCIA]]-CAMBIOS[[#This Row],[COSTOS DE ENVÍO]] -> 0 | K13: =IFERROR((CAMBIOS[[#This Row],[DIFERENCIA]]-CAMBIOS[[#This Row],[COSTOS DE ENVÍO]])*100/CAMBIOS[[#This Row],[ENVIAR ]],0) -> 0
H14: =CAMBIOS[[#This Row],[RECIBIDO ]]-CAMBIOS[[#This Row],[ENVIAR ]] -> 0 | I14: =IFERROR(CAMBIOS[[#This Row],[DIFERENCIA]]*100/CAMBIOS[[#This Row],[ENVIAR ]],0) -> 0 | J14: =CAMBIOS[[#This Row],[DIFERENCIA]]-CAMBIOS[[#This Row],[COSTOS DE ENVÍO]] -> 0 | K14: =IFERROR((CAMBIOS[[#This Row],[DIFERENCIA]]-CAMBIOS[[#This Row],[COSTOS DE ENVÍO]])*100/CAMBIOS[[#This Row],[ENVIAR ]],0) -> 0

Sheet CLIENTES
B2: CLIENTE | C2: PENDIENTE | D2: COMPRA | E2: VENTA | F2: PAGO | G2: RETIRO | H2: COMISION | I2: SALDO | J2: TIPO | K2: GRUPO
B3: =Tabla3[[#This Row],[CLIENTES]] -> EVELIO RAMIREZ | C3: 100 | D3: =SUMIF(BOLIVARES[EMISOR],Tabla3[[#This Row],[CLIENTES]],BOLIVARES[DOLARES]) -> 0 | E3: =SUMIF(BOLIVARES[RECEPTOR],Tabla3[[#This Row],[CLIENTES]],BOLIVARES[DOLARES2]) -> 130 | F3: =SUMIF(Tabla12[EMISOR2],Tabla3[[#This Row],[CLIENTES]],Tabla12[MONTO]) -> 0 | G3: =SUMIF(Tabla12[RECEPTOR],Tabla3[[#This Row],[CLIENTES]],Tabla12[MONTO2]) -> 900 | H3: =SUMIF(CAMBIOS[SOLIICTANTES],Tabla3[[#This Row],[CLIENTES]],CAMBIOS[DIFERENCIA])+ SUMIF(CAMBIOS[SOLIICTANTES],Tabla3[[#This Row],[CLIENTES]],CAMBIOS[COSTOS DE ENVÍO]) -> 0 | I3: =Tabla14[[#This Row],[PENDIENTE]]+Tabla14[[#This Row],[VENTA]]+Tabla14[[#This Row],[RETIRO]]-Tabla14[[#This Row],[COMPRA]]-Tabla14[[#This Row],[PAGO]]+Tabla14[[#This Row],[COMISION]] -> 1130 | J3: MOTO
B4: =Tabla3[[#This Row],[CLIENTES]] -> JOHANA RODRIGUEZ | C4: 3000 | D4: =SUMIF(BOLIVARES[EMISOR],Tabla3[[#This Row],[CLIENTES]],BOLIVARES[DOLARES]) -> 0 | E4: =SUMIF(BOLIVARES[RECEPTOR],Tabla3[[#This Row],[CLIENTES]],BOLIVARES[DOLARES2]) -> 0 | F4: =SUMIF(Tabla12[EMISOR2],Tabla3[[#This Row],[CLIENTES]],Tabla12[MONTO]) -> 0 | G4: =SUMIF(Tabla12[RECEPTOR],Tabla3[[#This Row],[CLIENTES]],Tabla12[MONTO2]) -> 0 | H4: =SUMIF(CAMBIOS[SOLIICTANTES],Tabla3[[#This Row],[CLIENTES]],CAMBIOS[DIFERENCIA])+ SUMIF(CAMBIOS[SOLIICTANTES],Tabla3[[#This Row],[CLIENTES]],CAMBIOS[COSTOS DE ENVÍO]) -> 0 | I4: =Tabla14[[#This Row],[PENDIENTE]]+Tabla14[[#This Row],[VENTA]]+Tabla14[[#This Row],[RETIRO]]-Tabla14[[#This Row],[COMPRA]]-Tabla14[[#This Row],[PAGO]]+Tabla14[[#This Row],[COMISION]] -> 3000 | J4: TINTORERIA
B5: =Tabla3[[#This Row],[CLIENTES]] -> KAROL MALDONADO | D5: =SUMIF(BOLIVARES[EMISOR],Tabla3[[#This Row],[CLIENTES]],BOLIVARES[DOLARES]) -> 0 | E5: =SUMIF(BOLIVARES[RECEPTOR],Tabla3[[#This Row],[CLIENTES]],BOLIVARES[DOLARES2]) -> 200 | F5: =SUMIF(Tabla12[EMISOR2],Tabla3[[#This Row],[CLIENTES]],Tabla12[MONTO]) -> 0 | G5: =SUMIF(Tabla12[RECEPTOR],Tabla3[[#This Row],[CLIENTES]],Tabla12[MONTO2]) -> 0 | H5: =SUMIF(CAMBIOS[SOLIICTANTES],Tabla3[[#This Row],[CLIENTES]],CAMBIOS[DIFERENCIA])+ SUMIF(CAMBIOS[SOLIICTANTES],Tabla3[[#This Row],[CLIENTES]],CAMBIOS[COSTOS DE ENVÍO]) -> 0 | I5: =Tabla14[[#This Row],[PENDIENTE]]+Tabla14[[#This Row],[VENTA]]+Tabla14[[#This Row],[RETIRO]]-Tabla14[[#This Row],[COMPRA]]-Tabla14[[#This Row],[PAGO]]+Tabla14[[#This Row],[COMISION]] -> 200 | J5: PANAMA
B6: =Tabla3[[#This Row],[CLIENTES]] -> SARAH ALVAREZ | D6: =SUMIF(BOLIVARES[EMISOR],Tabla3[[#This Row],[CLIENTES]],BOLIVARES[DOLARES]) -> 0 | E6: =SUMIF(BOLIVARES[RECEPTOR],Tabla3[[#This Row],[CLIENTES]],BOLIVARES[DOLARES2]) -> 125 | F6: =SUMIF(Tabla12[EMISOR2],Tabla3[[#This Row],[CLIENTES]],Tabla12[MONTO]) -> 900 | G6: =SUMIF(Tabla12[RECEPTOR],Tabla3[[#This Row],[CLIENTES]],Tabla12[MONTO2]) -> 1000 | H6: =SUMIF(CAMBIOS[SOLIICTANTES],Tabla3[[#This Row],[CLIENTES]],CAMBIOS[DIFERENCIA])+ SUMIF(CAMBIOS[SOLIICTANTES],Tabla3[[#This Row],[CLIENTES]],CAMBIOS[COSTOS DE ENVÍO]) -> -100 | I6: =Tabla14[[#This Row],[PENDIENTE]]+Tabla14[[#This Row],[VENTA]]+Tabla14[[#This Row],[RETIRO]]-Tabla14[[#This Row],[COMPRA]]-Tabla14[[#This Row],[PAGO]]+Tabla14[[#This Row],[COMISION]] -> 125 | J6: EUROS
B7: =Tabla3[[#This Row],[CLIENTES]] -> 0 | D7: =SUMIF(BOLIVARES[EMISOR],Tabla3[[#This Row],[CLIENTES]],BOLIVARES[DOLARES]) -> 0 | E7: =SUMIF(BOLIVARES[RECEPTOR],Tabla3[[#This Row],[CLIENTES]],BOLIVARES[DOLARES2]) -> 0 | F7: =SUMIF(Tabla12[EMISOR2],Tabla3[[#This Row],[CLIENTES]],Tabla12[MONTO]) -> 0 | G7: =SUMIF(Tabla12[RECEPTOR],Tabla3[[#This Row],[CLIENTES]],Tabla12[MONTO2]) -> 0 | H7: =SUMIF(CAMBIOS[SOLIICTANTES],Tabla3[[#This Row],[CLIENTES]],CAMBIOS[DIFERENCIA])+ SUMIF(CAMBIOS[SOLIICTANTES],Tabla3[[#This Row],[CLIENTES]],CAMBIOS[COSTOS DE ENVÍO]) -> 0 | I7: =Tabla14[[#This Row],[PENDIENTE]]+Tabla14[[#This Row],[VENTA]]+Tabla14[[#This Row],[RETIRO]]-Tabla14[[#This Row],[COMPRA]]-Tabla14[[#This Row],[PAGO]]+Tabla14[[#This Row],[COMISION]] -> 0 | K7: GRUPO A
B8: =Tabla3[[#This Row],[CLIENTES]] -> 0 | D8: =SUMIF(BOLIVARES[EMISOR],Tabla3[[#This Row],[CLIENTES]],BOLIVARES[DOLARES]) -> 0 | E8: =SUMIF(BOLIVARES[RECEPTOR],Tabla3[[#This Row],[CLIENTES]],BOLIVARES[DOLARES2]) -> 0 | F8: =SUMIF(Tabla12[EMISOR2],Tabla3[[#This Row],[CLIENTES]],Tabla12[MONTO]) -> 0 | G8: =SUMIF(Tabla12[RECEPTOR],Tabla3[[#This Row],[CLIENTES]],Tabla12[MONTO2]) -> 0 | H8: =SUMIF(CAMBIOS[SOLIICTANTES],Tabla3[[#This Row],[CLIENTES]],CAMBIOS[DIFERENCIA])+ SUMIF(CAMBIOS[SOLIICTANTES],Tabla3[[#This Row],[CLIENTES]],CAMBIOS[COSTOS DE ENVÍO]) -> 0 | I8: =Tabla14[[#This Row],[PENDIENTE]]+Tabla14[[#This Row],[VENTA]]+Tabla14[[#This Row],[RETIRO]]-Tabla14[[#This Row],[COMPRA]]-Tabla14[[#This Row],[PAGO]]+Tabla14[[#This Row],[COMISION]] -> 0
B9: =Tabla3[[#This Row],[CLIENTES]] -> 0 | D9: =SUMIF(BOLIVARES[EMISOR],Tabla3[[#This Row],[CLIENTES]],BOLIVARES[DOLARES]) -> 0 | E9: =SUMIF(BOLIVARES[RECEPTOR],Tabla3[[#This Row],[CLIENTES]],BOLIVARES[DOLARES2]) -> 0 | F9: =SUMIF(Tabla12[EMISOR2],Tabla3[[#This Row],[CLIENTES]],Tabla12[MONTO]) -> 0 | G9: =SUMIF(Tabla12[RECEPTOR],Tabla3[[#This Row],[CLIENTES]],Tabla12[MONTO2]) -> 0 | H9: =SUMIF(CAMBIOS[SOLIICTANTES],Tabla3[[#This Row],[CLIENTES]],CAMBIOS[DIFERENCIA])+ SUMIF(CAMBIOS[SOLIICTANTES],Tabla3[[#This Row],[CLIENTES]],CAMBIOS[COSTOS DE ENVÍO]) -> 0 | I9: =Tabla14[[#This Row],[PENDIENTE]]+Tabla14[[#This Row],[VENTA]]+Tabla14[[#This Row],[RETIRO]]-Tabla14[[#This Row],[COMPRA]]-Tabla14[[#This Row],[PAGO]]+Tabla14[[#This Row],[COMISION]] -> 0
B10: =Tabla3[[#This Row],[CLIENTES]] -> 0 | D10: =SUMIF(BOLIVARES[EMISOR],Tabla3[[#This Row],[CLIENTES]],BOLIVARES[DOLARES]) -> 0 | E10: =SUMIF(BOLIVARES[RECEPTOR],Tabla3[[#This Row],[CLIENTES]],BOLIVARES[DOLARES2]) -> 0 | F10: =SUMIF(Tabla12[EMISOR2],Tabla3[[#This Row],[CLIENTES]],Tabla12[MONTO]) -> 0 | G10: =SUMIF(Tabla12[RECEPTOR],Tabla3[[#This Row],[CLIENTES]],Tabla12[MONTO2]) -> 0 | H10: =SUMIF(CAMBIOS[SOLIICTANTES],Tabla3[[#This Row],[CLIENTES]],CAMBIOS[DIFERENCIA])+ SUMIF(CAMBIOS[SOLIICTANTES],Tabla3[[#This Row],[CLIENTES]],CAMBIOS[COSTOS DE ENVÍO]) -> 0 | I10: =Tabla14[[#This Row],[PENDIENTE]]+Tabla14[[#This Row],[VENTA]]+Tabla14[[#This Row],[RETIRO]]-Tabla14[[#This Row],[COMPRA]]-Tabla14[[#This Row],[PAGO]]+Tabla14[[#This Row],[COMISION]] -> 0
B11: =Tabla3[[#This Row],[CLIENTES]] -> 0 | D11: =SUMIF(BOLIVARES[EMISOR],Tabla3[[#This Row],[CLIENTES]],BOLIVARES[DOLARES]) -> 0 | E11: =SUMIF(BOLIVARES[RECEPTOR],Tabla3[[#This Row],[CLIENTES]],BOLIVARES[DOLARES2]) -> 0 | F11: =SUMIF(Tabla12[EMISOR2],Tabla3[[#This Row],[CLIENTES]],Tabla12[MONTO]) -> 0 | G11: =SUMIF(Tabla12[RECEPTOR],Tabla3[[#This Row],[CLIENTES]],Tabla12[MONTO2]) -> 0 | H11: =SUMIF(CAMBIOS[SOLIICTANTES],Tabla3[[#This Row],[CLIENTES]],CAMBIOS[DIFERENCIA])+ SUMIF(CAMBIOS[SOLIICTANTES],Tabla3[[#This Row],[CLIENTES]],CAMBIOS[COSTOS DE ENVÍO]) -> 0 | I11: =Tabla14[[#This Row],[PENDIENTE]]+Tabla14[[#This Row],[VENTA]]+Tabla14[[#This Row],[RETIRO]]-Tabla14[[#This Row],[COMPRA]]-Tabla14[[#This Row],[PAGO]]+Tabla14[[#This Row],[COMISION]] -> 0
B12: =Tabla3[[#This Row],[CLIENTES]] -> 0 | D12: =SUMIF(BOLIVARES[EMISOR],Tabla3[[#This Row],[CLIENTES]],BOLIVARES[DOLARES]) -> 0 | E12: =SUMIF(BOLIVARES[RECEPTOR],Tabla3[[#This Row],[CLIENTES]],BOLIVARES[DOLARES2]) -> 0 | F12: =SUMIF(Tabla12[EMISOR2],Tabla3[[#This Row],[CLIENTES]],Tabla12[MONTO]) -> 0 | G12: =SUMIF(Tabla12[RECEPTOR],Tabla3[[#This Row],[CLIENTES]],Tabla12[MONTO2]) -> 0 | H12: =SUMIF(CAMBIOS[SOLIICTANTES],Tabla3[[#This Row],[CLIENTES]],CAMBIOS[DIFERENCIA])+ SUMIF(CAMBIOS[SOLIICTANTES],Tabla3[[#This Row],[CLIENTES]],CAMBIOS[COSTOS DE ENVÍO]) -> 0 | I12: =Tabla14[[#This Row],[PENDIENTE]]+Tabla14[[#This Row],[VENTA]]+Tabla14[[#This Row],[RETIRO]]-Tabla14[[#This Row],[COMPRA]]-Tabla14[[#This Row],[PAGO]]+Tabla14[[#This Row],[COMISION]] -> 0
B13: =Tabla3[[#This Row],[CLIENTES]] -> 0 | D13: =SUMIF(BOLIVARES[EMISOR],Tabla3[[#This Row],[CLIENTES]],BOLIVARES[DOLARES]) -> 0 | E13: =SUMIF(BOLIVARES[RECEPTOR],Tabla3[[#This Row],[CLIENTES]],BOLIVARES[DOLARES2]) -> 0 | F13: =SUMIF(Tabla12[EMISOR2],Tabla3[[#This Row],[CLIENTES]],Tabla12[MONTO]) -> 0 | G13: =SUMIF(Tabla12[RECEPTOR],Tabla3[[#This Row],[CLIENTES]],Tabla12[MONTO2]) -> 0 | H13: =SUMIF(CAMBIOS[SOLIICTANTES],Tabla3[[#This Row],[CLIENTES]],CAMBIOS[DIFERENCIA])+ SUMIF(CAMBIOS[SOLIICTANTES],Tabla3[[#This Row],[CLIENTES]],CAMBIOS[COSTOS DE ENVÍO]) -> 0 | I13: =Tabla14[[#This Row],[PENDIENTE]]+Tabla14[[#This Row],[VENTA]]+Tabla14[[#This Row],[RETIRO]]-Tabla14[[#This Row],[COMPRA]]-Tabla14[[#This Row],[PAGO]]+Tabla14[[#This Row],[COMISION]] -> 0
B14: =Tabla3[[#This Row],[CLIENTES]] -> 0 | D14: =SUMIF(BOLIVARES[EMISOR],Tabla3[[#This Row],[CLIENTES]],BOLIVARES[DOLARES]) -> 0 | E14: =SUMIF(BOLIVARES[RECEPTOR],Tabla3[[#This Row],[CLIENTES]],BOLIVARES[DOLARES2]) -> 0 | F14: =SUMIF(Tabla12[EMISOR2],Tabla3[[#This Row],[CLIENTES]],Tabla12[MONTO]) -> 0 | G14: =SUMIF(Tabla12[RECEPTOR],Tabla3[[#This Row],[CLIENTES]],Tabla12[MONTO2]) -> 0 | H14: =SUMIF(CAMBIOS[SOLIICTANTES],Tabla3[[#This Row],[CLIENTES]],CAMBIOS[DIFERENCIA])+ SUMIF(CAMBIOS[SOLIICTANTES],Tabla3[[#This Row],[CLIENTES]],CAMBIOS[COSTOS DE ENVÍO]) -> 0 | I14: =Tabla14[[#This Row],[PENDIENTE]]+Tabla14[[#This Row],[VENTA]]+Tabla14[[#This Row],[RETIRO]]-Tabla14[[#This Row],[COMPRA]]-Tabla14[[#This Row],[PAGO]]+Tabla14[[#This Row],[COMISION]] -> 0
B15: =Tabla3[[#This Row],[CLIENTES]] -> 0 | D15: =SUMIF(BOLIVARES[EMISOR],Tabla3[[#This Row],[CLIENTES]],BOLIVARES[DOLARES]) -> 0 | E15: =SUMIF(BOLIVARES[RECEPTOR],Tabla3[[#This Row],[CLIENTES]],BOLIVARES[DOLARES2]) -> 0 | F15: =SUMIF(Tabla12[EMISOR2],Tabla3[[#This Row],[CLIENTES]],Tabla12[MONTO]) -> 0 | G15: =SUMIF(Tabla12[RECEPTOR],Tabla3[[#This Row],[CLIENTES]],Tabla12[MONTO2]) -> 0 | H15: =SUMIF(CAMBIOS[SOLIICTANTES],Tabla3[[#This Row],[CLIENTES]],CAMBIOS[DIFERENCIA])+ SUMIF(CAMBIOS[SOLIICTANTES],Tabla3[[#This Row],[CLIENTES]],CAMBIOS[COSTOS DE ENVÍO]) -> 0 | I15: =Tabla14[[#This Row],[PENDIENTE]]+Tabla14[[#This Row],[VENTA]]+Tabla14[[#This Row],[RETIRO]]-Tabla14[[#This Row],[COMPRA]]-Tabla14[[#This Row],[PAGO]]+Tabla14[[#This Row],[COMISION]] -> 0
B16: =Tabla3[[#This Row],[CLIENTES]] -> 0 | D16: =SUMIF(BOLIVARES[EMISOR],Tabla3[[#This Row],[CLIENTES]],BOLIVARES[DOLARES]) -> 0 | E16: =SUMIF(BOLIVARES[RECEPTOR],Tabla3[[#This Row],[CLIENTES]],BOLIVARES[DOLARES2]) -> 0 | F16: =SUMIF(Tabla12[EMISOR2],Tabla3[[#This Row],[CLIENTES]],Tabla12[MONTO]) -> 0 | G16: =SUMIF(Tabla12[RECEPTOR],Tabla3[[#This Row],[CLIENTES]],Tabla12[MONTO2]) -> 0 | H16: =SUMIF(CAMBIOS[SOLIICTANTES],Tabla3[[#This Row],[CLIENTES]],CAMBIOS[DIFERENCIA])+ SUMIF(CAMBIOS[SOLIICTANTES],Tabla3[[#This Row],[CLIENTES]],CAMBIOS[COSTOS DE ENVÍO]) -> 0 | I16: =Tabla14[[#This Row],[PENDIENTE]]+Tabla14[[#This Row],[VENTA]]+Tabla14[[#This Row],[RETIRO]]-Tabla14[[#This Row],[COMPRA]]-Tabla14[[#This Row],[PAGO]]+Tabla14[[#This Row],[COMISION]] -> 0
B17: =Tabla3[[#This Row],[CLIENTES]] -> 0 | D17: =SUMIF(BOLIVARES[EMISOR],Tabla3[[#This Row],[CLIENTES]],BOLIVARES[DOLARES]) -> 0 | E17: =SUMIF(BOLIVARES[RECEPTOR],Tabla3[[#This Row],[CLIENTES]],BOLIVARES[DOLARES2]) -> 0 | F17: =SUMIF(Tabla12[EMISOR2],Tabla3[[#This Row],[CLIENTES]],Tabla12[MONTO]) -> 0 | G17: =SUMIF(Tabla12[RECEPTOR],Tabla3[[#This Row],[CLIENTES]],Tabla12[MONTO2]) -> 0 | H17: =SUMIF(CAMBIOS[SOLIICTANTES],Tabla3[[#This Row],[CLIENTES]],CAMBIOS[DIFERENCIA])+ SUMIF(CAMBIOS[SOLIICTANTES],Tabla3[[#This Row],[CLIENTES]],CAMBIOS[COSTOS DE ENVÍO]) -> 0 | I17: =Tabla14[[#This Row],[PENDIENTE]]+Tabla14[[#This Row],[VENTA]]+Tabla14[[#This Row],[RETIRO]]-Tabla14[[#This Row],[COMPRA]]-Tabla14[[#This Row],[PAGO]]+Tabla14[[#This Row],[COMISION]] -> 0
B18: =Tabla3[[#This Row],[CLIENTES]] -> 0 | D18: =SUMIF(BOLIVARES[EMISOR],Tabla3[[#This Row],[CLIENTES]],BOLIVARES[DOLARES]) -> 0 | E18: =SUMIF(BOLIVARES[RECEPTOR],Tabla3[[#This Row],[CLIENTES]],BOLIVARES[DOLARES2]) -> 0 | F18: =SUMIF(Tabla12[EMISOR2],Tabla3[[#This Row],[CLIENTES]],Tabla12[MONTO]) -> 0 | G18: =SUMIF(Tabla12[RECEPTOR],Tabla3[[#This Row],[CLIENTES]],Tabla12[MONTO2]) -> 0 | H18: =SUMIF(CAMBIOS[SOLIICTANTES],Tabla3[[#This Row],[CLIENTES]],CAMBIOS[DIFERENCIA])+ SUMIF(CAMBIOS[SOLIICTANTES],Tabla3[[#This Row],[CLIENTES]],CAMBIOS[COSTOS DE ENVÍO]) -> 0 | I18: =Tabla14[[#This Row],[PENDIENTE]]+Tabla14[[#This Row],[VENTA]]+Tabla14[[#This Row],[RETIRO]]-Tabla14[[#This Row],[COMPRA]]-Tabla14[[#This Row],[PAGO]]+Tabla14[[#This Row],[COMISION]] -> 0
B19: =Tabla3[[#This Row],[CLIENTES]] -> 0 | D19: =SUMIF(BOLIVARES[EMISOR],Tabla3[[#This Row],[CLIENTES]],BOLIVARES[DOLARES]) -> 0 | E19: =SUMIF(BOLIVARES[RECEPTOR],Tabla3[[#This Row],[CLIENTES]],BOLIVARES[DOLARES2]) -> 0 | F19: =SUMIF(Tabla12[EMISOR2],Tabla3[[#This Row],[CLIENTES]],Tabla12[MONTO]) -> 0 | G19: =SUMIF(Tabla12[RECEPTOR],Tabla3[[#This Row],[CLIENTES]],Tabla12[MONTO2]) -> 0 | H19: =SUMIF(CAMBIOS[SOLIICTANTES],Tabla3[[#This Row],[CLIENTES]],CAMBIOS[DIFERENCIA])+ SUMIF(CAMBIOS[SOLIICTANTES],Tabla3[[#This Row],[CLIENTES]],CAMBIOS[COSTOS DE ENVÍO]) -> 0 | I19: =Tabla14[[#This Row],[PENDIENTE]]+Tabla14[[#This Row],[VENTA]]+Tabla14[[#This Row],[RETIRO]]-Tabla14[[#This Row],[COMPRA]]-Tabla14[[#This Row],[PAGO]]+Tabla14[[#This Row],[COMISION]] -> 0
... B21: =Tabla3[[#This Row],[CLIENTES]] -> 0 | D21: =SUMIF(BOLIVARES[EMISOR],Tabla3[[#This Row],[CLIENTES]],BOLIVARES[DOLARES]) -> 0 | E21: =SUMIF(BOLIVARES[RECEPTOR],Tabla3[[#This Row],[CLIENTES]],BOLIVARES[DOLARES2]) -> 0 | F21: =SUMIF(Tabla12[EMISOR2],Tabla3[[#This Row],[CLIENTES]],Tabla12[MONTO]) -> 0 | G21: =SUMIF(Tabla12[RECEPTOR],Tabla3[[#This Row],[CLIENTES]],Tabla12[MONTO2]) -> 0 | H21: =SUMIF(CAMBIOS[SOLIICTANTES],Tabla3[[#This Row],[CLIENTES]],CAMBIOS[DIFERENCIA])+ SUMIF(CAMBIOS[SOLIICTANTES],Tabla3[[#This Row],[CLIENTES]],CAMBIOS[COSTOS DE ENVÍO]) -> 0 | I21: =Tabla14[[#This Row],[PENDIENTE]]+Tabla14[[#This Row],[VENTA]]+Tabla14[[#This Row],[RETIRO]]-Tabla14[[#This Row],[COMPRA]]-Tabla14[[#This Row],[PAGO]]+Tabla14[[#This Row],[COMISION]] -> 0
B22: =Tabla3[[#This Row],[CLIENTES]] -> 0 | D22: =SUMIF(BOLIVARES[EMISOR],Tabla3[[#This Row],[CLIENTES]],BOLIVARES[DOLARES]) -> 0 | E22: =SUMIF(BOLIVARES[RECEPTOR],Tabla3[[#This Row],[CLIENTES]],BOLIVARES[DOLARES2]) -> 0 | F22: =SUMIF(Tabla12[EMISOR2],Tabla3[[#This Row],[CLIENTES]],Tabla12[MONTO]) -> 0 | G22: =SUMIF(Tabla12[RECEPTOR],Tabla3[[#This Row],[CLIENTES]],Tabla12[MONTO2]) -> 0 | H22: =SUMIF(CAMBIOS[SOLIICTANTES],Tabla3[[#This Row],[CLIENTES]],CAMBIOS[DIFERENCIA])+ SUMIF(CAMBIOS[SOLIICTANTES],Tabla3[[#This Row],[CLIENTES]],CAMBIOS[COSTOS DE ENVÍO]) -> 0 | I22: =Tabla14[[#This Row],[PENDIENTE]]+Tabla14[[#This Row],[VENTA]]+Tabla14[[#This Row],[RETIRO]]-Tabla14[[#This Row],[COMPRA]]-Tabla14[[#This Row],[PAGO]]+Tabla14[[#This Row],[COMISION]] -> 0 | K22: GRUPO A
B23: =Tabla3[[#This Row],[CLIENTES]] -> 0 | D23: =SUMIF(BOLIVARES[EMISOR],Tabla3[[#This Row],[CLIENTES]],BOLIVARES[DOLARES]) -> 0 | E23: =SUMIF(BOLIVARES[RECEPTOR],Tabla3[[#This Row],[CLIENTES]],BOLIVARES[DOLARES2]) -> 0 | F23: =SUMIF(Tabla12[EMISOR2],Tabla3[[#This Row],[CLIENTES]],Tabla12[MONTO]) -> 0 | G23: =SUMIF(Tabla12[RECEPTOR],Tabla3[[#This Row],[CLIENTES]],Tabla12[MONTO2]) -> 0 | H23: =SUMIF(CAMBIOS[SOLIICTANTES],Tabla3[[#This Row],[CLIENTES]],CAMBIOS[DIFERENCIA])+ SUMIF(CAMBIOS[SOLIICTANTES],Tabla3[[#This Row],[CLIENTES]],CAMBIOS[COSTOS DE ENVÍO]) -> 0 | I23: =Tabla14[[#This Row],[PENDIENTE]]+Tabla14[[#This Row],[VENTA]]+Tabla14[[#This Row],[RETIRO]]-Tabla14[[#This Row],[COMPRA]]-Tabla14[[#This Row],[PAGO]]+Tabla14[[#This Row],[COMISION]] -> 0
B24: =Tabla3[[#This Row],[CLIENTES]] -> 0 | D24: =SUMIF(BOLIVARES[EMISOR],Tabla3[[#This Row],[CLIENTES]],BOLIVARES[DOLARES]) -> 0 | E24: =SUMIF(BOLIVARES[RECEPTOR],Tabla3[[#This Row],[CLIENTES]],BOLIVARES[DOLARES2]) -> 0 | F24: =SUMIF(Tabla12[EMISOR2],Tabla3[[#This Row],[CLIENTES]],Tabla12[MONTO]) -> 0 | G24: =SUMIF(Tabla12[RECEPTOR],Tabla3[[#This Row],[CLIENTES]],Tabla12[MONTO2]) -> 0 | H24: =SUMIF(CAMBIOS[SOLIICTANTES],Tabla3[[#This Row],[CLIENTES]],CAMBIOS[DIFERENCIA])+ SUMIF(CAMBIOS[SOLIICTANTES],Tabla3[[#This Row],[CLIENTES]],CAMBIOS[COSTOS DE ENVÍO]) -> 0 | I24: =Tabla14[[#This Row],[PENDIENTE]]+Tabla14[[#This Row],[VENTA]]+Tabla14[[#This Row],[RETIRO]]-Tabla14[[#This Row],[COMPRA]]-Tabla14[[#This Row],[PAGO]]+Tabla14[[#This Row],[COMISION]] -> 0
B25: =Tabla3[[#This Row],[CLIENTES]] -> 0 | D25: =SUMIF(BOLIVARES[EMISOR],Tabla3[[#This Row],[CLIENTES]],BOLIVARES[DOLARES]) -> 0 | E25: =SUMIF(BOLIVARES[RECEPTOR],Tabla3[[#This Row],[CLIENTES]],BOLIVARES[DOLARES2]) -> 0 | F25: =SUMIF(Tabla12[EMISOR2],Tabla3[[#This Row],[CLIENTES]],Tabla12[MONTO]) -> 0 | G25: =SUMIF(Tabla12[RECEPTOR],Tabla3[[#This Row],[CLIENTES]],Tabla12[MONTO2]) -> 0 | H25: =SUMIF(CAMBIOS[SOLIICTANTES],Tabla3[[#This Row],[CLIENTES]],CAMBIOS[DIFERENCIA])+ SUMIF(CAMBIOS[SOLIICTANTES],Tabla3[[#This Row],[CLIENTES]],CAMBIOS[COSTOS DE ENVÍO]) -> 0 | I25: =Tabla14[[#This Row],[PENDIENTE]]+Tabla14[[#This Row],[VENTA]]+Tabla14[[#This Row],[RETIRO]]-Tabla14[[#This Row],[COMPRA]]-Tabla14[[#This Row],[PAGO]]+Tabla14[[#This Row],[COMISION]] -> 0
B26: =Tabla3[[#This Row],[CLIENTES]] -> 0 | D26: =SUMIF(BOLIVARES[EMISOR],Tabla3[[#This Row],[CLIENTES]],BOLIVARES[DOLARES]) -> 0 | E26: =SUMIF(BOLIVARES[RECEPTOR],Tabla3[[#This Row],[CLIENTES]],BOLIVARES[DOLARES2]) -> 0 | F26: =SUMIF(Tabla12[EMISOR2],Tabla3[[#This Row],[CLIENTES]],Tabla12[MONTO]) -> 0 | G26: =SUMIF(Tabla12[RECEPTOR],Tabla3[[#This Row],[CLIENTES]],Tabla12[MONTO2]) -> 0 | H26: =SUMIF(CAMBIOS[SOLIICTANTES],Tabla3[[#This Row],[CLIENTES]],CAMBIOS[DIFERENCIA])+ SUMIF(CAMBIOS[SOLIICTANTES],Tabla3[[#This Row],[CLIENTES]],CAMBIOS[COSTOS DE ENVÍO]) -> 0 | I26: =Tabla14[[#This Row],[PENDIENTE]]+Tabla14[[#This Row],[VENTA]]+Tabla14[[#This Row],[RETIRO]]-Tabla14[[#This Row],[COMPRA]]-Tabla14[[#This Row],[PAGO]]+Tabla14[[#This Row],[COMISION]] -> 0
B27: =Tabla3[[#This Row],[CLIENTES]] -> 0 | D27: =SUMIF(BOLIVARES[EMISOR],Tabla3[[#This Row],[CLIENTES]],BOLIVARES[DOLARES]) -> 0 | E27: =SUMIF(BOLIVARES[RECEPTOR],Tabla3[[#This Row],[CLIENTES]],BOLIVARES[DOLARES2]) -> 0 | F27: =SUMIF(Tabla12[EMISOR2],Tabla3[[#This Row],[CLIENTES]],Tabla12[MONTO]) -> 0 | G27: =SUMIF(Tabla12[RECEPTOR],Tabla3[[#This Row],[CLIENTES]],Tabla12[MONTO2]) -> 0 | H27: =SUMIF(CAMBIOS[SOLIICTANTES],Tabla3[[#This Row],[CLIENTES]],CAMBIOS[DIFERENCIA])+ SUMIF(CAMBIOS[SOLIICTANTES],Tabla3[[#This Row],[CLIENTES]],CAMBIOS[COSTOS DE ENVÍO]) -> 0 | I27: =Tabla14[[#This Row],[PENDIENTE]]+Tabla14[[#This Row],[VENTA]]+Tabla14[[#This Row],[RETIRO]]-Tabla14[[#This Row],[COMPRA]]-Tabla14[[#This Row],[PAGO]]+Tabla14[[#This Row],[COMISION]] -> 0
B28: =Tabla3[[#This Row],[CLIENTES]] -> 0 | D28: =SUMIF(BOLIVARES[EMISOR],Tabla3[[#This Row],[CLIENTES]],BOLIVARES[DOLARES]) -> 0 | E28: =SUMIF(BOLIVARES[RECEPTOR],Tabla3[[#This Row],[CLIENTES]],BOLIVARES[DOLARES2]) -> 0 | F28: =SUMIF(Tabla12[EMISOR2],Tabla3[[#This Row],[CLIENTES]],Tabla12[MONTO]) -> 0 | G28: =SUMIF(Tabla12[RECEPTOR],Tabla3[[#This Row],[CLIENTES]],Tabla12[MONTO2]) -> 0 | H28: =SUMIF(CAMBIOS[SOLIICTANTES],Tabla3[[#This Row],[CLIENTES]],CAMBIOS[DIFERENCIA])+ SUMIF(CAMBIOS[SOLIICTANTES],Tabla3[[#This Row],[CLIENTES]],CAMBIOS[COSTOS DE ENVÍO]) -> 0 | I28: =Tabla14[[#This Row],[PENDIENTE]]+Tabla14[[#This Row],[VENTA]]+Tabla14[[#This Row],[RETIRO]]-Tabla14[[#This Row],[COMPRA]]-Tabla14[[#This Row],[PAGO]]+Tabla14[[#This Row],[COMISION]] -> 0
B29: =Tabla3[[#This Row],[CLIENTES]] -> 0 | D29: =SUMIF(BOLIVARES[EMISOR],Tabla3[[#This Row],[CLIENTES]],BOLIVARES[DOLARES]) -> 0 | E29: =SUMIF(BOLIVARES[RECEPTOR],Tabla3[[#This Row],[CLIENTES]],BOLIVARES[DOLARES2]) -> 0 | F29: =SUMIF(Tabla12[EMISOR2],Tabla3[[#This Row],[CLIENTES]],Tabla12[MONTO]) -> 0 | G29: =SUMIF(Tabla12[RECEPTOR],Tabla3[[#This Row],[CLIENTES]],Tabla12[MONTO2]) -> 0 | H29: =SUMIF(CAMBIOS[SOLIICTANTES],Tabla3[[#This Row],[CLIENTES]],CAMBIOS[DIFERENCIA])+ SUMIF(CAMBIOS[SOLIICTANTES],Tabla3[[#This Row],[CLIENTES]],CAMBIOS[COSTOS DE ENVÍO]) -> 0 | I29: =Tabla14[[#This Row],[PENDIENTE]]+Tabla14[[#This Row],[VENTA]]+Tabla14[[#This Row],[RETIRO]]-Tabla14[[#This Row],[COMPRA]]-Tabla14[[#This Row],[PAGO]]+Tabla14[[#This Row],[COMISION]] -> 0
B30: =Tabla3[[#This Row],[CLIENTES]] -> 0 | D30: =SUMIF(BOLIVARES[EMISOR],Tabla3[[#This Row],[CLIENTES]],BOLIVARES[DOLARES]) -> 0 | E30: =SUMIF(BOLIVARES[RECEPTOR],Tabla3[[#This Row],[CLIENTES]],BOLIVARES[DOLARES2]) -> 0 | F30: =SUMIF(Tabla12[EMISOR2],Tabla3[[#This Row],[CLIENTES]],Tabla12[MONTO]) -> 0 | G30: =SUMIF(Tabla12[RECEPTOR],Tabla3[[#This Row],[CLIENTES]],Tabla12[MONTO2]) -> 0 | H30: =SUMIF(CAMBIOS[SOLIICTANTES],Tabla3[[#This Row],[CLIENTES]],CAMBIOS[DIFERENCIA])+ SUMIF(CAMBIOS[SOLIICTANTES],Tabla3[[#This Row],[CLIENTES]],CAMBIOS[COSTOS DE ENVÍO]) -> 0 | I30: =Tabla14[[#This Row],[PENDIENTE]]+Tabla14[[#This Row],[VENTA]]+Tabla14[[#This Row],[RETIRO]]-Tabla14[[#This Row],[COMPRA]]-Tabla14[[#This Row],[PAGO]]+Tabla14[[#This Row],[COMISION]] -> 0
B31: =Tabla3[[#This Row],[CLIENTES]] -> 0 | D31: =SUMIF(BOLIVARES[EMISOR],Tabla3[[#This Row],[CLIENTES]],BOLIVARES[DOLARES]) -> 0 | E31: =SUMIF(BOLIVARES[RECEPTOR],Tabla3[[#This Row],[CLIENTES]],BOLIVARES[DOLARES2]) -> 0 | F31: =SUMIF(Tabla12[EMISOR2],Tabla3[[#This Row],[CLIENTES]],Tabla12[MONTO]) -> 0 | G31: =SUMIF(Tabla12[RECEPTOR],Tabla3[[#This Row],[CLIENTES]],Tabla12[MONTO2]) -> 0 | H31: =SUMIF(CAMBIOS[SOLIICTANTES],Tabla3[[#This Row],[CLIENTES]],CAMBIOS[DIFERENCIA])+ SUMIF(CAMBIOS[SOLIICTANTES],Tabla3[[#This Row],[CLIENTES]],CAMBIOS[COSTOS DE ENVÍO]) -> 0 | I31: =Tabla14[[#This Row],[PENDIENTE]]+Tabla14[[#This Row],[VENTA]]+Tabla14[[#This Row],[RETIRO]]-Tabla14[[#This Row],[COMPRA]]-Tabla14[[#This Row],[PAGO]]+Tabla14[[#This Row],[COMISION]] -> 0
B32: =Tabla3[[#This Row],[CLIENTES]] -> 0 | D32: =SUMIF(BOLIVARES[EMISOR],Tabla3[[#This Row],[CLIENTES]],BOLIVARES[DOLARES]) -> 0 | E32: =SUMIF(BOLIVARES[RECEPTOR],Tabla3[[#This Row],[CLIENTES]],BOLIVARES[DOLARES2]) -> 0 | F32: =SUMIF(Tabla12[EMISOR2],Tabla3[[#This Row],[CLIENTES]],Tabla12[MONTO]) -> 0 | G32: =SUMIF(Tabla12[RECEPTOR],Tabla3[[#This Row],[CLIENTES]],Tabla12[MONTO2]) -> 0 | H32: =SUMIF(CAMBIOS[SOLIICTANTES],Tabla3[[#This Row],[CLIENTES]],CAMBIOS[DIFERENCIA])+ SUMIF(CAMBIOS[SOLIICTANTES],Tabla3[[#This Row],[CLIENTES]],CAMBIOS[COSTOS DE ENVÍO]) -> 0 | I32: =Tabla14[[#This Row],[PENDIENTE]]+Tabla14[[#This Row],[VENTA]]+Tabla14[[#This Row],[RETIRO]]-Tabla14[[#This Row],[COMPRA]]-Tabla14[[#This Row],[PAGO]]+Tabla14[[#This Row],[COMISION]] -> 0
B33: =Tabla3[[#This Row],[CLIENTES]] -> 0 | D33: =SUMIF(BOLIVARES[EMISOR],Tabla3[[#This Row],[CLIENTES]],BOLIVARES[DOLARES]) -> 0 | E33: =SUMIF(BOLIVARES[RECEPTOR],Tabla3[[#This Row],[CLIENTES]],BOLIVARES[DOLARES2]) -> 0 | F33: =SUMIF(Tabla12[EMISOR2],Tabla3[[#This Row],[CLIENTES]],Tabla12[MONTO]) -> 0 | G33: =SUMIF(Tabla12[RECEPTOR],Tabla3[[#This Row],[CLIENTES]],Tabla12[MONTO2]) -> 0 | H33: =SUMIF(CAMBIOS[SOLIICTANTES],Tabla3[[#This Row],[CLIENTES]],CAMBIOS[DIFERENCIA])+ SUMIF(CAMBIOS[SOLIICTANTES],Tabla3[[#This Row],[CLIENTES]],CAMBIOS[COSTOS DE ENVÍO]) -> 0 | I33: =Tabla14[[#This Row],[PENDIENTE]]+Tabla14[[#This Row],[VENTA]]+Tabla14[[#This Row],[RETIRO]]-Tabla14[[#This Row],[COMPRA]]-Tabla14[[#This Row],[PAGO]]+Tabla14[[#This Row],[COMISION]] -> 0
B34: =Tabla3[[#This Row],[CLIENTES]] -> 0 | D34: =SUMIF(BOLIVARES[EMISOR],Tabla3[[#This Row],[CLIENTES]],BOLIVARES[DOLARES]) -> 0 | E34: =SUMIF(BOLIVARES[RECEPTOR],Tabla3[[#This Row],[CLIENTES]],BOLIVARES[DOLARES2]) -> 0 | F34: =SUMIF(Tabla12[EMISOR2],Tabla3[[#This Row],[CLIENTES]],Tabla12[MONTO]) -> 0 | G34: =SUMIF(Tabla12[RECEPTOR],Tabla3[[#This Row],[CLIENTES]],Tabla12[MONTO2]) -> 0 | H34: =SUMIF(CAMBIOS[SOLIICTANTES],Tabla3[[#This Row],[CLIENTES]],CAMBIOS[DIFERENCIA])+ SUMIF(CAMBIOS[SOLIICTANTES],Tabla3[[#This Row],[CLIENTES]],CAMBIOS[COSTOS DE ENVÍO]) -> 0 | I34: =Tabla14[[#This Row],[PENDIENTE]]+Tabla14[[#This Row],[VENTA]]+Tabla14[[#This Row],[RETIRO]]-Tabla14[[#This Row],[COMPRA]]-Tabla14[[#This Row],[PAGO]]+Tabla14[[#This Row],[COMISION]] -> 0
B35: =Tabla3[[#This Row],[CLIENTES]] -> 0 | D35: =SUMIF(BOLIVARES[EMISOR],Tabla3[[#This Row],[CLIENTES]],BOLIVARES[DOLARES]) -> 0 | E35: =SUMIF(BOLIVARES[RECEPTOR],Tabla3[[#This Row],[CLIENTES]],BOLIVARES[DOLARES2]) -> 0 | F35: =SUMIF(Tabla12[EMISOR2],Tabla3[[#This Row],[CLIENTES]],Tabla12[MONTO]) -> 0 | G35: =SUMIF(Tabla12[RECEPTOR],Tabla3[[#This Row],[CLIENTES]],Tabla12[MONTO2]) -> 0 | H35: =SUMIF(CAMBIOS[SOLIICTANTES],Tabla3[[#This Row],[CLIENTES]],CAMBIOS[DIFERENCIA])+ SUMIF(CAMBIOS[SOLIICTANTES],Tabla3[[#This Row],[CLIENTES]],CAMBIOS[COSTOS DE ENVÍO]) -> 0 | I35: =Tabla14[[#This Row],[PENDIENTE]]+Tabla14[[#This Row],[VENTA]]+Tabla14[[#This Row],[RETIRO]]-Tabla14[[#This Row],[COMPRA]]-Tabla14[[#This Row],[PAGO]]+Tabla14[[#This Row],[COMISION]] -> 0
B36: =Tabla3[[#This Row],[CLIENTES]] -> 0 | D36: =SUMIF(BOLIVARES[EMISOR],Tabla3[[#This Row],[CLIENTES]],BOLIVARES[DOLARES]) -> 0 | E36: =SUMIF(BOLIVARES[RECEPTOR],Tabla3[[#This Row],[CLIENTES]],BOLIVARES[DOLARES2]) -> 0 | F36: =SUMIF(Tabla12[EMISOR2],Tabla3[[#This Row],[CLIENTES]],Tabla12[MONTO]) -> 0 | G36: =SUMIF(Tabla12[RECEPTOR],Tabla3[[#This Row],[CLIENTES]],Tabla12[MONTO2]) -> 0 | H36: =SUMIF(CAMBIOS[SOLIICTANTES],Tabla3[[#This Row],[CLIENTES]],CAMBIOS[DIFERENCIA])+ SUMIF(CAMBIOS[SOLIICTANTES],Tabla3[[#This Row],[CLIENTES]],CAMBIOS[COSTOS DE ENVÍO]) -> 0 | I36: =Tabla14[[#This Row],[PENDIENTE]]+Tabla14[[#This Row],[VENTA]]+Tabla14[[#This Row],[RETIRO]]-Tabla14[[#This Row],[COMPRA]]-Tabla14[[#This Row],[PAGO]]+Tabla14[[#This Row],[COMISION]] -> 0 | K36: GRUPO A
B37: =Tabla3[[#This Row],[CLIENTES]] -> 0 | D37: =SUMIF(BOLIVARES[EMISOR],Tabla3[[#This Row],[CLIENTES]],BOLIVARES[DOLARES]) -> 0 | E37: =SUMIF(BOLIVARES[RECEPTOR],Tabla3[[#This Row],[CLIENTES]],BOLIVARES[DOLARES2]) -> 0 | F37: =SUMIF(Tabla12[EMISOR2],Tabla3[[#This Row],[CLIENTES]],Tabla12[MONTO]) -> 0 | G37: =SUMIF(Tabla12[RECEPTOR],Tabla3[[#This Row],[CLIENTES]],Tabla12[MONTO2]) -> 0 | H37: =SUMIF(CAMBIOS[SOLIICTANTES],Tabla3[[#This Row],[CLIENTES]],CAMBIOS[DIFERENCIA])+ SUMIF(CAMBIOS[SOLIICTANTES],Tabla3[[#This Row],[CLIENTES]],CAMBIOS[COSTOS DE ENVÍO]) -> 0 | I37: =Tabla14[[#This Row],[PENDIENTE]]+Tabla14[[#This Row],[VENTA]]+Tabla14[[#This Row],[RETIRO]]-Tabla14[[#This Row],[COMPRA]]-Tabla14[[#This Row],[PAGO]]+Tabla14[[#This Row],[COMISION]] -> 0
B38: =Tabla3[[#This Row],[CLIENTES]] -> 0 | D38: =SUMIF(BOLIVARES[EMISOR],Tabla3[[#This Row],[CLIENTES]],BOLIVARES[DOLARES]) -> 0 | E38: =SUMIF(BOLIVARES[RECEPTOR],Tabla3[[#This Row],[CLIENTES]],BOLIVARES[DOLARES2]) -> 0 | F38: =SUMIF(Tabla12[EMISOR2],Tabla3[[#This Row],[CLIENTES]],Tabla12[MONTO]) -> 0 | G38: =SUMIF(Tabla12[RECEPTOR],Tabla3[[#This Row],[CLIENTES]],Tabla12[MONTO2]) -> 0 | H38: =SUMIF(CAMBIOS[SOLIICTANTES],Tabla3[[#This Row],[CLIENTES]],CAMBIOS[DIFERENCIA])+ SUMIF(CAMBIOS[SOLIICTANTES],Tabla3[[#This Row],[CLIENTES]],CAMBIOS[COSTOS DE ENVÍO]) -> 0 | I38: =Tabla14[[#This Row],[PENDIENTE]]+Tabla14[[#This Row],[VENTA]]+Tabla14[[#This Row],[RETIRO]]-Tabla14[[#This Row],[COMPRA]]-Tabla14[[#This Row],[PAGO]]+Tabla14[[#This Row],[COMISION]] -> 0
B39: =Tabla3[[#This Row],[CLIENTES]] -> 0 | D39: =SUMIF(BOLIVARES[EMISOR],Tabla3[[#This Row],[CLIENTES]],BOLIVARES[DOLARES]) -> 0 | E39: =SUMIF(BOLIVARES[RECEPTOR],Tabla3[[#This Row],[CLIENTES]],BOLIVARES[DOLARES2]) -> 0 | F39: =SUMIF(Tabla12[EMISOR2],Tabla3[[#This Row],[CLIENTES]],Tabla12[MONTO]) -> 0 | G39: =SUMIF(Tabla12[RECEPTOR],Tabla3[[#This Row],[CLIENTES]],Tabla12[MONTO2]) -> 0 | H39: =SUMIF(CAMBIOS[SOLIICTANTES],Tabla3[[#This Row],[CLIENTES]],CAMBIOS[DIFERENCIA])+ SUMIF(CAMBIOS[SOLIICTANTES],Tabla3[[#This Row],[CLIENTES]],CAMBIOS[COSTOS DE ENVÍO]) -> 0 | I39: =Tabla14[[#This Row],[PENDIENTE]]+Tabla14[[#This Row],[VENTA]]+Tabla14[[#This Row],[RETIRO]]-Tabla14[[#This Row],[COMPRA]]-Tabla14[[#This Row],[PAGO]]+Tabla14[[#This Row],[COMISION]] -> 0
B40: =Tabla3[[#This Row],[CLIENTES]] -> 0 | D40: =SUMIF(BOLIVARES[EMISOR],Tabla3[[#This Row],[CLIENTES]],BOLIVARES[DOLARES]) -> 0 | E40: =SUMIF(BOLIVARES[RECEPTOR],Tabla3[[#This Row],[CLIENTES]],BOLIVARES[DOLARES2]) -> 0 | F40: =SUMIF(Tabla12[EMISOR2],Tabla3[[#This Row],[CLIENTES]],Tabla12[MONTO]) -> 0 | G40: =SUMIF(Tabla12[RECEPTOR],Tabla3[[#This Row],[CLIENTES]],Tabla12[MONTO2]) -> 0 | H40: =SUMIF(CAMBIOS[SOLIICTANTES],Tabla3[[#This Row],[CLIENTES]],CAMBIOS[DIFERENCIA])+ SUMIF(CAMBIOS[SOLIICTANTES],Tabla3[[#This Row],[CLIENTES]],CAMBIOS[COSTOS DE ENVÍO]) -> 0 | I40: =Tabla14[[#This Row],[PENDIENTE]]+Tabla14[[#This Row],[VENTA]]+Tabla14[[#This Row],[RETIRO]]-Tabla14[[#This Row],[COMPRA]]-Tabla14[[#This Row],[PAGO]]+Tabla14[[#This Row],[COMISION]] -> 0
B41: =Tabla3[[#This Row],[CLIENTES]] -> 0 | D41: =SUMIF(BOLIVARES[EMISOR],Tabla3[[#This Row],[CLIENTES]],BOLIVARES[DOLARES]) -> 0 | E41: =SUMIF(BOLIVARES[RECEPTOR],Tabla3[[#This Row],[CLIENTES]],BOLIVARES[DOLARES2]) -> 0 | F41: =SUMIF(Tabla12[EMISOR2],Tabla3[[#This Row],[CLIENTES]],Tabla12[MONTO]) -> 0 | G41: =SUMIF(Tabla12[RECEPTOR],Tabla3[[#This Row],[CLIENTES]],Tabla12[MONTO2]) -> 0 | H41: =SUMIF(CAMBIOS[SOLIICTANTES],Tabla3[[#This Row],[CLIENTES]],CAMBIOS[DIFERENCIA])+ SUMIF(CAMBIOS[SOLIICTANTES],Tabla3[[#This Row],[CLIENTES]],CAMBIOS[COSTOS DE ENVÍO]) -> 0 | I41: =Tabla14[[#This Row],[PENDIENTE]]+Tabla14[[#This Row],[VENTA]]+Tabla14[[#This Row],[RETIRO]]-Tabla14[[#This Row],[COMPRA]]-Tabla14[[#This Row],[PAGO]]+Tabla14[[#This Row],[COMISION]] -> 0
B42: =Tabla3[[#This Row],[CLIENTES]] -> 0 | D42: =SUMIF(BOLIVARES[EMISOR],Tabla3[[#This Row],[CLIENTES]],BOLIVARES[DOLARES]) -> 0 | E42: =SUMIF(BOLIVARES[RECEPTOR],Tabla3[[#This Row],[CLIENTES]],BOLIVARES[DOLARES2]) -> 0 | F42: =SUMIF(Tabla12[EMISOR2],Tabla3[[#This Row],[CLIENTES]],Tabla12[MONTO]) -> 0 | G42: =SUMIF(Tabla12[RECEPTOR],Tabla3[[#This Row],[CLIENTES]],Tabla12[MONTO2]) -> 0 | H42: =SUMIF(CAMBIOS[SOLIICTANTES],Tabla3[[#This Row],[CLIENTES]],CAMBIOS[DIFERENCIA])+ SUMIF(CAMBIOS[SOLIICTANTES],Tabla3[[#This Row],[CLIENTES]],CAMBIOS[COSTOS DE ENVÍO]) -> 0 | I42: =Tabla14[[#This Row],[PENDIENTE]]+Tabla14[[#This Row],[VENTA]]+Tabla14[[#This Row],[RETIRO]]-Tabla14[[#This Row],[COMPRA]]-Tabla14[[#This Row],[PAGO]]+Tabla14[[#This Row],[COMISION]] -> 0
B43: =Tabla3[[#This Row],[CLIENTES]] -> 0 | D43: =SUMIF(BOLIVARES[EMISOR],Tabla3[[#This Row],[CLIENTES]],BOLIVARES[DOLARES]) -> 0 | E43: =SUMIF(BOLIVARES[RECEPTOR],Tabla3[[#This Row],[CLIENTES]],BOLIVARES[DOLARES2]) -> 0 | F43: =SUMIF(Tabla12[EMISOR2],Tabla3[[#This Row],[CLIENTES]],Tabla12[MONTO]) -> 0 | G43: =SUMIF(Tabla12[RECEPTOR],Tabla3[[#This Row],[CLIENTES]],Tabla12[MONTO2]) -> 0 | H43: =SUMIF(CAMBIOS[SOLIICTANTES],Tabla3[[#This Row],[CLIENTES]],CAMBIOS[DIFERENCIA])+ SUMIF(CAMBIOS[SOLIICTANTES],Tabla3[[#This Row],[CLIENTES]],CAMBIOS[COSTOS DE ENVÍO]) -> 0 | I43: =Tabla14[[#This Row],[PENDIENTE]]+Tabla14[[#This Row],[VENTA]]+Tabla14[[#This Row],[RETIRO]]-Tabla14[[#This Row],[COMPRA]]-Tabla14[[#This Row],[PAGO]]+Tabla14[[#This Row],[COMISION]] -> 0
B44: =Tabla3[[#This Row],[CLIENTES]] -> 0 | D44: =SUMIF(BOLIVARES[EMISOR],Tabla3[[#This Row],[CLIENTES]],BOLIVARES[DOLARES]) -> 0 | E44: =SUMIF(BOLIVARES[RECEPTOR],Tabla3[[#This Row],[CLIENTES]],BOLIVARES[DOLARES2]) -> 0 | F44: =SUMIF(Tabla12[EMISOR2],Tabla3[[#This Row],[CLIENTES]],Tabla12[MONTO]) -> 0 | G44: =SUMIF(Tabla12[RECEPTOR],Tabla3[[#This Row],[CLIENTES]],Tabla12[MONTO2]) -> 0 | H44: =SUMIF(CAMBIOS[SOLIICTANTES],Tabla3[[#This Row],[CLIENTES]],CAMBIOS[DIFERENCIA])+ SUMIF(CAMBIOS[SOLIICTANTES],Tabla3[[#This Row],[CLIENTES]],CAMBIOS[COSTOS DE ENVÍO]) -> 0 | I44: =Tabla14[[#This Row],[PENDIENTE]]+Tabla14[[#This Row],[VENTA]]+Tabla14[[#This Row],[RETIRO]]-Tabla14[[#This Row],[COMPRA]]-Tabla14[[#This Row],[PAGO]]+Tabla14[[#This Row],[COMISION]] -> 0
B45: =Tabla3[[#This Row],[CLIENTES]] -> 0 | D45: =SUMIF(BOLIVARES[EMISOR],Tabla3[[#This Row],[CLIENTES]],BOLIVARES[DOLARES]) -> 0 | E45: =SUMIF(BOLIVARES[RECEPTOR],Tabla3[[#This Row],[CLIENTES]],BOLIVARES[DOLARES2]) -> 0 | F45: =SUMIF(Tabla12[EMISOR2],Tabla3[[#This Row],[CLIENTES]],Tabla12[MONTO]) -> 0 | G45: =SUMIF(Tabla12[RECEPTOR],Tabla3[[#This Row],[CLIENTES]],Tabla12[MONTO2]) -> 0 | H45: =SUMIF(CAMBIOS[SOLIICTANTES],Tabla3[[#This Row],[CLIENTES]],CAMBIOS[DIFERENCIA])+ SUMIF(CAMBIOS[SOLIICTANTES],Tabla3[[#This Row],[CLIENTES]],CAMBIOS[COSTOS DE ENVÍO]) -> 0 | I45: =Tabla14[[#This Row],[PENDIENTE]]+Tabla14[[#This Row],[VENTA]]+Tabla14[[#This Row],[RETIRO]]-Tabla14[[#This Row],[COMPRA]]-Tabla14[[#This Row],[PAGO]]+Tabla14[[#This Row],[COMISION]] -> 0
B46: =Tabla3[[#This Row],[CLIENTES]] -> 0 | D46: =SUMIF(BOLIVARES[EMISOR],Tabla3[[#This Row],[CLIENTES]],BOLIVARES[DOLARES]) -> 0 | E46: =SUMIF(BOLIVARES[RECEPTOR],Tabla3[[#This Row],[CLIENTES]],BOLIVARES[DOLARES2]) -> 0 | F46: =SUMIF(Tabla12[EMISOR2],Tabla3[[#This Row],[CLIENTES]],Tabla12[MONTO]) -> 0 | G46: =SUMIF(Tabla12[RECEPTOR],Tabla3[[#This Row],[CLIENTES]],Tabla12[MONTO2]) -> 0 | H46: =SUMIF(CAMBIOS[SOLIICTANTES],Tabla3[[#This Row],[CLIENTES]],CAMBIOS[DIFERENCIA])+ SUMIF(CAMBIOS[SOLIICTANTES],Tabla3[[#This Row],[CLIENTES]],CAMBIOS[COSTOS DE ENVÍO]) -> 0 | I46: =Tabla14[[#This Row],[PENDIENTE]]+Tabla14[[#This Row],[VENTA]]+Tabla14[[#This Row],[RETIRO]]-Tabla14[[#This Row],[COMPRA]]-Tabla14[[#This Row],[PAGO]]+Tabla14[[#This Row],[COMISION]] -> 0
B47: =Tabla3[[#This Row],[CLIENTES]] -> 0 | D47: =SUMIF(BOLIVARES[EMISOR],Tabla3[[#This Row],[CLIENTES]],BOLIVARES[DOLARES]) -> 0 | E47: =SUMIF(BOLIVARES[RECEPTOR],Tabla3[[#This Row],[CLIENTES]],BOLIVARES[DOLARES2]) -> 0 | F47: =SUMIF(Tabla12[EMISOR2],Tabla3[[#This Row],[CLIENTES]],Tabla12[MONTO]) -> 0 | G47: =SUMIF(Tabla12[RECEPTOR],Tabla3[[#This Row],[CLIENTES]],Tabla12[MONTO2]) -> 0 | H47: =SUMIF(CAMBIOS[SOLIICTANTES],Tabla3[[#This Row],[CLIENTES]],CAMBIOS[DIFERENCIA])+ SUMIF(CAMBIOS[SOLIICTANTES],Tabla3[[#This Row],[CLIENTES]],CAMBIOS[COSTOS DE ENVÍO]) -> 0 | I47: =Tabla14[[#This Row],[PENDIENTE]]+Tabla14[[#This Row],[VENTA]]+Tabla14[[#This Row],[RETIRO]]-Tabla14[[#This Row],[COMPRA]]-Tabla14[[#This Row],[PAGO]]+Tabla14[[#This Row],[COMISION]] -> 0 | K47: GRUPO A
B48: =Tabla3[[#This Row],[CLIENTES]] -> 0 | D48: =SUMIF(BOLIVARES[EMISOR],Tabla3[[#This Row],[CLIENTES]],BOLIVARES[DOLARES]) -> 0 | E48: =SUMIF(BOLIVARES[RECEPTOR],Tabla3[[#This Row],[CLIENTES]],BOLIVARES[DOLARES2]) -> 0 | F48: =SUMIF(Tabla12[EMISOR2],Tabla3[[#This Row],[CLIENTES]],Tabla12[MONTO]) -> 0 | G48: =SUMIF(Tabla12[RECEPTOR],Tabla3[[#This Row],[CLIENTES]],Tabla12[MONTO2]) -> 0 | H48: =SUMIF(CAMBIOS[SOLIICTANTES],Tabla3[[#This Row],[CLIENTES]],CAMBIOS[DIFERENCIA])+ SUMIF(CAMBIOS[SOLIICTANTES],Tabla3[[#This Row],[CLIENTES]],CAMBIOS[COSTOS DE ENVÍO]) -> 0 | I48: =Tabla14[[#This Row],[PENDIENTE]]+Tabla14[[#This Row],[VENTA]]+Tabla14[[#This Row],[RETIRO]]-Tabla14[[#This Row],[COMPRA]]-Tabla14[[#This Row],[PAGO]]+Tabla14[[#This Row],[COMISION]] -> 0 | K48: GRUPO A
B49: =Tabla3[[#This Row],[CLIENTES]] -> 0 | D49: =SUMIF(BOLIVARES[EMISOR],Tabla3[[#This Row],[CLIENTES]],BOLIVARES[DOLARES]) -> 0 | E49: =SUMIF(BOLIVARES[RECEPTOR],Tabla3[[#This Row],[CLIENTES]],BOLIVARES[DOLARES2]) -> 0 | F49: =SUMIF(Tabla12[EMISOR2],Tabla3[[#This Row],[CLIENTES]],Tabla12[MONTO]) -> 0 | G49: =SUMIF(Tabla12[RECEPTOR],Tabla3[[#This Row],[CLIENTES]],Tabla12[MONTO2]) -> 0 | H49: =SUMIF(CAMBIOS[SOLIICTANTES],Tabla3[[#This Row],[CLIENTES]],CAMBIOS[DIFERENCIA])+ SUMIF(CAMBIOS[SOLIICTANTES],Tabla3[[#This Row],[CLIENTES]],CAMBIOS[COSTOS DE ENVÍO]) -> 0 | I49: =Tabla14[[#This Row],[PENDIENTE]]+Tabla14[[#This Row],[VENTA]]+Tabla14[[#This Row],[RETIRO]]-Tabla14[[#This Row],[COMPRA]]-Tabla14[[#This Row],[PAGO]]+Tabla14[[#This Row],[COMISION]] -> 0
B50: =Tabla3[[#This Row],[CLIENTES]] -> 0 | D50: =SUMIF(BOLIVARES[EMISOR],Tabla3[[#This Row],[CLIENTES]],BOLIVARES[DOLARES]) -> 0 | E50: =SUMIF(BOLIVARES[RECEPTOR],Tabla3[[#This Row],[CLIENTES]],BOLIVARES[DOLARES2]) -> 0 | F50: =SUMIF(Tabla12[EMISOR2],Tabla3[[#This Row],[CLIENTES]],Tabla12[MONTO]) -> 0 | G50: =SUMIF(Tabla12[RECEPTOR],Tabla3[[#This Row],[CLIENTES]],Tabla12[MONTO2]) -> 0 | H50: =SUMIF(CAMBIOS[SOLIICTANTES],Tabla3[[#This Row],[CLIENTES]],CAMBIOS[DIFERENCIA])+ SUMIF(CAMBIOS[SOLIICTANTES],Tabla3[[#This Row],[CLIENTES]],CAMBIOS[COSTOS DE ENVÍO]) -> 0 | I50: =Tabla14[[#This Row],[PENDIENTE]]+Tabla14[[#This Row],[VENTA]]+Tabla14[[#This Row],[RETIRO]]-Tabla14[[#This Row],[COMPRA]]-Tabla14[[#This Row],[PAGO]]+Tabla14[[#This Row],[COMISION]] -> 0
B51: =Tabla3[[#This Row],[CLIENTES]] -> 0 | D51: =SUMIF(BOLIVARES[EMISOR],Tabla3[[#This Row],[CLIENTES]],BOLIVARES[DOLARES]) -> 0 | E51: =SUMIF(BOLIVARES[RECEPTOR],Tabla3[[#This Row],[CLIENTES]],BOLIVARES[DOLARES2]) -> 0 | F51: =SUMIF(Tabla12[EMISOR2],Tabla3[[#This Row],[CLIENTES]],Tabla12[MONTO]) -> 0 | G51: =SUMIF(Tabla12[RECEPTOR],Tabla3[[#This Row],[CLIENTES]],Tabla12[MONTO2]) -> 0 | H51: =SUMIF(CAMBIOS[SOLIICTANTES],Tabla3[[#This Row],[CLIENTES]],CAMBIOS[DIFERENCIA])+ SUMIF(CAMBIOS[SOLIICTANTES],Tabla3[[#This Row],[CLIENTES]],CAMBIOS[COSTOS DE ENVÍO]) -> 0 | I51: =Tabla14[[#This Row],[PENDIENTE]]+Tabla14[[#This Row],[VENTA]]+Tabla14[[#This Row],[RETIRO]]-Tabla14[[#This Row],[COMPRA]]-Tabla14[[#This Row],[PAGO]]+Tabla14[[#This Row],[COMISION]] -> 0
B52: =Tabla3[[#This Row],[CLIENTES]] -> 0 | D52: =SUMIF(BOLIVARES[EMISOR],Tabla3[[#This Row],[CLIENTES]],BOLIVARES[DOLARES]) -> 0 | E52: =SUMIF(BOLIVARES[RECEPTOR],Tabla3[[#This Row],[CLIENTES]],BOLIVARES[DOLARES2]) -> 0 | F52: =SUMIF(Tabla12[EMISOR2],Tabla3[[#This Row],[CLIENTES]],Tabla12[MONTO]) -> 0 | G52: =SUMIF(Tabla12[RECEPTOR],Tabla3[[#This Row],[CLIENTES]],Tabla12[MONTO2]) -> 0 | H52: =SUMIF(CAMBIOS[SOLIICTANTES],Tabla3[[#This Row],[CLIENTES]],CAMBIOS[DIFERENCIA])+ SUMIF(CAMBIOS[SOLIICTANTES],Tabla3[[#This Row],[CLIENTES]],CAMBIOS[COSTOS DE ENVÍO]) -> 0 | I52: =Tabla14[[#This Row],[PENDIENTE]]+Tabla14[[#This Row],[VENTA]]+Tabla14[[#This Row],[RETIRO]]-Tabla14[[#This Row],[COMPRA]]-Tabla14[[#This Row],[PAGO]]+Tabla14[[#This Row],[COMISION]] -> 0
B53: =Tabla3[[#This Row],[CLIENTES]] -> 0 | D53: =SUMIF(BOLIVARES[EMISOR],Tabla3[[#This Row],[CLIENTES]],BOLIVARES[DOLARES]) -> 0 | E53: =SUMIF(BOLIVARES[RECEPTOR],Tabla3[[#This Row],[CLIENTES]],BOLIVARES[DOLARES2]) -> 0 | F53: =SUMIF(Tabla12[EMISOR2],Tabla3[[#This Row],[CLIENTES]],Tabla12[MONTO]) -> 0 | G53: =SUMIF(Tabla12[RECEPTOR],Tabla3[[#This Row],[CLIENTES]],Tabla12[MONTO2]) -> 0 | H53: =SUMIF(CAMBIOS[SOLIICTANTES],Tabla3[[#This Row],[CLIENTES]],CAMBIOS[DIFERENCIA])+ SUMIF(CAMBIOS[SOLIICTANTES],Tabla3[[#This Row],[CLIENTES]],CAMBIOS[COSTOS DE ENVÍO]) -> 0 | I53: =Tabla14[[#This Row],[PENDIENTE]]+Tabla14[[#This Row],[VENTA]]+Tabla14[[#This Row],[RETIRO]]-Tabla14[[#This Row],[COMPRA]]-Tabla14[[#This Row],[PAGO]]+Tabla14[[#This Row],[COMISION]] -> 0 | K53: GRUPO A
B54: =Tabla3[[#This Row],[CLIENTES]] -> 0 | D54: =SUMIF(BOLIVARES[EMISOR],Tabla3[[#This Row],[CLIENTES]],BOLIVARES[DOLARES]) -> 0 | E54: =SUMIF(BOLIVARES[RECEPTOR],Tabla3[[#This Row],[CLIENTES]],BOLIVARES[DOLARES2]) -> 0 | F54: =SUMIF(Tabla12[EMISOR2],Tabla3[[#This Row],[CLIENTES]],Tabla12[MONTO]) -> 0 | G54: =SUMIF(Tabla12[RECEPTOR],Tabla3[[#This Row],[CLIENTES]],Tabla12[MONTO2]) -> 0 | H54: =SUMIF(CAMBIOS[SOLIICTANTES],Tabla3[[#This Row],[CLIENTES]],CAMBIOS[DIFERENCIA])+ SUMIF(CAMBIOS[SOLIICTANTES],Tabla3[[#This Row],[CLIENTES]],CAMBIOS[COSTOS DE ENVÍO]) -> 0 | I54: =Tabla14[[#This Row],[PENDIENTE]]+Tabla14[[#This Row],[VENTA]]+Tabla14[[#This Row],[RETIRO]]-Tabla14[[#This Row],[COMPRA]]-Tabla14[[#This Row],[PAGO]]+Tabla14[[#This Row],[COMISION]] -> 0
B55: =Tabla3[[#This Row],[CLIENTES]] -> 0 | D55: =SUMIF(BOLIVARES[EMISOR],Tabla3[[#This Row],[CLIENTES]],BOLIVARES[DOLARES]) -> 0 | E55: =SUMIF(BOLIVARES[RECEPTOR],Tabla3[[#This Row],[CLIENTES]],BOLIVARES[DOLARES2]) -> 0 | F55: =SUMIF(Tabla12[EMISOR2],Tabla3[[#This Row],[CLIENTES]],Tabla12[MONTO]) -> 0 | G55: =SUMIF(Tabla12[RECEPTOR],Tabla3[[#This Row],[CLIENTES]],Tabla12[MONTO2]) -> 0 | H55: =SUMIF(CAMBIOS[SOLIICTANTES],Tabla3[[#This Row],[CLIENTES]],CAMBIOS[DIFERENCIA])+ SUMIF(CAMBIOS[SOLIICTANTES],Tabla3[[#This Row],[CLIENTES]],CAMBIOS[COSTOS DE ENVÍO]) -> 0 | I55: =Tabla14[[#This Row],[PENDIENTE]]+Tabla14[[#This Row],[VENTA]]+Tabla14[[#This Row],[RETIRO]]-Tabla14[[#This Row],[COMPRA]]-Tabla14[[#This Row],[PAGO]]+Tabla14[[#This Row],[COMISION]] -> 0 | K55: GRUPO A
B56: =Tabla3[[#This Row],[CLIENTES]] -> 0 | D56: =SUMIF(BOLIVARES[EMISOR],Tabla3[[#This Row],[CLIENTES]],BOLIVARES[DOLARES]) -> 0 | E56: =SUMIF(BOLIVARES[RECEPTOR],Tabla3[[#This Row],[CLIENTES]],BOLIVARES[DOLARES2]) -> 0 | F56: =SUMIF(Tabla12[EMISOR2],Tabla3[[#This Row],[CLIENTES]],Tabla12[MONTO]) -> 0 | G56: =SUMIF(Tabla12[RECEPTOR],Tabla3[[#This Row],[CLIENTES]],Tabla12[MONTO2]) -> 0 | H56: =SUMIF(CAMBIOS[SOLIICTANTES],Tabla3[[#This Row],[CLIENTES]],CAMBIOS[DIFERENCIA])+ SUMIF(CAMBIOS[SOLIICTANTES],Tabla3[[#This Row],[CLIENTES]],CAMBIOS[COSTOS DE ENVÍO]) -> 0 | I56: =Tabla14[[#This Row],[PENDIENTE]]+Tabla14[[#This Row],[VENTA]]+Tabla14[[#This Row],[RETIRO]]-Tabla14[[#This Row],[COMPRA]]-Tabla14[[#This Row],[PAGO]]+Tabla14[[#This Row],[COMISION]] -> 0
B57: =Tabla3[[#This Row],[CLIENTES]] -> 0 | D57: =SUMIF(BOLIVARES[EMISOR],Tabla3[[#This Row],[CLIENTES]],BOLIVARES[DOLARES]) -> 0 | E57: =SUMIF(BOLIVARES[RECEPTOR],Tabla3[[#This Row],[CLIENTES]],BOLIVARES[DOLARES2]) -> 0 | F57: =SUMIF(Tabla12[EMISOR2],Tabla3[[#This Row],[CLIENTES]],Tabla12[MONTO]) -> 0 | G57: =SUMIF(Tabla12[RECEPTOR],Tabla3[[#This Row],[CLIENTES]],Tabla12[MONTO2]) -> 0 | H57: =SUMIF(CAMBIOS[SOLIICTANTES],Tabla3[[#This Row],[CLIENTES]],CAMBIOS[DIFERENCIA])+ SUMIF(CAMBIOS[SOLIICTANTES],Tabla3[[#This Row],[CLIENTES]],CAMBIOS[COSTOS DE ENVÍO]) -> 0 | I57: =Tabla14[[#This Row],[PENDIENTE]]+Tabla14[[#This Row],[VENTA]]+Tabla14[[#This Row],[RETIRO]]-Tabla14[[#This Row],[COMPRA]]-Tabla14[[#This Row],[PAGO]]+Tabla14[[#This Row],[COMISION]] -> 0
B58: =Tabla3[[#This Row],[CLIENTES]] -> 0 | D58: =SUMIF(BOLIVARES[EMISOR],Tabla3[[#This Row],[CLIENTES]],BOLIVARES[DOLARES]) -> 0 | E58: =SUMIF(BOLIVARES[RECEPTOR],Tabla3[[#This Row],[CLIENTES]],BOLIVARES[DOLARES2]) -> 0 | F58: =SUMIF(Tabla12[EMISOR2],Tabla3[[#This Row],[CLIENTES]],Tabla12[MONTO]) -> 0 | G58: =SUMIF(Tabla12[RECEPTOR],Tabla3[[#This Row],[CLIENTES]],Tabla12[MONTO2]) -> 0 | H58: =SUMIF(CAMBIOS[SOLIICTANTES],Tabla3[[#This Row],[CLIENTES]],CAMBIOS[DIFERENCIA])+ SUMIF(CAMBIOS[SOLIICTANTES],Tabla3[[#This Row],[CLIENTES]],CAMBIOS[COSTOS DE ENVÍO]) -> 0 | I58: =Tabla14[[#This Row],[PENDIENTE]]+Tabla14[[#This Row],[VENTA]]+Tabla14[[#This Row],[RETIRO]]-Tabla14[[#This Row],[COMPRA]]-Tabla14[[#This Row],[PAGO]]+Tabla14[[#This Row],[COMISION]] -> 0 | K58: GRUPO A
B59: =Tabla3[[#This Row],[CLIENTES]] -> 0 | D59: =SUMIF(BOLIVARES[EMISOR],Tabla3[[#This Row],[CLIENTES]],BOLIVARES[DOLARES]) -> 0 | E59: =SUMIF(BOLIVARES[RECEPTOR],Tabla3[[#This Row],[CLIENTES]],BOLIVARES[DOLARES2]) -> 0 | F59: =SUMIF(Tabla12[EMISOR2],Tabla3[[#This Row],[CLIENTES]],Tabla12[MONTO]) -> 0 | G59: =SUMIF(Tabla12[RECEPTOR],Tabla3[[#This Row],[CLIENTES]],Tabla12[MONTO2]) -> 0 | H59: =SUMIF(CAMBIOS[SOLIICTANTES],Tabla3[[#This Row],[CLIENTES]],CAMBIOS[DIFERENCIA])+ SUMIF(CAMBIOS[SOLIICTANTES],Tabla3[[#This Row],[CLIENTES]],CAMBIOS[COSTOS DE ENVÍO]) -> 0 | I59: =Tabla14[[#This Row],[PENDIENTE]]+Tabla14[[#This Row],[VENTA]]+Tabla14[[#This Row],[RETIRO]]-Tabla14[[#This Row],[COMPRA]]-Tabla14[[#This Row],[PAGO]]+Tabla14[[#This Row],[COMISION]] -> 0
B60: =Tabla3[[#This Row],[CLIENTES]] -> 0 | D60: =SUMIF(BOLIVARES[EMISOR],Tabla3[[#This Row],[CLIENTES]],BOLIVARES[DOLARES]) -> 0 | E60: =SUMIF(BOLIVARES[RECEPTOR],Tabla3[[#This Row],[CLIENTES]],BOLIVARES[DOLARES2]) -> 0 | F60: =SUMIF(Tabla12[EMISOR2],Tabla3[[#This Row],[CLIENTES]],Tabla12[MONTO]) -> 0 | G60: =SUMIF(Tabla12[RECEPTOR],Tabla3[[#This Row],[CLIENTES]],Tabla12[MONTO2]) -> 0 | H60: =SUMIF(CAMBIOS[SOLIICTANTES],Tabla3[[#This Row],[CLIENTES]],CAMBIOS[DIFERENCIA])+ SUMIF(CAMBIOS[SOLIICTANTES],Tabla3[[#This Row],[CLIENTES]],CAMBIOS[COSTOS DE ENVÍO]) -> 0 | I60: =Tabla14[[#This Row],[PENDIENTE]]+Tabla14[[#This Row],[VENTA]]+Tabla14[[#This Row],[RETIRO]]-Tabla14[[#This Row],[COMPRA]]-Tabla14[[#This Row],[PAGO]]+Tabla14[[#This Row],[COMISION]] -> 0
B61: =Tabla3[[#This Row],[CLIENTES]] -> 0 | D61: =SUMIF(BOLIVARES[EMISOR],Tabla3[[#This Row],[CLIENTES]],BOLIVARES[DOLARES]) -> 0 | E61: =SUMIF(BOLIVARES[RECEPTOR],Tabla3[[#This Row],[CLIENTES]],BOLIVARES[DOLARES2]) -> 0 | F61: =SUMIF(Tabla12[EMISOR2],Tabla3[[#This Row],[CLIENTES]],Tabla12[MONTO]) -> 0 | G61: =SUMIF(Tabla12[RECEPTOR],Tabla3[[#This Row],[CLIENTES]],Tabla12[MONTO2]) -> 0 | H61: =SUMIF(CAMBIOS[SOLIICTANTES],Tabla3[[#This Row],[CLIENTES]],CAMBIOS[DIFERENCIA])+ SUMIF(CAMBIOS[SOLIICTANTES],Tabla3[[#This Row],[CLIENTES]],CAMBIOS[COSTOS DE ENVÍO]) -> 0 | I61: =Tabla14[[#This Row],[PENDIENTE]]+Tabla14[[#This Row],[VENTA]]+Tabla14[[#This Row],[RETIRO]]-Tabla14[[#This Row],[COMPRA]]-Tabla14[[#This Row],[PAGO]]+Tabla14[[#This Row],[COMISION]] -> 0
B62: =Tabla3[[#This Row],[CLIENTES]] -> 0 | D62: =SUMIF(BOLIVARES[EMISOR],Tabla3[[#This Row],[CLIENTES]],BOLIVARES[DOLARES]) -> 0 | E62: =SUMIF(BOLIVARES[RECEPTOR],Tabla3[[#This Row],[CLIENTES]],BOLIVARES[DOLARES2]) -> 0 | F62: =SUMIF(Tabla12[EMISOR2],Tabla3[[#This Row],[CLIENTES]],Tabla12[MONTO]) -> 0 | G62: =SUMIF(Tabla12[RECEPTOR],Tabla3[[#This Row],[CLIENTES]],Tabla12[MONTO2]) -> 0 | H62: =SUMIF(CAMBIOS[SOLIICTANTES],Tabla3[[#This Row],[CLIENTES]],CAMBIOS[DIFERENCIA])+ SUMIF(CAMBIOS[SOLIICTANTES],Tabla3[[#This Row],[CLIENTES]],CAMBIOS[COSTOS DE ENVÍO]) -> 0 | I62: =Tabla14[[#This Row],[PENDIENTE]]+Tabla14[[#This Row],[VENTA]]+Tabla14[[#This Row],[RETIRO]]-Tabla14[[#This Row],[COMPRA]]-Tabla14[[#This Row],[PAGO]]+Tabla14[[#This Row],[COMISION]] -> 0
B63: =Tabla3[[#This Row],[CLIENTES]] -> 0 | D63: =SUMIF(BOLIVARES[EMISOR],Tabla3[[#This Row],[CLIENTES]],BOLIVARES[DOLARES]) -> 0 | E63: =SUMIF(BOLIVARES[RECEPTOR],Tabla3[[#This Row],[CLIENTES]],BOLIVARES[DOLARES2]) -> 0 | F63: =SUMIF(Tabla12[EMISOR2],Tabla3[[#This Row],[CLIENTES]],Tabla12[MONTO]) -> 0 | G63: =SUMIF(Tabla12[RECEPTOR],Tabla3[[#This Row],[CLIENTES]],Tabla12[MONTO2]) -> 0 | H63: =SUMIF(CAMBIOS[SOLIICTANTES],Tabla3[[#This Row],[CLIENTES]],CAMBIOS[DIFERENCIA])+ SUMIF(CAMBIOS[SOLIICTANTES],Tabla3[[#This Row],[CLIENTES]],CAMBIOS[COSTOS DE ENVÍO]) -> 0 | I63: =Tabla14[[#This Row],[PENDIENTE]]+Tabla14[[#This Row],[VENTA]]+Tabla14[[#This Row],[RETIRO]]-Tabla14[[#This Row],[COMPRA]]-Tabla14[[#This Row],[PAGO]]+Tabla14[[#This Row],[COMISION]] -> 0
B64: =Tabla3[[#This Row],[CLIENTES]] -> 0 | D64: =SUMIF(BOLIVARES[EMISOR],Tabla3[[#This Row],[CLIENTES]],BOLIVARES[DOLARES]) -> 0 | E64: =SUMIF(BOLIVARES[RECEPTOR],Tabla3[[#This Row],[CLIENTES]],BOLIVARES[DOLARES2]) -> 0 | F64: =SUMIF(Tabla12[EMISOR2],Tabla3[[#This Row],[CLIENTES]],Tabla12[MONTO]) -> 0 | G64: =SUMIF(Tabla12[RECEPTOR],Tabla3[[#This Row],[CLIENTES]],Tabla12[MONTO2]) -> 0 | H64: =SUMIF(CAMBIOS[SOLIICTANTES],Tabla3[[#This Row],[CLIENTES]],CAMBIOS[DIFERENCIA])+ SUMIF(CAMBIOS[SOLIICTANTES],Tabla3[[#This Row],[CLIENTES]],CAMBIOS[COSTOS DE ENVÍO]) -> 0 | I64: =Tabla14[[#This Row],[PENDIENTE]]+Tabla14[[#This Row],[VENTA]]+Tabla14[[#This Row],[RETIRO]]-Tabla14[[#This Row],[COMPRA]]-Tabla14[[#This Row],[PAGO]]+Tabla14[[#This Row],[COMISION]] -> 0
B65: =Tabla3[[#This Row],[CLIENTES]] -> 0 | D65: =SUMIF(BOLIVARES[EMISOR],Tabla3[[#This Row],[CLIENTES]],BOLIVARES[DOLARES]) -> 0 | E65: =SUMIF(BOLIVARES[RECEPTOR],Tabla3[[#This Row],[CLIENTES]],BOLIVARES[DOLARES2]) -> 0 | F65: =SUMIF(Tabla12[EMISOR2],Tabla3[[#This Row],[CLIENTES]],Tabla12[MONTO]) -> 0 | G65: =SUMIF(Tabla12[RECEPTOR],Tabla3[[#This Row],[CLIENTES]],Tabla12[MONTO2]) -> 0 | H65: =SUMIF(CAMBIOS[SOLIICTANTES],Tabla3[[#This Row],[CLIENTES]],CAMBIOS[DIFERENCIA])+ SUMIF(CAMBIOS[SOLIICTANTES],Tabla3[[#This Row],[CLIENTES]],CAMBIOS[COSTOS DE ENVÍO]) -> 0 | I65: =Tabla14[[#This Row],[PENDIENTE]]+Tabla14[[#This Row],[VENTA]]+Tabla14[[#This Row],[RETIRO]]-Tabla14[[#This Row],[COMPRA]]-Tabla14[[#This Row],[PAGO]]+Tabla14[[#This Row],[COMISION]] -> 0
B66: =Tabla3[[#This Row],[CLIENTES]] -> 0 | D66: =SUMIF(BOLIVARES[EMISOR],Tabla3[[#This Row],[CLIENTES]],BOLIVARES[DOLARES]) -> 0 | E66: =SUMIF(BOLIVARES[RECEPTOR],Tabla3[[#This Row],[CLIENTES]],BOLIVARES[DOLARES2]) -> 0 | F66: =SUMIF(Tabla12[EMISOR2],Tabla3[[#This Row],[CLIENTES]],Tabla12[MONTO]) -> 0 | G66: =SUMIF(Tabla12[RECEPTOR],Tabla3[[#This Row],[CLIENTES]],Tabla12[MONTO2]) -> 0 | H66: =SUMIF(CAMBIOS[SOLIICTANTES],Tabla3[[#This Row],[CLIENTES]],CAMBIOS[DIFERENCIA])+ SUMIF(CAMBIOS[SOLIICTANTES],Tabla3[[#This Row],[CLIENTES]],CAMBIOS[COSTOS DE ENVÍO]) -> 0 | I66: =Tabla14[[#This Row],[PENDIENTE]]+Tabla14[[#This Row],[VENTA]]+Tabla14[[#This Row],[RETIRO]]-Tabla14[[#This Row],[COMPRA]]-Tabla14[[#This Row],[PAGO]]+Tabla14[[#This Row],[COMISION]] -> 0 | K66: GRUPO A
B67: =Tabla3[[#This Row],[CLIENTES]] -> 0 | D67: =SUMIF(BOLIVARES[EMISOR],Tabla3[[#This Row],[CLIENTES]],BOLIVARES[DOLARES]) -> 0 | E67: =SUMIF(BOLIVARES[RECEPTOR],Tabla3[[#This Row],[CLIENTES]],BOLIVARES[DOLARES2]) -> 0 | F67: =SUMIF(Tabla12[EMISOR2],Tabla3[[#This Row],[CLIENTES]],Tabla12[MONTO]) -> 0 | G67: =SUMIF(Tabla12[RECEPTOR],Tabla3[[#This Row],[CLIENTES]],Tabla12[MONTO2]) -> 0 | H67: =SUMIF(CAMBIOS[SOLIICTANTES],Tabla3[[#This Row],[CLIENTES]],CAMBIOS[DIFERENCIA])+ SUMIF(CAMBIOS[SOLIICTANTES],Tabla3[[#This Row],[CLIENTES]],CAMBIOS[COSTOS DE ENVÍO]) -> 0 | I67: =Tabla14[[#This Row],[PENDIENTE]]+Tabla14[[#This Row],[VENTA]]+Tabla14[[#This Row],[RETIRO]]-Tabla14[[#This Row],[COMPRA]]-Tabla14[[#This Row],[PAGO]]+Tabla14[[#This Row],[COMISION]] -> 0
B68: =Tabla3[[#This Row],[CLIENTES]] -> 0 | D68: =SUMIF(BOLIVARES[EMISOR],Tabla3[[#This Row],[CLIENTES]],BOLIVARES[DOLARES]) -> 0 | E68: =SUMIF(BOLIVARES[RECEPTOR],Tabla3[[#This Row],[CLIENTES]],BOLIVARES[DOLARES2]) -> 0 | F68: =SUMIF(Tabla12[EMISOR2],Tabla3[[#This Row],[CLIENTES]],Tabla12[MONTO]) -> 0 | G68: =SUMIF(Tabla12[RECEPTOR],Tabla3[[#This Row],[CLIENTES]],Tabla12[MONTO2]) -> 0 | H68: =SUMIF(CAMBIOS[SOLIICTANTES],Tabla3[[#This Row],[CLIENTES]],CAMBIOS[DIFERENCIA])+ SUMIF(CAMBIOS[SOLIICTANTES],Tabla3[[#This Row],[CLIENTES]],CAMBIOS[COSTOS DE ENVÍO]) -> 0 | I68: =Tabla14[[#This Row],[PENDIENTE]]+Tabla14[[#This Row],[VENTA]]+Tabla14[[#This Row],[RETIRO]]-Tabla14[[#This Row],[COMPRA]]-Tabla14[[#This Row],[PAGO]]+Tabla14[[#This Row],[COMISION]] -> 0
B69: =Tabla3[[#This Row],[CLIENTES]] -> 0 | D69: =SUMIF(BOLIVARES[EMISOR],Tabla3[[#This Row],[CLIENTES]],BOLIVARES[DOLARES]) -> 0 | E69: =SUMIF(BOLIVARES[RECEPTOR],Tabla3[[#This Row],[CLIENTES]],BOLIVARES[DOLARES2]) -> 0 | F69: =SUMIF(Tabla12[EMISOR2],Tabla3[[#This Row],[CLIENTES]],Tabla12[MONTO]) -> 0 | G69: =SUMIF(Tabla12[RECEPTOR],Tabla3[[#This Row],[CLIENTES]],Tabla12[MONTO2]) -> 0 | H69: =SUMIF(CAMBIOS[SOLIICTANTES],Tabla3[[#This Row],[CLIENTES]],CAMBIOS[DIFERENCIA])+ SUMIF(CAMBIOS[SOLIICTANTES],Tabla3[[#This Row],[CLIENTES]],CAMBIOS[COSTOS DE ENVÍO]) -> 0 | I69: =Tabla14[[#This Row],[PENDIENTE]]+Tabla14[[#This Row],[VENTA]]+Tabla14[[#This Row],[RETIRO]]-Tabla14[[#This Row],[COMPRA]]-Tabla14[[#This Row],[PAGO]]+Tabla14[[#This Row],[COMISION]] -> 0
B70: =Tabla3[[#This Row],[CLIENTES]] -> 0 | D70: =SUMIF(BOLIVARES[EMISOR],Tabla3[[#This Row],[CLIENTES]],BOLIVARES[DOLARES]) -> 0 | E70: =SUMIF(BOLIVARES[RECEPTOR],Tabla3[[#This Row],[CLIENTES]],BOLIVARES[DOLARES2]) -> 0 | F70: =SUMIF(Tabla12[EMISOR2],Tabla3[[#This Row],[CLIENTES]],Tabla12[MONTO]) -> 0 | G70: =SUMIF(Tabla12[RECEPTOR],Tabla3[[#This Row],[CLIENTES]],Tabla12[MONTO2]) -> 0 | H70: =SUMIF(CAMBIOS[SOLIICTANTES],Tabla3[[#This Row],[CLIENTES]],CAMBIOS[DIFERENCIA])+ SUMIF(CAMBIOS[SOLIICTANTES],Tabla3[[#This Row],[CLIENTES]],CAMBIOS[COSTOS DE ENVÍO]) -> 0 | I70: =Tabla14[[#This Row],[PENDIENTE]]+Tabla14[[#This Row],[VENTA]]+Tabla14[[#This Row],[RETIRO]]-Tabla14[[#This Row],[COMPRA]]-Tabla14[[#This Row],[PAGO]]+Tabla14[[#This Row],[COMISION]] -> 0
B71: =Tabla3[[#This Row],[CLIENTES]] -> 0 | D71: =SUMIF(BOLIVARES[EMISOR],Tabla3[[#This Row],[CLIENTES]],BOLIVARES[DOLARES]) -> 0 | E71: =SUMIF(BOLIVARES[RECEPTOR],Tabla3[[#This Row],[CLIENTES]],BOLIVARES[DOLARES2]) -> 0 | F71: =SUMIF(Tabla12[EMISOR2],Tabla3[[#This Row],[CLIENTES]],Tabla12[MONTO]) -> 0 | G71: =SUMIF(Tabla12[RECEPTOR],Tabla3[[#This Row],[CLIENTES]],Tabla12[MONTO2]) -> 0 | H71: =SUMIF(CAMBIOS[SOLIICTANTES],Tabla3[[#This Row],[CLIENTES]],CAMBIOS[DIFERENCIA])+ SUMIF(CAMBIOS[SOLIICTANTES],Tabla3[[#This Row],[CLIENTES]],CAMBIOS[COSTOS DE ENVÍO]) -> 0 | I71: =Tabla14[[#This Row],[PENDIENTE]]+Tabla14[[#This Row],[VENTA]]+Tabla14[[#This Row],[RETIRO]]-Tabla14[[#This Row],[COMPRA]]-Tabla14[[#This Row],[PAGO]]+Tabla14[[#This Row],[COMISION]] -> 0
B72: =Tabla3[[#This Row],[CLIENTES]] -> 0 | D72: =SUMIF(BOLIVARES[EMISOR],Tabla3[[#This Row],[CLIENTES]],BOLIVARES[DOLARES]) -> 0 | E72: =SUMIF(BOLIVARES[RECEPTOR],Tabla3[[#This Row],[CLIENTES]],BOLIVARES[DOLARES2]) -> 0 | F72: =SUMIF(Tabla12[EMISOR2],Tabla3[[#This Row],[CLIENTES]],Tabla12[MONTO]) -> 0 | G72: =SUMIF(Tabla12[RECEPTOR],Tabla3[[#This Row],[CLIENTES]],Tabla12[MONTO2]) -> 0 | H72: =SUMIF(CAMBIOS[SOLIICTANTES],Tabla3[[#This Row],[CLIENTES]],CAMBIOS[DIFERENCIA])+ SUMIF(CAMBIOS[SOLIICTANTES],Tabla3[[#This Row],[CLIENTES]],CAMBIOS[COSTOS DE ENVÍO]) -> 0 | I72: =Tabla14[[#This Row],[PENDIENTE]]+Tabla14[[#This Row],[VENTA]]+Tabla14[[#This Row],[RETIRO]]-Tabla14[[#This Row],[COMPRA]]-Tabla14[[#This Row],[PAGO]]+Tabla14[[#This Row],[COMISION]] -> 0 | K72: GRUPO A
B73: =Tabla3[[#This Row],[CLIENTES]] -> 0 | D73: =SUMIF(BOLIVARES[EMISOR],Tabla3[[#This Row],[CLIENTES]],BOLIVARES[DOLARES]) -> 0 | E73: =SUMIF(BOLIVARES[RECEPTOR],Tabla3[[#This Row],[CLIENTES]],BOLIVARES[DOLARES2]) -> 0 | F73: =SUMIF(Tabla12[EMISOR2],Tabla3[[#This Row],[CLIENTES]],Tabla12[MONTO]) -> 0 | G73: =SUMIF(Tabla12[RECEPTOR],Tabla3[[#This Row],[CLIENTES]],Tabla12[MONTO2]) -> 0 | H73: =SUMIF(CAMBIOS[SOLIICTANTES],Tabla3[[#This Row],[CLIENTES]],CAMBIOS[DIFERENCIA])+ SUMIF(CAMBIOS[SOLIICTANTES],Tabla3[[#This Row],[CLIENTES]],CAMBIOS[COSTOS DE ENVÍO]) -> 0 | I73: =Tabla14[[#This Row],[PENDIENTE]]+Tabla14[[#This Row],[VENTA]]+Tabla14[[#This Row],[RETIRO]]-Tabla14[[#This Row],[COMPRA]]-Tabla14[[#This Row],[PAGO]]+Tabla14[[#This Row],[COMISION]] -> 0
B74: =Tabla3[[#This Row],[CLIENTES]] -> 0 | D74: =SUMIF(BOLIVARES[EMISOR],Tabla3[[#This Row],[CLIENTES]],BOLIVARES[DOLARES]) -> 0 | E74: =SUMIF(BOLIVARES[RECEPTOR],Tabla3[[#This Row],[CLIENTES]],BOLIVARES[DOLARES2]) -> 0 | F74: =SUMIF(Tabla12[EMISOR2],Tabla3[[#This Row],[CLIENTES]],Tabla12[MONTO]) -> 0 | G74: =SUMIF(Tabla12[RECEPTOR],Tabla3[[#This Row],[CLIENTES]],Tabla12[MONTO2]) -> 0 | H74: =SUMIF(CAMBIOS[SOLIICTANTES],Tabla3[[#This Row],[CLIENTES]],CAMBIOS[DIFERENCIA])+ SUMIF(CAMBIOS[SOLIICTANTES],Tabla3[[#This Row],[CLIENTES]],CAMBIOS[COSTOS DE ENVÍO]) -> 0 | I74: =Tabla14[[#This Row],[PENDIENTE]]+Tabla14[[#This Row],[VENTA]]+Tabla14[[#This Row],[RETIRO]]-Tabla14[[#This Row],[COMPRA]]-Tabla14[[#This Row],[PAGO]]+Tabla14[[#This Row],[COMISION]] -> 0
B75: =Tabla3[[#This Row],[CLIENTES]] -> 0 | D75: =SUMIF(BOLIVARES[EMISOR],Tabla3[[#This Row],[CLIENTES]],BOLIVARES[DOLARES]) -> 0 | E75: =SUMIF(BOLIVARES[RECEPTOR],Tabla3[[#This Row],[CLIENTES]],BOLIVARES[DOLARES2]) -> 0 | F75: =SUMIF(Tabla12[EMISOR2],Tabla3[[#This Row],[CLIENTES]],Tabla12[MONTO]) -> 0 | G75: =SUMIF(Tabla12[RECEPTOR],Tabla3[[#This Row],[CLIENTES]],Tabla12[MONTO2]) -> 0 | H75: =SUMIF(CAMBIOS[SOLIICTANTES],Tabla3[[#This Row],[CLIENTES]],CAMBIOS[DIFERENCIA])+ SUMIF(CAMBIOS[SOLIICTANTES],Tabla3[[#This Row],[CLIENTES]],CAMBIOS[COSTOS DE ENVÍO]) -> 0 | I75: =Tabla14[[#This Row],[PENDIENTE]]+Tabla14[[#This Row],[VENTA]]+Tabla14[[#This Row],[RETIRO]]-Tabla14[[#This Row],[COMPRA]]-Tabla14[[#This Row],[PAGO]]+Tabla14[[#This Row],[COMISION]] -> 0
B76: =Tabla3[[#This Row],[CLIENTES]] -> 0 | D76: =SUMIF(BOLIVARES[EMISOR],Tabla3[[#This Row],[CLIENTES]],BOLIVARES[DOLARES]) -> 0 | E76: =SUMIF(BOLIVARES[RECEPTOR],Tabla3[[#This Row],[CLIENTES]],BOLIVARES[DOLARES2]) -> 0 | F76: =SUMIF(Tabla12[EMISOR2],Tabla3[[#This Row],[CLIENTES]],Tabla12[MONTO]) -> 0 | G76: =SUMIF(Tabla12[RECEPTOR],Tabla3[[#This Row],[CLIENTES]],Tabla12[MONTO2]) -> 0 | H76: =SUMIF(CAMBIOS[SOLIICTANTES],Tabla3[[#This Row],[CLIENTES]],CAMBIOS[DIFERENCIA])+ SUMIF(CAMBIOS[SOLIICTANTES],Tabla3[[#This Row],[CLIENTES]],CAMBIOS[COSTOS DE ENVÍO]) -> 0 | I76: =Tabla14[[#This Row],[PENDIENTE]]+Tabla14[[#This Row],[VENTA]]+Tabla14[[#This Row],[RETIRO]]-Tabla14[[#This Row],[COMPRA]]-Tabla14[[#This Row],[PAGO]]+Tabla14[[#This Row],[COMISION]] -> 0
B77: =Tabla3[[#This Row],[CLIENTES]] -> 0 | D77: =SUMIF(BOLIVARES[EMISOR],Tabla3[[#This Row],[CLIENTES]],BOLIVARES[DOLARES]) -> 0 | E77: =SUMIF(BOLIVARES[RECEPTOR],Tabla3[[#This Row],[CLIENTES]],BOLIVARES[DOLARES2]) -> 0 | F77: =SUMIF(Tabla12[EMISOR2],Tabla3[[#This Row],[CLIENTES]],Tabla12[MONTO]) -> 0 | G77: =SUMIF(Tabla12[RECEPTOR],Tabla3[[#This Row],[CLIENTES]],Tabla12[MONTO2]) -> 0 | H77: =SUMIF(CAMBIOS[SOLIICTANTES],Tabla3[[#This Row],[CLIENTES]],CAMBIOS[DIFERENCIA])+ SUMIF(CAMBIOS[SOLIICTANTES],Tabla3[[#This Row],[CLIENTES]],CAMBIOS[COSTOS DE ENVÍO]) -> 0 | I77: =Tabla14[[#This Row],[PENDIENTE]]+Tabla14[[#This Row],[VENTA]]+Tabla14[[#This Row],[RETIRO]]-Tabla14[[#This Row],[COMPRA]]-Tabla14[[#This Row],[PAGO]]+Tabla14[[#This Row],[COMISION]] -> 0
B78: =Tabla3[[#This Row],[CLIENTES]] -> 0 | D78: =SUMIF(BOLIVARES[EMISOR],Tabla3[[#This Row],[CLIENTES]],BOLIVARES[DOLARES]) -> 0 | E78: =SUMIF(BOLIVARES[RECEPTOR],Tabla3[[#This Row],[CLIENTES]],BOLIVARES[DOLARES2]) -> 0 | F78: =SUMIF(Tabla12[EMISOR2],Tabla3[[#This Row],[CLIENTES]],Tabla12[MONTO]) -> 0 | G78: =SUMIF(Tabla12[RECEPTOR],Tabla3[[#This Row],[CLIENTES]],Tabla12[MONTO2]) -> 0 | H78: =SUMIF(CAMBIOS[SOLIICTANTES],Tabla3[[#This Row],[CLIENTES]],CAMBIOS[DIFERENCIA])+ SUMIF(CAMBIOS[SOLIICTANTES],Tabla3[[#This Row],[CLIENTES]],CAMBIOS[COSTOS DE ENVÍO]) -> 0 | I78: =Tabla14[[#This Row],[PENDIENTE]]+Tabla14[[#This Row],[VENTA]]+Tabla14[[#This Row],[RETIRO]]-Tabla14[[#This Row],[COMPRA]]-Tabla14[[#This Row],[PAGO]]+Tabla14[[#This Row],[COMISION]] -> 0
B79: =Tabla3[[#This Row],[CLIENTES]] -> 0 | D79: =SUMIF(BOLIVARES[EMISOR],Tabla3[[#This Row],[CLIENTES]],BOLIVARES[DOLARES]) -> 0 | E79: =SUMIF(BOLIVARES[RECEPTOR],Tabla3[[#This Row],[CLIENTES]],BOLIVARES[DOLARES2]) -> 0 | F79: =SUMIF(Tabla12[EMISOR2],Tabla3[[#This Row],[CLIENTES]],Tabla12[MONTO]) -> 0 | G79: =SUMIF(Tabla12[RECEPTOR],Tabla3[[#This Row],[CLIENTES]],Tabla12[MONTO2]) -> 0 | H79: =SUMIF(CAMBIOS[SOLIICTANTES],Tabla3[[#This Row],[CLIENTES]],CAMBIOS[DIFERENCIA])+ SUMIF(CAMBIOS[SOLIICTANTES],Tabla3[[#This Row],[CLIENTES]],CAMBIOS[COSTOS DE ENVÍO]) -> 0 | I79: =Tabla14[[#This Row],[PENDIENTE]]+Tabla14[[#This Row],[VENTA]]+Tabla14[[#This Row],[RETIRO]]-Tabla14[[#This Row],[COMPRA]]-Tabla14[[#This Row],[PAGO]]+Tabla14[[#This Row],[COMISION]] -> 0
B80: =Tabla3[[#This Row],[CLIENTES]] -> 0 | D80: =SUMIF(BOLIVARES[EMISOR],Tabla3[[#This Row],[CLIENTES]],BOLIVARES[DOLARES]) -> 0 | E80: =SUMIF(BOLIVARES[RECEPTOR],Tabla3[[#This Row],[CLIENTES]],BOLIVARES[DOLARES2]) -> 0 | F80: =SUMIF(Tabla12[EMISOR2],Tabla3[[#This Row],[CLIENTES]],Tabla12[MONTO]) -> 0 | G80: =SUMIF(Tabla12[RECEPTOR],Tabla3[[#This Row],[CLIENTES]],Tabla12[MONTO2]) -> 0 | H80: =SUMIF(CAMBIOS[SOLIICTANTES],Tabla3[[#This Row],[CLIENTES]],CAMBIOS[DIFERENCIA])+ SUMIF(CAMBIOS[SOLIICTANTES],Tabla3[[#This Row],[CLIENTES]],CAMBIOS[COSTOS DE ENVÍO]) -> 0 | I80: =Tabla14[[#This Row],[PENDIENTE]]+Tabla14[[#This Row],[VENTA]]+Tabla14[[#This Row],[RETIRO]]-Tabla14[[#This Row],[COMPRA]]-Tabla14[[#This Row],[PAGO]]+Tabla14[[#This Row],[COMISION]] -> 0
B81: =Tabla3[[#This Row],[CLIENTES]] -> 0 | D81: =SUMIF(BOLIVARES[EMISOR],Tabla3[[#This Row],[CLIENTES]],BOLIVARES[DOLARES]) -> 0 | E81: =SUMIF(BOLIVARES[RECEPTOR],Tabla3[[#This Row],[CLIENTES]],BOLIVARES[DOLARES2]) -> 0 | F81: =SUMIF(Tabla12[EMISOR2],Tabla3[[#This Row],[CLIENTES]],Tabla12[MONTO]) -> 0 | G81: =SUMIF(Tabla12[RECEPTOR],Tabla3[[#This Row],[CLIENTES]],Tabla12[MONTO2]) -> 0 | H81: =SUMIF(CAMBIOS[SOLIICTANTES],Tabla3[[#This Row],[CLIENTES]],CAMBIOS[DIFERENCIA])+ SUMIF(CAMBIOS[SOLIICTANTES],Tabla3[[#This Row],[CLIENTES]],CAMBIOS[COSTOS DE ENVÍO]) -> 0 | I81: =Tabla14[[#This Row],[PENDIENTE]]+Tabla14[[#This Row],[VENTA]]+Tabla14[[#This Row],[RETIRO]]-Tabla14[[#This Row],[COMPRA]]-Tabla14[[#This Row],[PAGO]]+Tabla14[[#This Row],[COMISION]] -> 0
B82: =Tabla3[[#This Row],[CLIENTES]] -> 0 | D82: =SUMIF(BOLIVARES[EMISOR],Tabla3[[#This Row],[CLIENTES]],BOLIVARES[DOLARES]) -> 0 | E82: =SUMIF(BOLIVARES[RECEPTOR],Tabla3[[#This Row],[CLIENTES]],BOLIVARES[DOLARES2]) -> 0 | F82: =SUMIF(Tabla12[EMISOR2],Tabla3[[#This Row],[CLIENTES]],Tabla12[MONTO]) -> 0 | G82: =SUMIF(Tabla12[RECEPTOR],Tabla3[[#This Row],[CLIENTES]],Tabla12[MONTO2]) -> 0 | H82: =SUMIF(CAMBIOS[SOLIICTANTES],Tabla3[[#This Row],[CLIENTES]],CAMBIOS[DIFERENCIA])+ SUMIF(CAMBIOS[SOLIICTANTES],Tabla3[[#This Row],[CLIENTES]],CAMBIOS[COSTOS DE ENVÍO]) -> 0 | I82: =Tabla14[[#This Row],[PENDIENTE]]+Tabla14[[#This Row],[VENTA]]+Tabla14[[#This Row],[RETIRO]]-Tabla14[[#This Row],[COMPRA]]-Tabla14[[#This Row],[PAGO]]+Tabla14[[#This Row],[COMISION]] -> 0
B83: =Tabla3[[#This Row],[CLIENTES]] -> 0 | D83: =SUMIF(BOLIVARES[EMISOR],Tabla3[[#This Row],[CLIENTES]],BOLIVARES[DOLARES]) -> 0 | E83: =SUMIF(BOLIVARES[RECEPTOR],Tabla3[[#This Row],[CLIENTES]],BOLIVARES[DOLARES2]) -> 0 | F83: =SUMIF(Tabla12[EMISOR2],Tabla3[[#This Row],[CLIENTES]],Tabla12[MONTO]) -> 0 | G83: =SUMIF(Tabla12[RECEPTOR],Tabla3[[#This Row],[CLIENTES]],Tabla12[MONTO2]) -> 0 | H83: =SUMIF(CAMBIOS[SOLIICTANTES],Tabla3[[#This Row],[CLIENTES]],CAMBIOS[DIFERENCIA])+ SUMIF(CAMBIOS[SOLIICTANTES],Tabla3[[#This Row],[CLIENTES]],CAMBIOS[COSTOS DE ENVÍO]) -> 0 | I83: =Tabla14[[#This Row],[PENDIENTE]]+Tabla14[[#This Row],[VENTA]]+Tabla14[[#This Row],[RETIRO]]-Tabla14[[#This Row],[COMPRA]]-Tabla14[[#This Row],[PAGO]]+Tabla14[[#This Row],[COMISION]] -> 0 | K83: GRUPO A
B84: =Tabla3[[#This Row],[CLIENTES]] -> 0 | D84: =SUMIF(BOLIVARES[EMISOR],Tabla3[[#This Row],[CLIENTES]],BOLIVARES[DOLARES]) -> 0 | E84: =SUMIF(BOLIVARES[RECEPTOR],Tabla3[[#This Row],[CLIENTES]],BOLIVARES[DOLARES2]) -> 0 | F84: =SUMIF(Tabla12[EMISOR2],Tabla3[[#This Row],[CLIENTES]],Tabla12[MONTO]) -> 0 | G84: =SUMIF(Tabla12[RECEPTOR],Tabla3[[#This Row],[CLIENTES]],Tabla12[MONTO2]) -> 0 | H84: =SUMIF(CAMBIOS[SOLIICTANTES],Tabla3[[#This Row],[CLIENTES]],CAMBIOS[DIFERENCIA])+ SUMIF(CAMBIOS[SOLIICTANTES],Tabla3[[#This Row],[CLIENTES]],CAMBIOS[COSTOS DE ENVÍO]) -> 0 | I84: =Tabla14[[#This Row],[PENDIENTE]]+Tabla14[[#This Row],[VENTA]]+Tabla14[[#This Row],[RETIRO]]-Tabla14[[#This Row],[COMPRA]]-Tabla14[[#This Row],[PAGO]]+Tabla14[[#This Row],[COMISION]] -> 0
B85: =Tabla3[[#This Row],[CLIENTES]] -> 0 | D85: =SUMIF(BOLIVARES[EMISOR],Tabla3[[#This Row],[CLIENTES]],BOLIVARES[DOLARES]) -> 0 | E85: =SUMIF(BOLIVARES[RECEPTOR],Tabla3[[#This Row],[CLIENTES]],BOLIVARES[DOLARES2]) -> 0 | F85: =SUMIF(Tabla12[EMISOR2],Tabla3[[#This Row],[CLIENTES]],Tabla12[MONTO]) -> 0 | G85: =SUMIF(Tabla12[RECEPTOR],Tabla3[[#This Row],[CLIENTES]],Tabla12[MONTO2]) -> 0 | H85: =SUMIF(CAMBIOS[SOLIICTANTES],Tabla3[[#This Row],[CLIENTES]],CAMBIOS[DIFERENCIA])+ SUMIF(CAMBIOS[SOLIICTANTES],Tabla3[[#This Row],[CLIENTES]],CAMBIOS[COSTOS DE ENVÍO]) -> 0 | I85: =Tabla14[[#This Row],[PENDIENTE]]+Tabla14[[#This Row],[VENTA]]+Tabla14[[#This Row],[RETIRO]]-Tabla14[[#This Row],[COMPRA]]-Tabla14[[#This Row],[PAGO]]+Tabla14[[#This Row],[COMISION]] -> 0
B86: =Tabla3[[#This Row],[CLIENTES]] -> 0 | D86: =SUMIF(BOLIVARES[EMISOR],Tabla3[[#This Row],[CLIENTES]],BOLIVARES[DOLARES]) -> 0 | E86: =SUMIF(BOLIVARES[RECEPTOR],Tabla3[[#This Row],[CLIENTES]],BOLIVARES[DOLARES2]) -> 0 | F86: =SUMIF(Tabla12[EMISOR2],Tabla3[[#This Row],[CLIENTES]],Tabla12[MONTO]) -> 0 | G86: =SUMIF(Tabla12[RECEPTOR],Tabla3[[#This Row],[CLIENTES]],Tabla12[MONTO2]) -> 0 | H86: =SUMIF(CAMBIOS[SOLIICTANTES],Tabla3[[#This Row],[CLIENTES]],CAMBIOS[DIFERENCIA])+ SUMIF(CAMBIOS[SOLIICTANTES],Tabla3[[#This Row],[CLIENTES]],CAMBIOS[COSTOS DE ENVÍO]) -> 0 | I86: =Tabla14[[#This Row],[PENDIENTE]]+Tabla14[[#This Row],[VENTA]]+Tabla14[[#This Row],[RETIRO]]-Tabla14[[#This Row],[COMPRA]]-Tabla14[[#This Row],[PAGO]]+Tabla14[[#This Row],[COMISION]] -> 0
B87: =Tabla3[[#This Row],[CLIENTES]] -> 0 | D87: =SUMIF(BOLIVARES[EMISOR],Tabla3[[#This Row],[CLIENTES]],BOLIVARES[DOLARES]) -> 0 | E87: =SUMIF(BOLIVARES[RECEPTOR],Tabla3[[#This Row],[CLIENTES]],BOLIVARES[DOLARES2]) -> 0 | F87: =SUMIF(Tabla12[EMISOR2],Tabla3[[#This Row],[CLIENTES]],Tabla12[MONTO]) -> 0 | G87: =SUMIF(Tabla12[RECEPTOR],Tabla3[[#This Row],[CLIENTES]],Tabla12[MONTO2]) -> 0 | H87: =SUMIF(CAMBIOS[SOLIICTANTES],Tabla3[[#This Row],[CLIENTES]],CAMBIOS[DIFERENCIA])+ SUMIF(CAMBIOS[SOLIICTANTES],Tabla3[[#This Row],[CLIENTES]],CAMBIOS[COSTOS DE ENVÍO]) -> 0 | I87: =Tabla14[[#This Row],[PENDIENTE]]+Tabla14[[#This Row],[VENTA]]+Tabla14[[#This Row],[RETIRO]]-Tabla14[[#This Row],[COMPRA]]-Tabla14[[#This Row],[PAGO]]+Tabla14[[#This Row],[COMISION]] -> 0
B88: =Tabla3[[#This Row],[CLIENTES]] -> 0 | D88: =SUMIF(BOLIVARES[EMISOR],Tabla3[[#This Row],[CLIENTES]],BOLIVARES[DOLARES]) -> 0 | E88: =SUMIF(BOLIVARES[RECEPTOR],Tabla3[[#This Row],[CLIENTES]],BOLIVARES[DOLARES2]) -> 0 | F88: =SUMIF(Tabla12[EMISOR2],Tabla3[[#This Row],[CLIENTES]],Tabla12[MONTO]) -> 0 | G88: =SUMIF(Tabla12[RECEPTOR],Tabla3[[#This Row],[CLIENTES]],Tabla12[MONTO2]) -> 0 | H88: =SUMIF(CAMBIOS[SOLIICTANTES],Tabla3[[#This Row],[CLIENTES]],CAMBIOS[DIFERENCIA])+ SUMIF(CAMBIOS[SOLIICTANTES],Tabla3[[#This Row],[CLIENTES]],CAMBIOS[COSTOS DE ENVÍO]) -> 0 | I88: =Tabla14[[#This Row],[PENDIENTE]]+Tabla14[[#This Row],[VENTA]]+Tabla14[[#This Row],[RETIRO]]-Tabla14[[#This Row],[COMPRA]]-Tabla14[[#This Row],[PAGO]]+Tabla14[[#This Row],[COMISION]] -> 0 | K88: GRUPO A
B89: =Tabla3[[#This Row],[CLIENTES]] -> 0 | D89: =SUMIF(BOLIVARES[EMISOR],Tabla3[[#This Row],[CLIENTES]],BOLIVARES[DOLARES]) -> 0 | E89: =SUMIF(BOLIVARES[RECEPTOR],Tabla3[[#This Row],[CLIENTES]],BOLIVARES[DOLARES2]) -> 0 | F89: =SUMIF(Tabla12[EMISOR2],Tabla3[[#This Row],[CLIENTES]],Tabla12[MONTO]) -> 0 | G89: =SUMIF(Tabla12[RECEPTOR],Tabla3[[#This Row],[CLIENTES]],Tabla12[MONTO2]) -> 0 | H89: =SUMIF(CAMBIOS[SOLIICTANTES],Tabla3[[#This Row],[CLIENTES]],CAMBIOS[DIFERENCIA])+ SUMIF(CAMBIOS[SOLIICTANTES],Tabla3[[#This Row],[CLIENTES]],CAMBIOS[COSTOS DE ENVÍO]) -> 0 | I89: =Tabla14[[#This Row],[PENDIENTE]]+Tabla14[[#This Row],[VENTA]]+Tabla14[[#This Row],[RETIRO]]-Tabla14[[#This Row],[COMPRA]]-Tabla14[[#This Row],[PAGO]]+Tabla14[[#This Row],[COMISION]] -> 0
B90: =Tabla3[[#This Row],[CLIENTES]] -> 0 | D90: =SUMIF(BOLIVARES[EMISOR],Tabla3[[#This Row],[CLIENTES]],BOLIVARES[DOLARES]) -> 0 | E90: =SUMIF(BOLIVARES[RECEPTOR],Tabla3[[#This Row],[CLIENTES]],BOLIVARES[DOLARES2]) -> 0 | F90: =SUMIF(Tabla12[EMISOR2],Tabla3[[#This Row],[CLIENTES]],Tabla12[MONTO]) -> 0 | G90: =SUMIF(Tabla12[RECEPTOR],Tabla3[[#This Row],[CLIENTES]],Tabla12[MONTO2]) -> 0 | H90: =SUMIF(CAMBIOS[SOLIICTANTES],Tabla3[[#This Row],[CLIENTES]],CAMBIOS[DIFERENCIA])+ SUMIF(CAMBIOS[SOLIICTANTES],Tabla3[[#This Row],[CLIENTES]],CAMBIOS[COSTOS DE ENVÍO]) -> 0 | I90: =Tabla14[[#This Row],[PENDIENTE]]+Tabla14[[#This Row],[VENTA]]+Tabla14[[#This Row],[RETIRO]]-Tabla14[[#This Row],[COMPRA]]-Tabla14[[#This Row],[PAGO]]+Tabla14[[#This Row],[COMISION]] -> 0
B91: =Tabla3[[#This Row],[CLIENTES]] -> 0 | D91: =SUMIF(BOLIVARES[EMISOR],Tabla3[[#This Row],[CLIENTES]],BOLIVARES[DOLARES]) -> 0 | E91: =SUMIF(BOLIVARES[RECEPTOR],Tabla3[[#This Row],[CLIENTES]],BOLIVARES[DOLARES2]) -> 0 | F91: =SUMIF(Tabla12[EMISOR2],Tabla3[[#This Row],[CLIENTES]],Tabla12[MONTO]) -> 0 | G91: =SUMIF(Tabla12[RECEPTOR],Tabla3[[#This Row],[CLIENTES]],Tabla12[MONTO2]) -> 0 | H91: =SUMIF(CAMBIOS[SOLIICTANTES],Tabla3[[#This Row],[CLIENTES]],CAMBIOS[DIFERENCIA])+ SUMIF(CAMBIOS[SOLIICTANTES],Tabla3[[#This Row],[CLIENTES]],CAMBIOS[COSTOS DE ENVÍO]) -> 0 | I91: =Tabla14[[#This Row],[PENDIENTE]]+Tabla14[[#This Row],[VENTA]]+Tabla14[[#This Row],[RETIRO]]-Tabla14[[#This Row],[COMPRA]]-Tabla14[[#This Row],[PAGO]]+Tabla14[[#This Row],[COMISION]] -> 0
B92: =Tabla3[[#This Row],[CLIENTES]] -> 0 | D92: =SUMIF(BOLIVARES[EMISOR],Tabla3[[#This Row],[CLIENTES]],BOLIVARES[DOLARES]) -> 0 | E92: =SUMIF(BOLIVARES[RECEPTOR],Tabla3[[#This Row],[CLIENTES]],BOLIVARES[DOLARES2]) -> 0 | F92: =SUMIF(Tabla12[EMISOR2],Tabla3[[#This Row],[CLIENTES]],Tabla12[MONTO]) -> 0 | G92: =SUMIF(Tabla12[RECEPTOR],Tabla3[[#This Row],[CLIENTES]],Tabla12[MONTO2]) -> 0 | H92: =SUMIF(CAMBIOS[SOLIICTANTES],Tabla3[[#This Row],[CLIENTES]],CAMBIOS[DIFERENCIA])+ SUMIF(CAMBIOS[SOLIICTANTES],Tabla3[[#This Row],[CLIENTES]],CAMBIOS[COSTOS DE ENVÍO]) -> 0 | I92: =Tabla14[[#This Row],[PENDIENTE]]+Tabla14[[#This Row],[VENTA]]+Tabla14[[#This Row],[RETIRO]]-Tabla14[[#This Row],[COMPRA]]-Tabla14[[#This Row],[PAGO]]+Tabla14[[#This Row],[COMISION]] -> 0
B93: =Tabla3[[#This Row],[CLIENTES]] -> 0 | D93: =SUMIF(BOLIVARES[EMISOR],Tabla3[[#This Row],[CLIENTES]],BOLIVARES[DOLARES]) -> 0 | E93: =SUMIF(BOLIVARES[RECEPTOR],Tabla3[[#This Row],[CLIENTES]],BOLIVARES[DOLARES2]) -> 0 | F93: =SUMIF(Tabla12[EMISOR2],Tabla3[[#This Row],[CLIENTES]],Tabla12[MONTO]) -> 0 | G93: =SUMIF(Tabla12[RECEPTOR],Tabla3[[#This Row],[CLIENTES]],Tabla12[MONTO2]) -> 0 | H93: =SUMIF(CAMBIOS[SOLIICTANTES],Tabla3[[#This Row],[CLIENTES]],CAMBIOS[DIFERENCIA])+ SUMIF(CAMBIOS[SOLIICTANTES],Tabla3[[#This Row],[CLIENTES]],CAMBIOS[COSTOS DE ENVÍO]) -> 0 | I93: =Tabla14[[#This Row],[PENDIENTE]]+Tabla14[[#This Row],[VENTA]]+Tabla14[[#This Row],[RETIRO]]-Tabla14[[#This Row],[COMPRA]]-Tabla14[[#This Row],[PAGO]]+Tabla14[[#This Row],[COMISION]] -> 0
B94: =Tabla3[[#This Row],[CLIENTES]] -> 0 | D94: =SUMIF(BOLIVARES[EMISOR],Tabla3[[#This Row],[CLIENTES]],BOLIVARES[DOLARES]) -> 0 | E94: =SUMIF(BOLIVARES[RECEPTOR],Tabla3[[#This Row],[CLIENTES]],BOLIVARES[DOLARES2]) -> 0 | F94: =SUMIF(Tabla12[EMISOR2],Tabla3[[#This Row],[CLIENTES]],Tabla12[MONTO]) -> 0 | G94: =SUMIF(Tabla12[RECEPTOR],Tabla3[[#This Row],[CLIENTES]],Tabla12[MONTO2]) -> 0 | H94: =SUMIF(CAMBIOS[SOLIICTANTES],Tabla3[[#This Row],[CLIENTES]],CAMBIOS[DIFERENCIA])+ SUMIF(CAMBIOS[SOLIICTANTES],Tabla3[[#This Row],[CLIENTES]],CAMBIOS[COSTOS DE ENVÍO]) -> 0 | I94: =Tabla14[[#This Row],[PENDIENTE]]+Tabla14[[#This Row],[VENTA]]+Tabla14[[#This Row],[RETIRO]]-Tabla14[[#This Row],[COMPRA]]-Tabla14[[#This Row],[PAGO]]+Tabla14[[#This Row],[COMISION]] -> 0
B95: =Tabla3[[#This Row],[CLIENTES]] -> 0 | D95: =SUMIF(BOLIVARES[EMISOR],Tabla3[[#This Row],[CLIENTES]],BOLIVARES[DOLARES]) -> 0 | E95: =SUMIF(BOLIVARES[RECEPTOR],Tabla3[[#This Row],[CLIENTES]],BOLIVARES[DOLARES2]) -> 0 | F95: =SUMIF(Tabla12[EMISOR2],Tabla3[[#This Row],[CLIENTES]],Tabla12[MONTO]) -> 0 | G95: =SUMIF(Tabla12[RECEPTOR],Tabla3[[#This Row],[CLIENTES]],Tabla12[MONTO2]) -> 0 | H95: =SUMIF(CAMBIOS[SOLIICTANTES],Tabla3[[#This Row],[CLIENTES]],CAMBIOS[DIFERENCIA])+ SUMIF(CAMBIOS[SOLIICTANTES],Tabla3[[#This Row],[CLIENTES]],CAMBIOS[COSTOS DE ENVÍO]) -> 0 | I95: =Tabla14[[#This Row],[PENDIENTE]]+Tabla14[[#This Row],[VENTA]]+Tabla14[[#This Row],[RETIRO]]-Tabla14[[#This Row],[COMPRA]]-Tabla14[[#This Row],[PAGO]]+Tabla14[[#This Row],[COMISION]] -> 0
B96: =Tabla3[[#This Row],[CLIENTES]] -> 0 | D96: =SUMIF(BOLIVARES[EMISOR],Tabla3[[#This Row],[CLIENTES]],BOLIVARES[DOLARES]) -> 0 | E96: =SUMIF(BOLIVARES[RECEPTOR],Tabla3[[#This Row],[CLIENTES]],BOLIVARES[DOLARES2]) -> 0 | F96: =SUMIF(Tabla12[EMISOR2],Tabla3[[#This Row],[CLIENTES]],Tabla12[MONTO]) -> 0 | G96: =SUMIF(Tabla12[RECEPTOR],Tabla3[[#This Row],[CLIENTES]],Tabla12[MONTO2]) -> 0 | H96: =SUMIF(CAMBIOS[SOLIICTANTES],Tabla3[[#This Row],[CLIENTES]],CAMBIOS[DIFERENCIA])+ SUMIF(CAMBIOS[SOLIICTANTES],Tabla3[[#This Row],[CLIENTES]],CAMBIOS[COSTOS DE ENVÍO]) -> 0 | I96: =Tabla14[[#This Row],[PENDIENTE]]+Tabla14[[#This Row],[VENTA]]+Tabla14[[#This Row],[RETIRO]]-Tabla14[[#This Row],[COMPRA]]-Tabla14[[#This Row],[PAGO]]+Tabla14[[#This Row],[COMISION]] -> 0
B97: =Tabla3[[#This Row],[CLIENTES]] -> 0 | D97: =SUMIF(BOLIVARES[EMISOR],Tabla3[[#This Row],[CLIENTES]],BOLIVARES[DOLARES]) -> 0 | E97: =SUMIF(BOLIVARES[RECEPTOR],Tabla3[[#This Row],[CLIENTES]],BOLIVARES[DOLARES2]) -> 0 | F97: =SUMIF(Tabla12[EMISOR2],Tabla3[[#This Row],[CLIENTES]],Tabla12[MONTO]) -> 0 | G97: =SUMIF(Tabla12[RECEPTOR],Tabla3[[#This Row],[CLIENTES]],Tabla12[MONTO2]) -> 0 | H97: =SUMIF(CAMBIOS[SOLIICTANTES],Tabla3[[#This Row],[CLIENTES]],CAMBIOS[DIFERENCIA])+ SUMIF(CAMBIOS[SOLIICTANTES],Tabla3[[#This Row],[CLIENTES]],CAMBIOS[COSTOS DE ENVÍO]) -> 0
B98: =Tabla3[[#This Row],[CLIENTES]] -> 0 | D98: =SUMIF(BOLIVARES[EMISOR],Tabla3[[#This Row],[CLIENTES]],BOLIVARES[DOLARES]) -> 0 | E98: =SUMIF(BOLIVARES[RECEPTOR],Tabla3[[#This Row],[CLIENTES]],BOLIVARES[DOLARES2]) -> 0 | F98: =SUMIF(Tabla12[EMISOR2],Tabla3[[#This Row],[CLIENTES]],Tabla12[MONTO]) -> 0 | G98: =SUMIF(Tabla12[RECEPTOR],Tabla3[[#This Row],[CLIENTES]],Tabla12[MONTO2]) -> 0 | H98: =SUMIF(CAMBIOS[SOLIICTANTES],Tabla3[[#This Row],[CLIENTES]],CAMBIOS[DIFERENCIA])+ SUMIF(CAMBIOS[SOLIICTANTES],Tabla3[[#This Row],[CLIENTES]],CAMBIOS[COSTOS DE ENVÍO]) -> 0 | I98: =Tabla14[[#This Row],[PENDIENTE]]+Tabla14[[#This Row],[VENTA]]+Tabla14[[#This Row],[RETIRO]]-Tabla14[[#This Row],[COMPRA]]-Tabla14[[#This Row],[PAGO]]+Tabla14[[#This Row],[COMISION]] -> 0
B99: =Tabla3[[#This Row],[CLIENTES]] -> 0 | D99: =SUMIF(BOLIVARES[EMISOR],Tabla3[[#This Row],[CLIENTES]],BOLIVARES[DOLARES]) -> 0 | E99: =SUMIF(BOLIVARES[RECEPTOR],Tabla3[[#This Row],[CLIENTES]],BOLIVARES[DOLARES2]) -> 0 | F99: =SUMIF(Tabla12[EMISOR2],Tabla3[[#This Row],[CLIENTES]],Tabla12[MONTO]) -> 0 | G99: =SUMIF(Tabla12[RECEPTOR],Tabla3[[#This Row],[CLIENTES]],Tabla12[MONTO2]) -> 0 | H99: =SUMIF(CAMBIOS[SOLIICTANTES],Tabla3[[#This Row],[CLIENTES]],CAMBIOS[DIFERENCIA])+ SUMIF(CAMBIOS[SOLIICTANTES],Tabla3[[#This Row],[CLIENTES]],CAMBIOS[COSTOS DE ENVÍO]) -> 0 | I99: =Tabla14[[#This Row],[PENDIENTE]]+Tabla14[[#This Row],[VENTA]]+Tabla14[[#This Row],[RETIRO]]-Tabla14[[#This Row],[COMPRA]]-Tabla14[[#This Row],[PAGO]]+Tabla14[[#This Row],[COMISION]] -> 0
B100: =Tabla3[[#This Row],[CLIENTES]] -> 0 | D100: =SUMIF(BOLIVARES[EMISOR],Tabla3[[#This Row],[CLIENTES]],BOLIVARES[DOLARES]) -> 0 | E100: =SUMIF(BOLIVARES[RECEPTOR],Tabla3[[#This Row],[CLIENTES]],BOLIVARES[DOLARES2]) -> 0 | F100: =SUMIF(Tabla12[EMISOR2],Tabla3[[#This Row],[CLIENTES]],Tabla12[MONTO]) -> 0 | G100: =SUMIF(Tabla12[RECEPTOR],Tabla3[[#This Row],[CLIENTES]],Tabla12[MONTO2]) -> 0 | H100: =SUMIF(CAMBIOS[SOLIICTANTES],Tabla3[[#This Row],[CLIENTES]],CAMBIOS[DIFERENCIA])+ SUMIF(CAMBIOS[SOLIICTANTES],Tabla3[[#This Row],[CLIENTES]],CAMBIOS[COSTOS DE ENVÍO]) -> 0 | I100: =Tabla14[[#This Row],[PENDIENTE]]+Tabla14[[#This Row],[VENTA]]+Tabla14[[#This Row],[RETIRO]]-Tabla14[[#This Row],[COMPRA]]-Tabla14[[#This Row],[PAGO]]+Tabla14[[#This Row],[COMISION]] -> 0
B101: =Tabla3[[#This Row],[CLIENTES]] -> 0 | D101: =SUMIF(BOLIVARES[EMISOR],Tabla3[[#This Row],[CLIENTES]],BOLIVARES[DOLARES]) -> 0 | E101: =SUMIF(BOLIVARES[RECEPTOR],Tabla3[[#This Row],[CLIENTES]],BOLIVARES[DOLARES2]) -> 0 | F101: =SUMIF(Tabla12[EMISOR2],Tabla3[[#This Row],[CLIENTES]],Tabla12[MONTO]) -> 0 | G101: =SUMIF(Tabla12[RECEPTOR],Tabla3[[#This Row],[CLIENTES]],Tabla12[MONTO2]) -> 0 | H101: =SUMIF(CAMBIOS[SOLIICTANTES],Tabla3[[#This Row],[CLIENTES]],CAMBIOS[DIFERENCIA])+ SUMIF(CAMBIOS[SOLIICTANTES],Tabla3[[#This Row],[CLIENTES]],CAMBIOS[COSTOS DE ENVÍO]) -> 0 | I101: =Tabla14[[#This Row],[PENDIENTE]]+Tabla14[[#This Row],[VENTA]]+Tabla14[[#This Row],[RETIRO]]-Tabla14[[#This Row],[COMPRA]]-Tabla14[[#This Row],[PAGO]]+Tabla14[[#This Row],[COMISION]] -> 0
B102: =Tabla3[[#This Row],[CLIENTES]] -> 0 | D102: =SUMIF(BOLIVARES[EMISOR],Tabla3[[#This Row],[CLIENTES]],BOLIVARES[DOLARES]) -> 0 | E102: =SUMIF(BOLIVARES[RECEPTOR],Tabla3[[#This Row],[CLIENTES]],BOLIVARES[DOLARES2]) -> 0 | F102: =SUMIF(Tabla12[EMISOR2],Tabla3[[#This Row],[CLIENTES]],Tabla12[MONTO]) -> 0 | G102: =SUMIF(Tabla12[RECEPTOR],Tabla3[[#This Row],[CLIENTES]],Tabla12[MONTO2]) -> 0 | H102: =SUMIF(CAMBIOS[SOLIICTANTES],Tabla3[[#This Row],[CLIENTES]],CAMBIOS[DIFERENCIA])+ SUMIF(CAMBIOS[SOLIICTANTES],Tabla3[[#This Row],[CLIENTES]],CAMBIOS[COSTOS DE ENVÍO]) -> 0 | I102: =Tabla14[[#This Row],[PENDIENTE]]+Tabla14[[#This Row],[VENTA]]+Tabla14[[#This Row],[RETIRO]]-Tabla14[[#This Row],[COMPRA]]-Tabla14[[#This Row],[PAGO]]+Tabla14[[#This Row],[COMISION]] -> 0
...

Sheet BANCOS
B2: BANCOS | C2: ACUMULADO | D2: INGRESO | E2: EGRESO | F2: SALDO | G2: DISPONIBLE | H2: DIFERENCIA | I2: OBSERVACION
B3: =Tabla4[[#This Row],[BANCOS]] -> BAN ALE | D3: =SUMIF(BOLIVARES[RECEPTOR],Tabla4[[#This Row],[BANCOS]],BOLIVARES[BOLIVARES1]) -> 0 | E3: =SUMIF(BOLIVARES[EMISOR],Tabla4[[#This Row],[BANCOS]],BOLIVARES[BOLIVARES1])+ SUMIF(BOLIVARES[EMISOR],Tabla4[[#This Row],[BANCOS]],BOLIVARES[COMISION]) -> 0 | F3: =Tabla16[[#This Row],[ACUMULADO]]+Tabla16[[#This Row],[INGRESO]]-Tabla16[[#This Row],[EGRESO]] -> 0 | H3: =Tabla16[[#This Row],[SALDO]]-Tabla16[[#This Row],[DISPONIBLE]] -> 0
B4: =Tabla4[[#This Row],[BANCOS]] -> BAN ANA K | C4: 600000 | D4: =SUMIF(BOLIVARES[RECEPTOR],Tabla4[[#This Row],[BANCOS]],BOLIVARES[BOLIVARES1]) -> 0 | E4: =SUMIF(BOLIVARES[EMISOR],Tabla4[[#This Row],[BANCOS]],BOLIVARES[BOLIVARES1])+ SUMIF(BOLIVARES[EMISOR],Tabla4[[#This Row],[BANCOS]],BOLIVARES[COMISION]) -> 0 | F4: =Tabla16[[#This Row],[ACUMULADO]]+Tabla16[[#This Row],[INGRESO]]-Tabla16[[#This Row],[EGRESO]] -> 600000 | H4: =Tabla16[[#This Row],[SALDO]]-Tabla16[[#This Row],[DISPONIBLE]] -> 600000
B5: =Tabla4[[#This Row],[BANCOS]] -> BAN BEA | C5: 422000 | D5: =SUMIF(BOLIVARES[RECEPTOR],Tabla4[[#This Row],[BANCOS]],BOLIVARES[BOLIVARES1]) -> 0 | E5: =SUMIF(BOLIVARES[EMISOR],Tabla4[[#This Row],[BANCOS]],BOLIVARES[BOLIVARES1])+ SUMIF(BOLIVARES[EMISOR],Tabla4[[#This Row],[BANCOS]],BOLIVARES[COMISION]) -> 0 | F5: =Tabla16[[#This Row],[ACUMULADO]]+Tabla16[[#This Row],[INGRESO]]-Tabla16[[#This Row],[EGRESO]] -> 422000 | H5: =Tabla16[[#This Row],[SALDO]]-Tabla16[[#This Row],[DISPONIBLE]] -> 422000
B6: =Tabla4[[#This Row],[BANCOS]] -> BAN BEL | D6: =SUMIF(BOLIVARES[RECEPTOR],Tabla4[[#This Row],[BANCOS]],BOLIVARES[BOLIVARES1]) -> 0 | E6: =SUMIF(BOLIVARES[EMISOR],Tabla4[[#This Row],[BANCOS]],BOLIVARES[BOLIVARES1])+ SUMIF(BOLIVARES[EMISOR],Tabla4[[#This Row],[BANCOS]],BOLIVARES[COMISION]) -> 0 | F6: =Tabla16[[#This Row],[ACUMULADO]]+Tabla16[[#This Row],[INGRESO]]-Tabla16[[#This Row],[EGRESO]] -> 0 | H6: =Tabla16[[#This Row],[SALDO]]-Tabla16[[#This Row],[DISPONIBLE]] -> 0
B7: =Tabla4[[#This Row],[BANCOS]] -> BAN EVE | C7: 20409.05 | D7: =SUMIF(BOLIVARES[RECEPTOR],Tabla4[[#This Row],[BANCOS]],BOLIVARES[BOLIVARES1]) -> 0 | E7: =SUMIF(BOLIVARES[EMISOR],Tabla4[[#This Row],[BANCOS]],BOLIVARES[BOLIVARES1])+ SUMIF(BOLIVARES[EMISOR],Tabla4[[#This Row],[BANCOS]],BOLIVARES[COMISION]) -> 0 | F7: =Tabla16[[#This Row],[ACUMULADO]]+Tabla16[[#This Row],[INGRESO]]-Tabla16[[#This Row],[EGRESO]] -> 20409.05 | H7: =Tabla16[[#This Row],[SALDO]]-Tabla16[[#This Row],[DISPONIBLE]] -> 20409.05
B8: =Tabla4[[#This Row],[BANCOS]] -> BAN JOH | C8: 92994.63 | D8: =SUMIF(BOLIVARES[RECEPTOR],Tabla4[[#This Row],[BANCOS]],BOLIVARES[BOLIVARES1]) -> 100000 | E8: =SUMIF(BOLIVARES[EMISOR],Tabla4[[#This Row],[BANCOS]],BOLIVARES[BOLIVARES1])+ SUMIF(BOLIVARES[EMISOR],Tabla4[[#This Row],[BANCOS]],BOLIVARES[COMISION]) -> 0 | F8: =Tabla16[[#This Row],[ACUMULADO]]+Tabla16[[#This Row],[INGRESO]]-Tabla16[[#This Row],[EGRESO]] -> 192994.63 | H8: =Tabla16[[#This Row],[SALDO]]-Tabla16[[#This Row],[DISPONIBLE]] -> 192994.63
B9: =Tabla4[[#This Row],[BANCOS]] -> BAN KAR | D9: =SUMIF(BOLIVARES[RECEPTOR],Tabla4[[#This Row],[BANCOS]],BOLIVARES[BOLIVARES1]) -> 0 | E9: =SUMIF(BOLIVARES[EMISOR],Tabla4[[#This Row],[BANCOS]],BOLIVARES[BOLIVARES1])+ SUMIF(BOLIVARES[EMISOR],Tabla4[[#This Row],[BANCOS]],BOLIVARES[COMISION]) -> 0 | F9: =Tabla16[[#This Row],[ACUMULADO]]+Tabla16[[#This Row],[INGRESO]]-Tabla16[[#This Row],[EGRESO]] -> 0 | H9: =Tabla16[[#This Row],[SALDO]]-Tabla16[[#This Row],[DISPONIBLE]] -> 0
B10: =Tabla4[[#This Row],[BANCOS]] -> BAN SAR | C10: 6900 | D10: =SUMIF(BOLIVARES[RECEPTOR],Tabla4[[#This Row],[BANCOS]],BOLIVARES[BOLIVARES1]) -> 0 | E10: =SUMIF(BOLIVARES[EMISOR],Tabla4[[#This Row],[BANCOS]],BOLIVARES[BOLIVARES1])+ SUMIF(BOLIVARES[EMISOR],Tabla4[[#This Row],[BANCOS]],BOLIVARES[COMISION]) -> 0 | F10: =Tabla16[[#This Row],[ACUMULADO]]+Tabla16[[#This Row],[INGRESO]]-Tabla16[[#This Row],[EGRESO]] -> 6900 | H10: =Tabla16[[#This Row],[SALDO]]-Tabla16[[#This Row],[DISPONIBLE]] -> 6900
B11: =Tabla4[[#This Row],[BANCOS]] -> MER SAR | D11: =SUMIF(BOLIVARES[RECEPTOR],Tabla4[[#This Row],[BANCOS]],BOLIVARES[BOLIVARES1]) -> 0 | E11: =SUMIF(BOLIVARES[EMISOR],Tabla4[[#This Row],[BANCOS]],BOLIVARES[BOLIVARES1])+ SUMIF(BOLIVARES[EMISOR],Tabla4[[#This Row],[BANCOS]],BOLIVARES[COMISION]) -> 0 | F11: =Tabla16[[#This Row],[ACUMULADO]]+Tabla16[[#This Row],[INGRESO]]-Tabla16[[#This Row],[EGRESO]] -> 0 | H11: =Tabla16[[#This Row],[SALDO]]-Tabla16[[#This Row],[DISPONIBLE]] -> 0
B12: =Tabla4[[#This Row],[BANCOS]] -> MERC BEL | C12: 22790.29 | D12: =SUMIF(BOLIVARES[RECEPTOR],Tabla4[[#This Row],[BANCOS]],BOLIVARES[BOLIVARES1]) -> 0 | E12: =SUMIF(BOLIVARES[EMISOR],Tabla4[[#This Row],[BANCOS]],BOLIVARES[BOLIVARES1])+ SUMIF(BOLIVARES[EMISOR],Tabla4[[#This Row],[BANCOS]],BOLIVARES[COMISION]) -> 0 | F12: =Tabla16[[#This Row],[ACUMULADO]]+Tabla16[[#This Row],[INGRESO]]-Tabla16[[#This Row],[EGRESO]] -> 22790.29 | H12: =Tabla16[[#This Row],[SALDO]]-Tabla16[[#This Row],[DISPONIBLE]] -> 22790.29
B13: =Tabla4[[#This Row],[BANCOS]] -> MERC EVE | C13: 142.73 | D13: =SUMIF(BOLIVARES[RECEPTOR],Tabla4[[#This Row],[BANCOS]],BOLIVARES[BOLIVARES1]) -> 0 | E13: =SUMIF(BOLIVARES[EMISOR],Tabla4[[#This Row],[BANCOS]],BOLIVARES[BOLIVARES1])+ SUMIF(BOLIVARES[EMISOR],Tabla4[[#This Row],[BANCOS]],BOLIVARES[COMISION]) -> 0 | F13: =Tabla16[[#This Row],[ACUMULADO]]+Tabla16[[#This Row],[INGRESO]]-Tabla16[[#This Row],[EGRESO]] -> 142.73 | H13: =Tabla16[[#This Row],[SALDO]]-Tabla16[[#This Row],[DISPONIBLE]] -> 142.73
B14: =Tabla4[[#This Row],[BANCOS]] -> MERC JOH | C14: 301640.47 | D14: =SUMIF(BOLIVARES[RECEPTOR],Tabla4[[#This Row],[BANCOS]],BOLIVARES[BOLIVARES1]) -> 0 | E14: =SUMIF(BOLIVARES[EMISOR],Tabla4[[#This Row],[BANCOS]],BOLIVARES[BOLIVARES1])+ SUMIF(BOLIVARES[EMISOR],Tabla4[[#This Row],[BANCOS]],BOLIVARES[COMISION]) -> 0 | F14: =Tabla16[[#This Row],[ACUMULADO]]+Tabla16[[#This Row],[INGRESO]]-Tabla16[[#This Row],[EGRESO]] -> 301640.47 | H14: =Tabla16[[#This Row],[SALDO]]-Tabla16[[#This Row],[DISPONIBLE]] -> 301640.47
B15: =Tabla4[[#This Row],[BANCOS]] -> MERC KAR | C15: 430600.64 | D15: =SUMIF(BOLIVARES[RECEPTOR],Tabla4[[#This Row],[BANCOS]],BOLIVARES[BOLIVARES1]) -> 0 | E15: =SUMIF(BOLIVARES[EMISOR],Tabla4[[#This Row],[BANCOS]],BOLIVARES[BOLIVARES1])+ SUMIF(BOLIVARES[EMISOR],Tabla4[[#This Row],[BANCOS]],BOLIVARES[COMISION]) -> 80000 | F15: =Tabla16[[#This Row],[ACUMULADO]]+Tabla16[[#This Row],[INGRESO]]-Tabla16[[#This Row],[EGRESO]] -> 350600.64 | H15: =Tabla16[[#This Row],[SALDO]]-Tabla16[[#This Row],[DISPONIBLE]] -> 350600.64
B16: =Tabla4[[#This Row],[BANCOS]] -> PROV EVE | C16: 4694.29 | D16: =SUMIF(BOLIVARES[RECEPTOR],Tabla4[[#This Row],[BANCOS]],BOLIVARES[BOLIVARES1]) -> 0 | E16: =SUMIF(BOLIVARES[EMISOR],Tabla4[[#This Row],[BANCOS]],BOLIVARES[BOLIVARES1])+ SUMIF(BOLIVARES[EMISOR],Tabla4[[#This Row],[BANCOS]],BOLIVARES[COMISION]) -> 0 | F16: =Tabla16[[#This Row],[ACUMULADO]]+Tabla16[[#This Row],[INGRESO]]-Tabla16[[#This Row],[EGRESO]] -> 4694.29 | H16: =Tabla16[[#This Row],[SALDO]]-Tabla16[[#This Row],[DISPONIBLE]] -> 4694.29
B17: =Tabla4[[#This Row],[BANCOS]] -> PROV JOH | D17: =SUMIF(BOLIVARES[RECEPTOR],Tabla4[[#This Row],[BANCOS]],BOLIVARES[BOLIVARES1]) -> 0 | E17: =SUMIF(BOLIVARES[EMISOR],Tabla4[[#This Row],[BANCOS]],BOLIVARES[BOLIVARES1])+ SUMIF(BOLIVARES[EMISOR],Tabla4[[#This Row],[BANCOS]],BOLIVARES[COMISION]) -> 0 | F17: =Tabla16[[#This Row],[ACUMULADO]]+Tabla16[[#This Row],[INGRESO]]-Tabla16[[#This Row],[EGRESO]] -> 0 | H17: =Tabla16[[#This Row],[SALDO]]-Tabla16[[#This Row],[DISPONIBLE]] -> 0
B18: =Tabla4[[#This Row],[BANCOS]] -> PROV KAR | D18: =SUMIF(BOLIVARES[RECEPTOR],Tabla4[[#This Row],[BANCOS]],BOLIVARES[BOLIVARES1]) -> 0 | E18: =SUMIF(BOLIVARES[EMISOR],Tabla4[[#This Row],[BANCOS]],BOLIVARES[BOLIVARES1])+ SUMIF(BOLIVARES[EMISOR],Tabla4[[#This Row],[BANCOS]],BOLIVARES[COMISION]) -> 0 | F18: =Tabla16[[#This Row],[ACUMULADO]]+Tabla16[[#This Row],[INGRESO]]-Tabla16[[#This Row],[EGRESO]] -> 0 | H18: =Tabla16[[#This Row],[SALDO]]-Tabla16[[#This Row],[DISPONIBLE]] -> 0
B19: =Tabla4[[#This Row],[BANCOS]] -> PROV SAR | C19: 202327.6 | D19: =SUMIF(BOLIVARES[RECEPTOR],Tabla4[[#This Row],[BANCOS]],BOLIVARES[BOLIVARES1]) -> 0 | E19: =SUMIF(BOLIVARES[EMISOR],Tabla4[[#This Row],[BANCOS]],BOLIVARES[BOLIVARES1])+ SUMIF(BOLIVARES[EMISOR],Tabla4[[#This Row],[BANCOS]],BOLIVARES[COMISION]) -> 0 | F19: =Tabla16[[#This Row],[ACUMULADO]]+Tabla16[[#This Row],[INGRESO]]-Tabla16[[#This Row],[EGRESO]] -> 202327.6 | H19: =Tabla16[[#This Row],[SALDO]]-Tabla16[[#This Row],[DISPONIBLE]] -> 202327.6
B20: =Tabla4[[#This Row],[BANCOS]] -> VZLA ALE | C20: 59475 | D20: =SUMIF(BOLIVARES[RECEPTOR],Tabla4[[#This Row],[BANCOS]],BOLIVARES[BOLIVARES1]) -> 0 | E20: =SUMIF(BOLIVARES[EMISOR],Tabla4[[#This Row],[BANCOS]],BOLIVARES[BOLIVARES1])+ SUMIF(BOLIVARES[EMISOR],Tabla4[[#This Row],[BANCOS]],BOLIVARES[COMISION]) -> 0 | F20: =Tabla16[[#This Row],[ACUMULADO]]+Tabla16[[#This Row],[INGRESO]]-Tabla16[[#This Row],[EGRESO]] -> 59475 | H20: =Tabla16[[#This Row],[SALDO]]-Tabla16[[#This Row],[DISPONIBLE]] -> 59475
B21: =Tabla4[[#This Row],[BANCOS]] -> VZLA ANA K | D21: =SUMIF(BOLIVARES[RECEPTOR],Tabla4[[#This Row],[BANCOS]],BOLIVARES[BOLIVARES1]) -> 0 | E21: =SUMIF(BOLIVARES[EMISOR],Tabla4[[#This Row],[BANCOS]],BOLIVARES[BOLIVARES1])+ SUMIF(BOLIVARES[EMISOR],Tabla4[[#This Row],[BANCOS]],BOLIVARES[COMISION]) -> 0 | F21: =Tabla16[[#This Row],[ACUMULADO]]+Tabla16[[#This Row],[INGRESO]]-Tabla16[[#This Row],[EGRESO]] -> 0 | H21: =Tabla16[[#This Row],[SALDO]]-Tabla16[[#This Row],[DISPONIBLE]] -> 0
B22: =Tabla4[[#This Row],[BANCOS]] -> VZLA EVE | C22: 562.25 | D22: =SUMIF(BOLIVARES[RECEPTOR],Tabla4[[#This Row],[BANCOS]],BOLIVARES[BOLIVARES1]) -> 0 | E22: =SUMIF(BOLIVARES[EMISOR],Tabla4[[#This Row],[BANCOS]],BOLIVARES[BOLIVARES1])+ SUMIF(BOLIVARES[EMISOR],Tabla4[[#This Row],[BANCOS]],BOLIVARES[COMISION]) -> 0 | F22: =Tabla16[[#This Row],[ACUMULADO]]+Tabla16[[#This Row],[INGRESO]]-Tabla16[[#This Row],[EGRESO]] -> 562.25 | H22: =Tabla16[[#This Row],[SALDO]]-Tabla16[[#This Row],[DISPONIBLE]] -> 562.25
B23: =Tabla4[[#This Row],[BANCOS]] -> VZLA JHAS | D23: =SUMIF(BOLIVARES[RECEPTOR],Tabla4[[#This Row],[BANCOS]],BOLIVARES[BOLIVARES1]) -> 0 | E23: =SUMIF(BOLIVARES[EMISOR],Tabla4[[#This Row],[BANCOS]],BOLIVARES[BOLIVARES1])+ SUMIF(BOLIVARES[EMISOR],Tabla4[[#This Row],[BANCOS]],BOLIVARES[COMISION]) -> 0 | F23: =Tabla16[[#This Row],[ACUMULADO]]+Tabla16[[#This Row],[INGRESO]]-Tabla16[[#This Row],[EGRESO]] -> 0 | H23: =Tabla16[[#This Row],[SALDO]]-Tabla16[[#This Row],[DISPONIBLE]] -> 0
B24: =Tabla4[[#This Row],[BANCOS]] -> VZLA JOHA | C24: 1806032.9 | D24: =SUMIF(BOLIVARES[RECEPTOR],Tabla4[[#This Row],[BANCOS]],BOLIVARES[BOLIVARES1]) -> 0 | E24: =SUMIF(BOLIVARES[EMISOR],Tabla4[[#This Row],[BANCOS]],BOLIVARES[BOLIVARES1])+ SUMIF(BOLIVARES[EMISOR],Tabla4[[#This Row],[BANCOS]],BOLIVARES[COMISION]) -> 50700 | F24: =Tabla16[[#This Row],[ACUMULADO]]+Tabla16[[#This Row],[INGRESO]]-Tabla16[[#This Row],[EGRESO]] -> 1755332.9 | G24: 1755332.9 | H24: =Tabla16[[#This Row],[SALDO]]-Tabla16[[#This Row],[DISPONIBLE]] -> 0
B25: =Tabla4[[#This Row],[BANCOS]] -> VZLA KAR | C25: 11888.11 | D25: =SUMIF(BOLIVARES[RECEPTOR],Tabla4[[#This Row],[BANCOS]],BOLIVARES[BOLIVARES1]) -> 0 | E25: =SUMIF(BOLIVARES[EMISOR],Tabla4[[#This Row],[BANCOS]],BOLIVARES[BOLIVARES1])+ SUMIF(BOLIVARES[EMISOR],Tabla4[[#This Row],[BANCOS]],BOLIVARES[COMISION]) -> 0 | F25: =Tabla16[[#This Row],[ACUMULADO]]+Tabla16[[#This Row],[INGRESO]]-Tabla16[[#This Row],[EGRESO]] -> 11888.11 | H25: =Tabla16[[#This Row],[SALDO]]-Tabla16[[#This Row],[DISPONIBLE]] -> 11888.11
B26: =Tabla4[[#This Row],[BANCOS]] -> VZLA SAR | D26: =SUMIF(BOLIVARES[RECEPTOR],Tabla4[[#This Row],[BANCOS]],BOLIVARES[BOLIVARES1]) -> 0 | E26: =SUMIF(BOLIVARES[EMISOR],Tabla4[[#This Row],[BANCOS]],BOLIVARES[BOLIVARES1])+ SUMIF(BOLIVARES[EMISOR],Tabla4[[#This Row],[BANCOS]],BOLIVARES[COMISION]) -> 0 | F26: =Tabla16[[#This Row],[ACUMULADO]]+Tabla16[[#This Row],[INGRESO]]-Tabla16[[#This Row],[EGRESO]] -> 0 | H26: =Tabla16[[#This Row],[SALDO]]-Tabla16[[#This Row],[DISPONIBLE]] -> 0
B27: =Tabla4[[#This Row],[BANCOS]] -> VZLA BEL | C27: 5054.19 | D27: =SUMIF(BOLIVARES[RECEPTOR],Tabla4[[#This Row],[BANCOS]],BOLIVARES[BOLIVARES1]) -> 0 | E27: =SUMIF(BOLIVARES[EMISOR],Tabla4[[#This Row],[BANCOS]],BOLIVARES[BOLIVARES1])+ SUMIF(BOLIVARES[EMISOR],Tabla4[[#This Row],[BANCOS]],BOLIVARES[COMISION]) -> 0 | F27: =Tabla16[[#This Row],[ACUMULADO]]+Tabla16[[#This Row],[INGRESO]]-Tabla16[[#This Row],[EGRESO]] -> 5054.19 | H27: =Tabla16[[#This Row],[SALDO]]-Tabla16[[#This Row],[DISPONIBLE]] -> 5054.19
B28: =Tabla4[[#This Row],[BANCOS]] -> BANCA KAR | C28: 648261.16 | D28: =SUMIF(BOLIVARES[RECEPTOR],Tabla4[[#This Row],[BANCOS]],BOLIVARES[BOLIVARES1]) -> 0 | E28: =SUMIF(BOLIVARES[EMISOR],Tabla4[[#This Row],[BANCOS]],BOLIVARES[BOLIVARES1])+ SUMIF(BOLIVARES[EMISOR],Tabla4[[#This Row],[BANCOS]],BOLIVARES[COMISION]) -> 0 | F28: =Tabla16[[#This Row],[ACUMULADO]]+Tabla16[[#This Row],[INGRESO]]-Tabla16[[#This Row],[EGRESO]] -> 648261.16 | H28: =Tabla16[[#This Row],[SALDO]]-Tabla16[[#This Row],[DISPONIBLE]] -> 648261.16
B29: =Tabla4[[#This Row],[BANCOS]] -> BANCA EVE | C29: 370415.76 | D29: =SUMIF(BOLIVARES[RECEPTOR],Tabla4[[#This Row],[BANCOS]],BOLIVARES[BOLIVARES1]) -> 0 | E29: =SUMIF(BOLIVARES[EMISOR],Tabla4[[#This Row],[BANCOS]],BOLIVARES[BOLIVARES1])+ SUMIF(BOLIVARES[EMISOR],Tabla4[[#This Row],[BANCOS]],BOLIVARES[COMISION]) -> 0 | F29: =Tabla16[[#This Row],[ACUMULADO]]+Tabla16[[#This Row],[INGRESO]]-Tabla16[[#This Row],[EGRESO]] -> 370415.76 | H29: =Tabla16[[#This Row],[SALDO]]-Tabla16[[#This Row],[DISPONIBLE]] -> 370415.76
B30: =Tabla4[[#This Row],[BANCOS]] -> BANCA MANUEL | C30: 265000 | D30: =SUMIF(BOLIVARES[RECEPTOR],Tabla4[[#This Row],[BANCOS]],BOLIVARES[BOLIVARES1]) -> 0 | E30: =SUMIF(BOLIVARES[EMISOR],Tabla4[[#This Row],[BANCOS]],BOLIVARES[BOLIVARES1])+ SUMIF(BOLIVARES[EMISOR],Tabla4[[#This Row],[BANCOS]],BOLIVARES[COMISION]) -> 0 | F30: =Tabla16[[#This Row],[ACUMULADO]]+Tabla16[[#This Row],[INGRESO]]-Tabla16[[#This Row],[EGRESO]] -> 265000 | H30: =Tabla16[[#This Row],[SALDO]]-Tabla16[[#This Row],[DISPONIBLE]] -> 265000
B31: =Tabla4[[#This Row],[BANCOS]] -> BANCARIBE EVE | C31: 421.56 | D31: =SUMIF(BOLIVARES[RECEPTOR],Tabla4[[#This Row],[BANCOS]],BOLIVARES[BOLIVARES1]) -> 0 | E31: =SUMIF(BOLIVARES[EMISOR],Tabla4[[#This Row],[BANCOS]],BOLIVARES[BOLIVARES1])+ SUMIF(BOLIVARES[EMISOR],Tabla4[[#This Row],[BANCOS]],BOLIVARES[COMISION]) -> 0 | F31: =Tabla16[[#This Row],[ACUMULADO]]+Tabla16[[#This Row],[INGRESO]]-Tabla16[[#This Row],[EGRESO]] -> 421.56 | H31: =Tabla16[[#This Row],[SALDO]]-Tabla16[[#This Row],[DISPONIBLE]] -> 421.56
C32: =SUM(Tabla16[ACUMULADO]) -> 5271610.6 | D32: =SUM(Tabla16[INGRESO]) -> 100000 | E32: =SUM(Tabla16[EGRESO]) -> 130700 | F32: =SUM(Tabla16[SALDO]) -> 5240910.6 | G32: -

Sheet PLATAFORMAS
B2: PLATAFORMAS | C2: ACUMULADO | D2: INGRESOS | E2: EGRESOS | F2: SALDO | G2: DISPONIBLE | H2: DIFERENCIA
B3: =Tabla10[[#This Row],[PLATAFORMAS]] -> CASH SARAH | D3: =SUMIF(Tabla12[RECEPTOR],Tabla10[[#This Row],[PLATAFORMAS]],Tabla12[MONTO2]) -> 0 | E3: =SUMIF(Tabla12[EMISOR2],Tabla10[[#This Row],[PLATAFORMAS]],Tabla12[MONTO]) -> 0 | H3: =Tabla17[[#This Row],[SALDO]]-Tabla17[[#This Row],[DISPONIBLE]] -> 0
B4: =Tabla10[[#This Row],[PLATAFORMAS]] -> CASH TINTORERIA | D4: =SUMIF(Tabla12[RECEPTOR],Tabla10[[#This Row],[PLATAFORMAS]],Tabla12[MONTO2]) -> 0 | E4: =SUMIF(Tabla12[EMISOR2],Tabla10[[#This Row],[PLATAFORMAS]],Tabla12[MONTO]) -> 0 | H4: =Tabla17[[#This Row],[SALDO]]-Tabla17[[#This Row],[DISPONIBLE]] -> 0
B5: =Tabla10[[#This Row],[PLATAFORMAS]] -> CASH YENSY | D5: =SUMIF(Tabla12[RECEPTOR],Tabla10[[#This Row],[PLATAFORMAS]],Tabla12[MONTO2]) -> 0 | E5: =SUMIF(Tabla12[EMISOR2],Tabla10[[#This Row],[PLATAFORMAS]],Tabla12[MONTO]) -> 0 | H5: =Tabla17[[#This Row],[SALDO]]-Tabla17[[#This Row],[DISPONIBLE]] -> 0
B6: =Tabla10[[#This Row],[PLATAFORMAS]] -> CASH GUILLERMO | D6: =SUMIF(Tabla12[RECEPTOR],Tabla10[[#This Row],[PLATAFORMAS]],Tabla12[MONTO2]) -> 0 | E6: =SUMIF(Tabla12[EMISOR2],Tabla10[[#This Row],[PLATAFORMAS]],Tabla12[MONTO]) -> 0 | H6: =Tabla17[[#This Row],[SALDO]]-Tabla17[[#This Row],[DISPONIBLE]] -> 0
B7: =Tabla10[[#This Row],[PLATAFORMAS]] -> ZELLE ITSIA | D7: =SUMIF(Tabla12[RECEPTOR],Tabla10[[#This Row],[PLATAFORMAS]],Tabla12[MONTO2]) -> 0 | E7: =SUMIF(Tabla12[EMISOR2],Tabla10[[#This Row],[PLATAFORMAS]],Tabla12[MONTO]) -> 0 | H7: =Tabla17[[#This Row],[SALDO]]-Tabla17[[#This Row],[DISPONIBLE]] -> 0
B8: =Tabla10[[#This Row],[PLATAFORMAS]] -> EUROS CASH SARAH | D8: =SUMIF(Tabla12[RECEPTOR],Tabla10[[#This Row],[PLATAFORMAS]],Tabla12[MONTO2]) -> 0 | E8: =SUMIF(Tabla12[EMISOR2],Tabla10[[#This Row],[PLATAFORMAS]],Tabla12[MONTO]) -> 0 | H8: =Tabla17[[#This Row],[SALDO]]-Tabla17[[#This Row],[DISPONIBLE]] -> 0
B9: =Tabla10[[#This Row],[PLATAFORMAS]] -> BNB SARAH | D9: =SUMIF(Tabla12[RECEPTOR],Tabla10[[#This Row],[PLATAFORMAS]],Tabla12[MONTO2]) -> 0 | E9: =SUMIF(Tabla12[EMISOR2],Tabla10[[#This Row],[PLATAFORMAS]],Tabla12[MONTO]) -> 0 | H9: =Tabla17[[#This Row],[SALDO]]-Tabla17[[#This Row],[DISPONIBLE]] -> 0
B10: =Tabla10[[#This Row],[PLATAFORMAS]] -> BANPA KAROL | D10: =SUMIF(Tabla12[RECEPTOR],Tabla10[[#This Row],[PLATAFORMAS]],Tabla12[MONTO2]) -> 0 | E10: =SUMIF(Tabla12[EMISOR2],Tabla10[[#This Row],[PLATAFORMAS]],Tabla12[MONTO]) -> 0 | H10: =Tabla17[[#This Row],[SALDO]]-Tabla17[[#This Row],[DISPONIBLE]] -> 0
B11: =Tabla10[[#This Row],[PLATAFORMAS]] -> MERCAPY KAROL | D11: =SUMIF(Tabla12[RECEPTOR],Tabla10[[#This Row],[PLATAFORMAS]],Tabla12[MONTO2]) -> 0 | E11: =SUMIF(Tabla12[EMISOR2],Tabla10[[#This Row],[PLATAFORMAS]],Tabla12[MONTO]) -> 0 | H11: =Tabla17[[#This Row],[SALDO]]-Tabla17[[#This Row],[DISPONIBLE]] -> 0
B12: =Tabla10[[#This Row],[PLATAFORMAS]] -> BNB KAROL | D12: =SUMIF(Tabla12[RECEPTOR],Tabla10[[#This Row],[PLATAFORMAS]],Tabla12[MONTO2]) -> 0 | E12: =SUMIF(Tabla12[EMISOR2],Tabla10[[#This Row],[PLATAFORMAS]],Tabla12[MONTO]) -> 0 | H12: =Tabla17[[#This Row],[SALDO]]-Tabla17[[#This Row],[DISPONIBLE]] -> 0
B13: =Tabla10[[#This Row],[PLATAFORMAS]] -> ZINLI KAROL | D13: =SUMIF(Tabla12[RECEPTOR],Tabla10[[#This Row],[PLATAFORMAS]],Tabla12[MONTO2]) -> 0 | E13: =SUMIF(Tabla12[EMISOR2],Tabla10[[#This Row],[PLATAFORMAS]],Tabla12[MONTO]) -> 0 | H13: =Tabla17[[#This Row],[SALDO]]-Tabla17[[#This Row],[DISPONIBLE]] -> 0
B14: =Tabla10[[#This Row],[PLATAFORMAS]] -> BANPA EVE | D14: =SUMIF(Tabla12[RECEPTOR],Tabla10[[#This Row],[PLATAFORMAS]],Tabla12[MONTO2]) -> 0 | E14: =SUMIF(Tabla12[EMISOR2],Tabla10[[#This Row],[PLATAFORMAS]],Tabla12[MONTO]) -> 0 | H14: =Tabla17[[#This Row],[SALDO]]-Tabla17[[#This Row],[DISPONIBLE]] -> 0
... B31: =Tabla10[[#This Row],[PLATAFORMAS]] -> BOFA IG | D31: =SUMIF(Tabla12[RECEPTOR],Tabla10[[#This Row],[PLATAFORMAS]],Tabla12[MONTO2]) -> 0 | E31: =SUMIF(Tabla12[EMISOR2],Tabla10[[#This Row],[PLATAFORMAS]],Tabla12[MONTO]) -> 0 | H31: =Tabla17[[#This Row],[SALDO]]-Tabla17[[#This Row],[DISPONIBLE]] -> 0
D32: =SUM(Tabla17[INGRESOS]) -> 0 | F32: =SUM(Tabla17[SALDO]) -> 0

Sheet LISTAS
B2: ORIGEN | D2: CLIENTES | F2: BANCOS | H2: MONEDAS | J2: DESTINO | L2: GASTOS | N2: PLATAFORMAS | P2: CAMBIOS
B3: BANCOS | D3: EVELIO RAMIREZ | F3: BAN ALE | H3: BS | J3: BANCOS | L3: AHORRO | N3: CASH SARAH | P3: EUR/USD
B4: CLIENTES | D4: JOHANA RODRIGUEZ | F4: BAN ANA K | H4: CASH | J4: CLIENTES | L4: ALQUILER KAROL | N4: CASH TINTORERIA | P4: USD/EUR
B5: PLATAFORMAS | D5: KAROL MALDONADO | F5: BAN BEA | H5: PANAMA | J5: GASTOS | L5: ALQUILER SARAH | N5: CASH YENSY | P5: PY/CASH
D6: SARAH ALVAREZ | F6: BAN BEL | H6: ZINLI | J6: PLATAFORMAS | L6: COMISION KAROL | N6: CASH GUILLERMO | P6: CASH/PY
F7: BAN EVE | H7: EUROS | L7: COMISION SARAH | N7: ZELLE ITSIA | P7: USDT/CASH
F8: BAN JOH | H8: USDT | L8: NOMINA KAROL | N8: EUROS CASH SARAH | P8: CASH/USDT
F9: BAN KAR | H9: BOFA | L9: NOMINA SARAH | N9: BNB SARAH | P9: ZELLE/CASH
F10: BAN SAR | H10: ZELLE | L10: NOMINA SERGIO | N10: BANPA KAROL | P10: USDT/EUR
F11: MER SAR | H11: FACEBANK | L11: NOMINA YENSI | N11: MERCAPY KAROL | P11: USDT/ZELLE
F12: MERC BEL | L12: OPERATIVOS | N12: BNB KAROL | P12: EUR/ZELLE
F13: MERC EVE | L13: OTROS | N13: ZINLI KAROL | P13: PRESTAMO
F14: MERC JOH | L14: PERDIDAS | N14: BANPA EVE | P14: ZINLI/CASH
F15: MERC KAR | L15: TRX | N15: MERCAPY EVE | P15: EUR/CASH
F16: PROV EVE | N16: BNB EVE
F17: PROV JOH | N17: ZINLI EVE
F18: PROV KAR | N18: TRUST WALLET I
F19: PROV SAR | N19: TRUST WALLET II
F20: VZLA ALE | N20: TRUST WALLET III
F21: VZLA ANA K | N21: TRUST WALLET IV
F22: VZLA EVE | N22: TRUST WALLET ETH
F23: VZLA JHAS | N23: BANPA BELKIS
F24: VZLA JOHA | N24: CASH BELKIS
F25: VZLA KAR | N25: EUR BELKIS
F26: VZLA SAR | N26: BANPA JOHA
F27: VZLA BEL | N27: BNB JOHA
... F31: BANCARIBE EVE | N31: BOFA IG

Sheet Hoja1
